Workbook

Sheet Dashboard
A1: Play Store PPP Pricing Template
A3: Base Price USD | B3: 1
A4: Global Min USD | B4: 0.49
A5: High PPP Floor USD | B5: 1.99
A6: Default Market Adj | B6: 1
A7: Default FX Source | B7: Manual / Google Sheets formula
A8: Last Updated | B8: 2026-05-01
A9: Notes | B9: Edit yellow cells only. Final price uses PPP + Market Adj + FX + rounding rules.
A10: Output Sheet | B10: PricingModel
A12: How to use | B12: 1) Set Base Price USD in B3 | C12: 2) Edit PPP/Market Adj/FX in PricingModel | D12: 3) Check Final Rounded Local Price | E12: 4) Enter prices manually in Play Console
A14: Tier | B14: PPP Range | C14: Strategy | D14: Typical Use
A15: A | B15: 0.80 - 1.00 | C15: Premium / near full price | D15: US, wealthier EU
A16: B | B16: 0.60 - 0.79 | C16: Slight discount | D16: Strong purchasing power
A17: C | B17: 0.40 - 0.59 | C17: Mid discount | D17: Balanced conversion/revenue
A18: D/E | B18: 0.10 - 0.39 | C18: Aggressive local price | D18: Volume markets

Sheet PricingModel
A1: 1. sütun | B1: Country | C1: Country Code | D1: Currency | E1: PPP Factor | F1: Tier | G1: Base USD | H1: PPP Price USD | I1: Market Adj | J1: FX USD→Local | K1: Raw Local Price | L1: Rounding Group | M1: Final Rounded Local | N1: Final USD Approx | O1: Recommended Action | P1: FX Formula for Google Sheets | Q1: Notes
A2: Arnavutluk | B2: Albania | C2: AL | D2: ALL | E2: 0.35 | F2: D | G2: =Dashboard!$B$3 -> 1 | H2: =MAX(Dashboard!$B$4,G2*E2) -> 0.49 | I2: 1 | J2: =IFERROR(__xludf.DUMMYFUNCTION("GOOGLEFINANCE(""CURRENCY:USDALL"")"),81.26480000000001) -> 81.2648 | K2: =H2*I2*J2 -> 39.819752 | L2: TRY_TIERS | M2: =IF(L2="TRY_TIERS",IF(K2<25,19,IF(K2<35,29,IF(K2<45,39,IF(K2<60,49,79)))), IF(L2="INR_TIERS",IF(K2<40,29,IF(K2<70,49,99)), IF(L2="BRL_90",IF(K2<3,2.9,IF(K2<6,4.9,IF(K2<10,6.9,9.9))), IF(L2="IDR_000",ROUND(K2/1000,0)*1000, IF(L2="JPY_00",ROUND(K2/100,0)*100, IF(L2="KRW_000",ROUND(K2/1000,0)*1000, IF(L2="VND_000",ROUND(K2/1000,0)*1000, IF(OR(L2="USD_99",L2="EUR_99",L2="GBP_99",L2="CAD_99",L2="AUD_99",L2="PLN_99"),MAX(0.49,ROUND(K2,0)-0.01), IF(L2="MXN_00",ROUND(K2,0),IF(L2="THB_00",ROUND(K2,0),ROUND(K2,2))))))))))) -> 39 | N2: =M2/J2 -> 0.47991258 | P2: =IFERROR(__xludf.DUMMYFUNCTION("GOOGLEFINANCE(""CURRENCY:USDALL"")"),81.26480000000001) -> 81.2648
A3: Cezayir | B3: Algeria | C3: DZ | D3: DZD | E3: 0.28 | F3: D | G3: =Dashboard!$B$3 -> 1 | H3: =MAX(Dashboard!$B$4,G3*E3) -> 0.49 | I3: 1 | J3: =IFERROR(__xludf.DUMMYFUNCTION("GOOGLEFINANCE(""CURRENCY:USDDZD"")"),132.3826) -> 132.3826 | K3: =H3*I3*J3 -> 64.867474 | L3: TRY_TIERS | M3: =IF(L3="TRY_TIERS",IF(K3<25,19,IF(K3<35,29,IF(K3<45,39,IF(K3<60,49,79)))), IF(L3="INR_TIERS",IF(K3<40,29,IF(K3<70,49,99)), IF(L3="BRL_90",IF(K3<3,2.9,IF(K3<6,4.9,IF(K3<10,6.9,9.9))), IF(L3="IDR_000",ROUND(K3/1000,0)*1000, IF(L3="JPY_00",ROUND(K3/100,0)*100, IF(L3="KRW_000",ROUND(K3/1000,0)*1000, IF(L3="VND_000",ROUND(K3/1000,0)*1000, IF(OR(L3="USD_99",L3="EUR_99",L3="GBP_99",L3="CAD_99",L3="AUD_99",L3="PLN_99"),MAX(0.49,ROUND(K3,0)-0.01), IF(L3="MXN_00",ROUND(K3,0),IF(L3="THB_00",ROUND(K3,0),ROUND(K3,2))))))))))) -> 79 | N3: =M3/J3 -> 0.59675516 | P3: =IFERROR(__xludf.DUMMYFUNCTION("GOOGLEFINANCE(""CURRENCY:USDDZD"")"),132.3826) -> 132.3826
A4: Angola | B4: Angola | C4: AO | D4: AOA | E4: 0.22 | F4: E | G4: =Dashboard!$B$3 -> 1 | H4: =MAX(Dashboard!$B$4,G4*E4) -> 0.49 | I4: 1 | J4: =IFERROR(__xludf.DUMMYFUNCTION("GOOGLEFINANCE(""CURRENCY:USDAOA"")"),918.0) -> 918 | K4: =H4*I4*J4 -> 449.82 | L4: THB_00 | M4: =IF(L4="TRY_TIERS",IF(K4<25,19,IF(K4<35,29,IF(K4<45,39,IF(K4<60,49,79)))), IF(L4="INR_TIERS",IF(K4<40,29,IF(K4<70,49,99)), IF(L4="BRL_90",IF(K4<3,2.9,IF(K4<6,4.9,IF(K4<10,6.9,9.9))), IF(L4="IDR_000",ROUND(K4/1000,0)*1000, IF(L4="JPY_00",ROUND(K4/100,0)*100, IF(L4="KRW_000",ROUND(K4/1000,0)*1000, IF(L4="VND_000",ROUND(K4/1000,0)*1000, IF(OR(L4="USD_99",L4="EUR_99",L4="GBP_99",L4="CAD_99",L4="AUD_99",L4="PLN_99"),MAX(0.49,ROUND(K4,0)-0.01), IF(L4="MXN_00",ROUND(K4,0),IF(L4="THB_00",ROUND(K4,0),ROUND(K4,2))))))))))) -> 450 | N4: =M4/J4 -> 0.49019608 | P4: =IFERROR(__xludf.DUMMYFUNCTION("GOOGLEFINANCE(""CURRENCY:USDAOA"")"),918.0) -> 918
A5: Antigua ve Barbuda | B5: Antigua and Barbuda | C5: AG | D5: XCD | E5: 0.65 | F5: B | G5: =Dashboard!$B$3 -> 1 | H5: =MAX(Dashboard!$B$4,G5*E5) -> 0.65 | I5: 1 | J5: =IFERROR(__xludf.DUMMYFUNCTION("GOOGLEFINANCE(""CURRENCY:USDXCD"")"),2.70255) -> 2.70255 | K5: =H5*I5*J5 -> 1.7566575 | L5: USD_99 | M5: =IF(L5="TRY_TIERS",IF(K5<25,19,IF(K5<35,29,IF(K5<45,39,IF(K5<60,49,79)))), IF(L5="INR_TIERS",IF(K5<40,29,IF(K5<70,49,99)), IF(L5="BRL_90",IF(K5<3,2.9,IF(K5<6,4.9,IF(K5<10,6.9,9.9))), IF(L5="IDR_000",ROUND(K5/1000,0)*1000, IF(L5="JPY_00",ROUND(K5/100,0)*100, IF(L5="KRW_000",ROUND(K5/1000,0)*1000, IF(L5="VND_000",ROUND(K5/1000,0)*1000, IF(OR(L5="USD_99",L5="EUR_99",L5="GBP_99",L5="CAD_99",L5="AUD_99",L5="PLN_99"),MAX(0.49,ROUND(K5,0)-0.01), IF(L5="MXN_00",ROUND(K5,0),IF(L5="THB_00",ROUND(K5,0),ROUND(K5,2))))))))))) -> 1.99 | N5: =M5/J5 -> 0.7363416 | P5: =IFERROR(__xludf.DUMMYFUNCTION("GOOGLEFINANCE(""CURRENCY:USDXCD"")"),2.70255) -> 2.70255
A6: Arjantin | B6: Argentina | C6: AR | D6: ARS | E6: 0.3 | F6: D | G6: =Dashboard!$B$3 -> 1 | H6: =MAX(Dashboard!$B$4,G6*E6) -> 0.49 | I6: 1 | J6: =IFERROR(__xludf.DUMMYFUNCTION("GOOGLEFINANCE(""CURRENCY:USDARS"")"),1385.0) -> 1385 | K6: =H6*I6*J6 -> 678.65 | L6: THB_00 | M6: =IF(L6="TRY_TIERS",IF(K6<25,19,IF(K6<35,29,IF(K6<45,39,IF(K6<60,49,79)))), IF(L6="INR_TIERS",IF(K6<40,29,IF(K6<70,49,99)), IF(L6="BRL_90",IF(K6<3,2.9,IF(K6<6,4.9,IF(K6<10,6.9,9.9))), IF(L6="IDR_000",ROUND(K6/1000,0)*1000, IF(L6="JPY_00",ROUND(K6/100,0)*100, IF(L6="KRW_000",ROUND(K6/1000,0)*1000, IF(L6="VND_000",ROUND(K6/1000,0)*1000, IF(OR(L6="USD_99",L6="EUR_99",L6="GBP_99",L6="CAD_99",L6="AUD_99",L6="PLN_99"),MAX(0.49,ROUND(K6,0)-0.01), IF(L6="MXN_00",ROUND(K6,0),IF(L6="THB_00",ROUND(K6,0),ROUND(K6,2))))))))))) -> 679 | N6: =M6/J6 -> 0.49025271 | P6: =IFERROR(__xludf.DUMMYFUNCTION("GOOGLEFINANCE(""CURRENCY:USDARS"")"),1385.0) -> 1385
A7: Ermenistan | B7: Armenia | C7: AM | D7: AMD | E7: 0.3 | F7: D | G7: =Dashboard!$B$3 -> 1 | H7: =MAX(Dashboard!$B$4,G7*E7) -> 0.49 | I7: 1 | J7: =IFERROR(__xludf.DUMMYFUNCTION("GOOGLEFINANCE(""CURRENCY:USDAMD"")"),368.0783) -> 368.0783 | K7: =H7*I7*J7 -> 180.35837 | L7: USD_99 | M7: =IF(L7="TRY_TIERS",IF(K7<25,19,IF(K7<35,29,IF(K7<45,39,IF(K7<60,49,79)))), IF(L7="INR_TIERS",IF(K7<40,29,IF(K7<70,49,99)), IF(L7="BRL_90",IF(K7<3,2.9,IF(K7<6,4.9,IF(K7<10,6.9,9.9))), IF(L7="IDR_000",ROUND(K7/1000,0)*1000, IF(L7="JPY_00",ROUND(K7/100,0)*100, IF(L7="KRW_000",ROUND(K7/1000,0)*1000, IF(L7="VND_000",ROUND(K7/1000,0)*1000, IF(OR(L7="USD_99",L7="EUR_99",L7="GBP_99",L7="CAD_99",L7="AUD_99",L7="PLN_99"),MAX(0.49,ROUND(K7,0)-0.01), IF(L7="MXN_00",ROUND(K7,0),IF(L7="THB_00",ROUND(K7,0),ROUND(K7,2))))))))))) -> 179.99 | N7: =M7/J7 -> 0.48899922 | P7: =IFERROR(__xludf.DUMMYFUNCTION("GOOGLEFINANCE(""CURRENCY:USDAMD"")"),368.0783) -> 368.0783
A8: Aruba | B8: Aruba | C8: AW | D8: AWG | E8: 0.75 | F8: B | G8: =Dashboard!$B$3 -> 1 | H8: =MAX(Dashboard!$B$4,G8*E8) -> 0.75 | I8: 1 | J8: =IFERROR(__xludf.DUMMYFUNCTION("GOOGLEFINANCE(""CURRENCY:USDAWG"")"),1.8025) -> 1.8025 | K8: =H8*I8*J8 -> 1.351875 | L8: PLN_99 | M8: =IF(L8="TRY_TIERS",IF(K8<25,19,IF(K8<35,29,IF(K8<45,39,IF(K8<60,49,79)))), IF(L8="INR_TIERS",IF(K8<40,29,IF(K8<70,49,99)), IF(L8="BRL_90",IF(K8<3,2.9,IF(K8<6,4.9,IF(K8<10,6.9,9.9))), IF(L8="IDR_000",ROUND(K8/1000,0)*1000, IF(L8="JPY_00",ROUND(K8/100,0)*100, IF(L8="KRW_000",ROUND(K8/1000,0)*1000, IF(L8="VND_000",ROUND(K8/1000,0)*1000, IF(OR(L8="USD_99",L8="EUR_99",L8="GBP_99",L8="CAD_99",L8="AUD_99",L8="PLN_99"),MAX(0.49,ROUND(K8,0)-0.01), IF(L8="MXN_00",ROUND(K8,0),IF(L8="THB_00",ROUND(K8,0),ROUND(K8,2))))))))))) -> 0.99 | N8: =M8/J8 -> 0.54923717 | P8: =IFERROR(__xludf.DUMMYFUNCTION("GOOGLEFINANCE(""CURRENCY:USDAWG"")"),1.8025) -> 1.8025
A9: Avustralya | B9: Australia | C9: AU | D9: AUD | E9: 0.82 | F9: =IF(E9>=0.8,"A",IF(E9>=0.6,"B",IF(E9>=0.4,"C",IF(E9>=0.2,"D","E")))) -> A | G9: =Dashboard!$B$3 -> 1 | H9: =MAX(Dashboard!$B$4,G9*E9) -> 0.82 | I9: 1 | J9: =IFERROR(__xludf.DUMMYFUNCTION("GOOGLEFINANCE(""CURRENCY:USDAUD"")"),1.381082) -> 1.381082 | K9: =H9*I9*J9 -> 1.1324872 | L9: AUD_99 | M9: =IF(L9="TRY_TIERS",IF(K9<25,19,IF(K9<35,29,IF(K9<45,39,IF(K9<60,49,79)))), IF(L9="INR_TIERS",IF(K9<40,29,IF(K9<70,49,99)), IF(L9="BRL_90",IF(K9<3,2.9,IF(K9<6,4.9,IF(K9<10,6.9,9.9))), IF(L9="IDR_000",ROUND(K9/1000,0)*1000, IF(L9="JPY_00",ROUND(K9/100,0)*100, IF(L9="KRW_000",ROUND(K9/1000,0)*1000, IF(L9="VND_000",ROUND(K9/1000,0)*1000, IF(OR(L9="USD_99",L9="EUR_99",L9="GBP_99",L9="CAD_99",L9="AUD_99",L9="PLN_99"),MAX(0.49,ROUND(K9,0)-0.01), IF(L9="MXN_00",ROUND(K9,0),IF(L9="THB_00",ROUND(K9,0),ROUND(K9,2))))))))))) -> 0.99 | N9: =M9/J9 -> 0.71682927 | O9: =IF(N9<Dashboard!$B$4,"Below global min",IF(AND(E9>=0.8,N9<Dashboard!$B$5),"Raise high-PPP floor","OK")) -> Raise high-PPP floor | P9: =IFERROR(__xludf.DUMMYFUNCTION("GOOGLEFINANCE(""CURRENCY:USDAUD"")"),1.381082) -> 1.381082
A10: Avusturya | B10: Austria | C10: AT | D10: EUR | E10: 0.86 | F10: A | G10: =Dashboard!$B$3 -> 1 | H10: =MAX(Dashboard!$B$4,G10*E10) -> 0.86 | I10: 1 | J10: =IFERROR(__xludf.DUMMYFUNCTION("GOOGLEFINANCE(""CURRENCY:USDEUR"")"),0.8519) -> 0.8519 | K10: =H10*I10*J10 -> 0.732634 | M10: =IF(L10="TRY_TIERS",IF(K10<25,19,IF(K10<35,29,IF(K10<45,39,IF(K10<60,49,79)))), IF(L10="INR_TIERS",IF(K10<40,29,IF(K10<70,49,99)), IF(L10="BRL_90",IF(K10<3,2.9,IF(K10<6,4.9,IF(K10<10,6.9,9.9))), IF(L10="IDR_000",ROUND(K10/1000,0)*1000, IF(L10="JPY_00",ROUND(K10/100,0)*100, IF(L10="KRW_000",ROUND(K10/1000,0)*1000, IF(L10="VND_000",ROUND(K10/1000,0)*1000, IF(OR(L10="USD_99",L10="EUR_99",L10="GBP_99",L10="CAD_99",L10="AUD_99",L10="PLN_99"),MAX(0.49,ROUND(K10,0)-0.01), IF(L10="MXN_00",ROUND(K10,0),IF(L10="THB_00",ROUND(K10,0),ROUND(K10,2))))))))))) -> 0.73 | N10: =M10/J10 -> 0.85690809 | P10: =IFERROR(__xludf.DUMMYFUNCTION("GOOGLEFINANCE(""CURRENCY:USDEUR"")"),0.8519) -> 0.8519
A11: Azerbaycan | B11: Azerbaijan | C11: AZ | D11: AZN | E11: 0.4 | F11: D | G11: =Dashboard!$B$3 -> 1 | H11: =MAX(Dashboard!$B$4,G11*E11) -> 0.49 | I11: 1 | J11: =IFERROR(__xludf.DUMMYFUNCTION("GOOGLEFINANCE(""CURRENCY:USDAZN"")"),1.7) -> 1.7 | K11: =H11*I11*J11 -> 0.833 | M11: =IF(L11="TRY_TIERS",IF(K11<25,19,IF(K11<35,29,IF(K11<45,39,IF(K11<60,49,79)))), IF(L11="INR_TIERS",IF(K11<40,29,IF(K11<70,49,99)), IF(L11="BRL_90",IF(K11<3,2.9,IF(K11<6,4.9,IF(K11<10,6.9,9.9))), IF(L11="IDR_000",ROUND(K11/1000,0)*1000, IF(L11="JPY_00",ROUND(K11/100,0)*100, IF(L11="KRW_000",ROUND(K11/1000,0)*1000, IF(L11="VND_000",ROUND(K11/1000,0)*1000, IF(OR(L11="USD_99",L11="EUR_99",L11="GBP_99",L11="CAD_99",L11="AUD_99",L11="PLN_99"),MAX(0.49,ROUND(K11,0)-0.01), IF(L11="MXN_00",ROUND(K11,0),IF(L11="THB_00",ROUND(K11,0),ROUND(K11,2))))))))))) -> 0.83 | N11: =M11/J11 -> 0.48823529 | P11: =IFERROR(__xludf.DUMMYFUNCTION("GOOGLEFINANCE(""CURRENCY:USDAZN"")"),1.7) -> 1.7
A12: Bahamalar | B12: Bahamas | C12: BS | D12: BSD | E12: 0.75 | F12: B | G12: =Dashboard!$B$3 -> 1 | H12: =MAX(Dashboard!$B$4,G12*E12) -> 0.75 | I12: 1 | J12: =IFERROR(__xludf.DUMMYFUNCTION("GOOGLEFINANCE(""CURRENCY:USDBSD"")"),1.000136) -> 1.000136 | K12: =H12*I12*J12 -> 0.750102 | M12: =IF(L12="TRY_TIERS",IF(K12<25,19,IF(K12<35,29,IF(K12<45,39,IF(K12<60,49,79)))), IF(L12="INR_TIERS",IF(K12<40,29,IF(K12<70,49,99)), IF(L12="BRL_90",IF(K12<3,2.9,IF(K12<6,4.9,IF(K12<10,6.9,9.9))), IF(L12="IDR_000",ROUND(K12/1000,0)*1000, IF(L12="JPY_00",ROUND(K12/100,0)*100, IF(L12="KRW_000",ROUND(K12/1000,0)*1000, IF(L12="VND_000",ROUND(K12/1000,0)*1000, IF(OR(L12="USD_99",L12="EUR_99",L12="GBP_99",L12="CAD_99",L12="AUD_99",L12="PLN_99"),MAX(0.49,ROUND(K12,0)-0.01), IF(L12="MXN_00",ROUND(K12,0),IF(L12="THB_00",ROUND(K12,0),ROUND(K12,2))))))))))) -> 0.75 | N12: =M12/J12 -> 0.74989801 | P12: =IFERROR(__xludf.DUMMYFUNCTION("GOOGLEFINANCE(""CURRENCY:USDBSD"")"),1.000136) -> 1.000136
A13: Bahreyn | B13: Bahrain | C13: BH | D13: BHD | E13: 0.85 | F13: A | G13: =Dashboard!$B$3 -> 1 | H13: =MAX(Dashboard!$B$4,G13*E13) -> 0.85 | I13: 1 | J13: =IFERROR(__xludf.DUMMYFUNCTION("GOOGLEFINANCE(""CURRENCY:USDBHD"")"),0.3774469) -> 0.3774469 | K13: =H13*I13*J13 -> 0.32082986 | M13: =IF(L13="TRY_TIERS",IF(K13<25,19,IF(K13<35,29,IF(K13<45,39,IF(K13<60,49,79)))), IF(L13="INR_TIERS",IF(K13<40,29,IF(K13<70,49,99)), IF(L13="BRL_90",IF(K13<3,2.9,IF(K13<6,4.9,IF(K13<10,6.9,9.9))), IF(L13="IDR_000",ROUND(K13/1000,0)*1000, IF(L13="JPY_00",ROUND(K13/100,0)*100, IF(L13="KRW_000",ROUND(K13/1000,0)*1000, IF(L13="VND_000",ROUND(K13/1000,0)*1000, IF(OR(L13="USD_99",L13="EUR_99",L13="GBP_99",L13="CAD_99",L13="AUD_99",L13="PLN_99"),MAX(0.49,ROUND(K13,0)-0.01), IF(L13="MXN_00",ROUND(K13,0),IF(L13="THB_00",ROUND(K13,0),ROUND(K13,2))))))))))) -> 0.32 | N13: =M13/J13 -> 0.84780137 | P13: =IFERROR(__xludf.DUMMYFUNCTION("GOOGLEFINANCE(""CURRENCY:USDBHD"")"),0.3774469) -> 0.3774469
A14: Bangladeş | B14: Bangladesh | C14: BD | D14: BDT | E14: 0.15 | F14: E | G14: =Dashboard!$B$3 -> 1 | H14: =MAX(Dashboard!$B$4,G14*E14) -> 0.49 | I14: 1 | J14: =IFERROR(__xludf.DUMMYFUNCTION("GOOGLEFINANCE(""CURRENCY:USDBDT"")"),122.9364) -> 122.9364 | K14: =H14*I14*J14 -> 60.238836 | M14: =IF(L14="TRY_TIERS",IF(K14<25,19,IF(K14<35,29,IF(K14<45,39,IF(K14<60,49,79)))), IF(L14="INR_TIERS",IF(K14<40,29,IF(K14<70,49,99)), IF(L14="BRL_90",IF(K14<3,2.9,IF(K14<6,4.9,IF(K14<10,6.9,9.9))), IF(L14="IDR_000",ROUND(K14/1000,0)*1000, IF(L14="JPY_00",ROUND(K14/100,0)*100, IF(L14="KRW_000",ROUND(K14/1000,0)*1000, IF(L14="VND_000",ROUND(K14/1000,0)*1000, IF(OR(L14="USD_99",L14="EUR_99",L14="GBP_99",L14="CAD_99",L14="AUD_99",L14="PLN_99"),MAX(0.49,ROUND(K14,0)-0.01), IF(L14="MXN_00",ROUND(K14,0),IF(L14="THB_00",ROUND(K14,0),ROUND(K14,2))))))))))) -> 60.24 | N14: =M14/J14 -> 0.49000947 | P14: =IFERROR(__xludf.DUMMYFUNCTION("GOOGLEFINANCE(""CURRENCY:USDBDT"")"),122.9364) -> 122.9364
A15: Belarus | B15: Belarus | C15: BY | D15: BYN | E15: 0.4 | F15: D | G15: =Dashboard!$B$3 -> 1 | H15: =MAX(Dashboard!$B$4,G15*E15) -> 0.49 | I15: 1 | J15: =IFERROR(__xludf.DUMMYFUNCTION("GOOGLEFINANCE(""CURRENCY:USDBYN"")"),2.7962249999999997) -> 2.796225 | K15: =H15*I15*J15 -> 1.3701503 | M15: =IF(L15="TRY_TIERS",IF(K15<25,19,IF(K15<35,29,IF(K15<45,39,IF(K15<60,49,79)))), IF(L15="INR_TIERS",IF(K15<40,29,IF(K15<70,49,99)), IF(L15="BRL_90",IF(K15<3,2.9,IF(K15<6,4.9,IF(K15<10,6.9,9.9))), IF(L15="IDR_000",ROUND(K15/1000,0)*1000, IF(L15="JPY_00",ROUND(K15/100,0)*100, IF(L15="KRW_000",ROUND(K15/1000,0)*1000, IF(L15="VND_000",ROUND(K15/1000,0)*1000, IF(OR(L15="USD_99",L15="EUR_99",L15="GBP_99",L15="CAD_99",L15="AUD_99",L15="PLN_99"),MAX(0.49,ROUND(K15,0)-0.01), IF(L15="MXN_00",ROUND(K15,0),IF(L15="THB_00",ROUND(K15,0),ROUND(K15,2))))))))))) -> 1.37 | N15: =M15/J15 -> 0.48994627 | P15: =IFERROR(__xludf.DUMMYFUNCTION("GOOGLEFINANCE(""CURRENCY:USDBYN"")"),2.7962249999999997) -> 2.796225
A16: Belçika | B16: Belgium | C16: BE | D16: EUR | E16: 0.84 | F16: A | G16: =Dashboard!$B$3 -> 1 | H16: =MAX(Dashboard!$B$4,G16*E16) -> 0.84 | I16: 1 | J16: =IFERROR(__xludf.DUMMYFUNCTION("GOOGLEFINANCE(""CURRENCY:USDEUR"")"),0.8519) -> 0.8519 | K16: =H16*I16*J16 -> 0.715596 | M16: =IF(L16="TRY_TIERS",IF(K16<25,19,IF(K16<35,29,IF(K16<45,39,IF(K16<60,49,79)))), IF(L16="INR_TIERS",IF(K16<40,29,IF(K16<70,49,99)), IF(L16="BRL_90",IF(K16<3,2.9,IF(K16<6,4.9,IF(K16<10,6.9,9.9))), IF(L16="IDR_000",ROUND(K16/1000,0)*1000, IF(L16="JPY_00",ROUND(K16/100,0)*100, IF(L16="KRW_000",ROUND(K16/1000,0)*1000, IF(L16="VND_000",ROUND(K16/1000,0)*1000, IF(OR(L16="USD_99",L16="EUR_99",L16="GBP_99",L16="CAD_99",L16="AUD_99",L16="PLN_99"),MAX(0.49,ROUND(K16,0)-0.01), IF(L16="MXN_00",ROUND(K16,0),IF(L16="THB_00",ROUND(K16,0),ROUND(K16,2))))))))))) -> 0.72 | N16: =M16/J16 -> 0.84516962 | P16: =IFERROR(__xludf.DUMMYFUNCTION("GOOGLEFINANCE(""CURRENCY:USDEUR"")"),0.8519) -> 0.8519
A17: Belize | B17: Belize | C17: BZ | D17: BZD | E17: 0.35 | F17: D | G17: =Dashboard!$B$3 -> 1 | H17: =MAX(Dashboard!$B$4,G17*E17) -> 0.49 | I17: 1 | J17: =IFERROR(__xludf.DUMMYFUNCTION("GOOGLEFINANCE(""CURRENCY:USDBZD"")"),2.011432) -> 2.011432 | K17: =H17*I17*J17 -> 0.98560168 | M17: =IF(L17="TRY_TIERS",IF(K17<25,19,IF(K17<35,29,IF(K17<45,39,IF(K17<60,49,79)))), IF(L17="INR_TIERS",IF(K17<40,29,IF(K17<70,49,99)), IF(L17="BRL_90",IF(K17<3,2.9,IF(K17<6,4.9,IF(K17<10,6.9,9.9))), IF(L17="IDR_000",ROUND(K17/1000,0)*1000, IF(L17="JPY_00",ROUND(K17/100,0)*100, IF(L17="KRW_000",ROUND(K17/1000,0)*1000, IF(L17="VND_000",ROUND(K17/1000,0)*1000, IF(OR(L17="USD_99",L17="EUR_99",L17="GBP_99",L17="CAD_99",L17="AUD_99",L17="PLN_99"),MAX(0.49,ROUND(K17,0)-0.01), IF(L17="MXN_00",ROUND(K17,0),IF(L17="THB_00",ROUND(K17,0),ROUND(K17,2))))))))))) -> 0.99 | N17: =M17/J17 -> 0.49218666 | P17: =IFERROR(__xludf.DUMMYFUNCTION("GOOGLEFINANCE(""CURRENCY:USDBZD"")"),2.011432) -> 2.011432
A18: Benin | B18: Benin | C18: BJ | D18: XOF | E18: 0.18 | F18: E | G18: =Dashboard!$B$3 -> 1 | H18: =MAX(Dashboard!$B$4,G18*E18) -> 0.49 | I18: 1 | J18: =IFERROR(__xludf.DUMMYFUNCTION("GOOGLEFINANCE(""CURRENCY:USDXOF"")"),558.7654) -> 558.7654 | K18: =H18*I18*J18 -> 273.79505 | M18: =IF(L18="TRY_TIERS",IF(K18<25,19,IF(K18<35,29,IF(K18<45,39,IF(K18<60,49,79)))), IF(L18="INR_TIERS",IF(K18<40,29,IF(K18<70,49,99)), IF(L18="BRL_90",IF(K18<3,2.9,IF(K18<6,4.9,IF(K18<10,6.9,9.9))), IF(L18="IDR_000",ROUND(K18/1000,0)*1000, IF(L18="JPY_00",ROUND(K18/100,0)*100, IF(L18="KRW_000",ROUND(K18/1000,0)*1000, IF(L18="VND_000",ROUND(K18/1000,0)*1000, IF(OR(L18="USD_99",L18="EUR_99",L18="GBP_99",L18="CAD_99",L18="AUD_99",L18="PLN_99"),MAX(0.49,ROUND(K18,0)-0.01), IF(L18="MXN_00",ROUND(K18,0),IF(L18="THB_00",ROUND(K18,0),ROUND(K18,2))))))))))) -> 273.8 | N18: =M18/J18 -> 0.49000887 | P18: =IFERROR(__xludf.DUMMYFUNCTION("GOOGLEFINANCE(""CURRENCY:USDXOF"")"),558.7654) -> 558.7654
A19: Bermuda | B19: Bermuda | C19: BM | D19: BMD | E19: 1 | F19: A | G19: =Dashboard!$B$3 -> 1 | H19: =MAX(Dashboard!$B$4,G19*E19) -> 1 | I19: 1 | J19: =IFERROR(__xludf.DUMMYFUNCTION("GOOGLEFINANCE(""CURRENCY:USDBMD"")"),1.0) -> 1 | K19: =H19*I19*J19 -> 1 | M19: =IF(L19="TRY_TIERS",IF(K19<25,19,IF(K19<35,29,IF(K19<45,39,IF(K19<60,49,79)))), IF(L19="INR_TIERS",IF(K19<40,29,IF(K19<70,49,99)), IF(L19="BRL_90",IF(K19<3,2.9,IF(K19<6,4.9,IF(K19<10,6.9,9.9))), IF(L19="IDR_000",ROUND(K19/1000,0)*1000, IF(L19="JPY_00",ROUND(K19/100,0)*100, IF(L19="KRW_000",ROUND(K19/1000,0)*1000, IF(L19="VND_000",ROUND(K19/1000,0)*1000, IF(OR(L19="USD_99",L19="EUR_99",L19="GBP_99",L19="CAD_99",L19="AUD_99",L19="PLN_99"),MAX(0.49,ROUND(K19,0)-0.01), IF(L19="MXN_00",ROUND(K19,0),IF(L19="THB_00",ROUND(K19,0),ROUND(K19,2))))))))))) -> 1 | N19: =M19/J19 -> 1 | P19: =IFERROR(__xludf.DUMMYFUNCTION("GOOGLEFINANCE(""CURRENCY:USDBMD"")"),1.0) -> 1
A20: Bolivya | B20: Bolivia | C20: BO | D20: BOB-BOV | E20: 0.3 | F20: D | G20: =Dashboard!$B$3 -> 1 | H20: =MAX(Dashboard!$B$4,G20*E20) -> 0.49 | I20: 1 | J20: =IFERROR(__xludf.DUMMYFUNCTION("GOOGLEFINANCE(""CURRENCY:USDBOB"")"),6.910945) -> 6.910945 | K20: =H20*I20*J20 -> 3.386363 | M20: =IF(L20="TRY_TIERS",IF(K20<25,19,IF(K20<35,29,IF(K20<45,39,IF(K20<60,49,79)))), IF(L20="INR_TIERS",IF(K20<40,29,IF(K20<70,49,99)), IF(L20="BRL_90",IF(K20<3,2.9,IF(K20<6,4.9,IF(K20<10,6.9,9.9))), IF(L20="IDR_000",ROUND(K20/1000,0)*1000, IF(L20="JPY_00",ROUND(K20/100,0)*100, IF(L20="KRW_000",ROUND(K20/1000,0)*1000, IF(L20="VND_000",ROUND(K20/1000,0)*1000, IF(OR(L20="USD_99",L20="EUR_99",L20="GBP_99",L20="CAD_99",L20="AUD_99",L20="PLN_99"),MAX(0.49,ROUND(K20,0)-0.01), IF(L20="MXN_00",ROUND(K20,0),IF(L20="THB_00",ROUND(K20,0),ROUND(K20,2))))))))))) -> 3.39 | N20: =M20/J20 -> 0.49052626 | P20: =IFERROR(__xludf.DUMMYFUNCTION("GOOGLEFINANCE(""CURRENCY:USDBOB"")"),6.910945) -> 6.910945
A21: Bosna-Hersek | B21: Bosnia and Herzegovina | C21: BA | D21: BAM | E21: 0.45 | F21: C | G21: =Dashboard!$B$3 -> 1 | H21: =MAX(Dashboard!$B$4,G21*E21) -> 0.49 | I21: 1 | J21: =IFERROR(__xludf.DUMMYFUNCTION("GOOGLEFINANCE(""CURRENCY:USDBAM"")"),1.6660139999999999) -> 1.666014 | K21: =H21*I21*J21 -> 0.81634686 | M21: =IF(L21="TRY_TIERS",IF(K21<25,19,IF(K21<35,29,IF(K21<45,39,IF(K21<60,49,79)))), IF(L21="INR_TIERS",IF(K21<40,29,IF(K21<70,49,99)), IF(L21="BRL_90",IF(K21<3,2.9,IF(K21<6,4.9,IF(K21<10,6.9,9.9))), IF(L21="IDR_000",ROUND(K21/1000,0)*1000, IF(L21="JPY_00",ROUND(K21/100,0)*100, IF(L21="KRW_000",ROUND(K21/1000,0)*1000, IF(L21="VND_000",ROUND(K21/1000,0)*1000, IF(OR(L21="USD_99",L21="EUR_99",L21="GBP_99",L21="CAD_99",L21="AUD_99",L21="PLN_99"),MAX(0.49,ROUND(K21,0)-0.01), IF(L21="MXN_00",ROUND(K21,0),IF(L21="THB_00",ROUND(K21,0),ROUND(K21,2))))))))))) -> 0.82 | N21: =M21/J21 -> 0.49219274 | P21: =IFERROR(__xludf.DUMMYFUNCTION("GOOGLEFINANCE(""CURRENCY:USDBAM"")"),1.6660139999999999) -> 1.666014
A22: Botsvana | B22: Botswana | C22: BW | D22: BWP | E22: 0.4 | F22: D | G22: =Dashboard!$B$3 -> 1 | H22: =MAX(Dashboard!$B$4,G22*E22) -> 0.49 | I22: 1 | J22: =IFERROR(__xludf.DUMMYFUNCTION("GOOGLEFINANCE(""CURRENCY:USDBWP"")"),13.49984) -> 13.49984 | K22: =H22*I22*J22 -> 6.6149216 | M22: =IF(L22="TRY_TIERS",IF(K22<25,19,IF(K22<35,29,IF(K22<45,39,IF(K22<60,49,79)))), IF(L22="INR_TIERS",IF(K22<40,29,IF(K22<70,49,99)), IF(L22="BRL_90",IF(K22<3,2.9,IF(K22<6,4.9,IF(K22<10,6.9,9.9))), IF(L22="IDR_000",ROUND(K22/1000,0)*1000, IF(L22="JPY_00",ROUND(K22/100,0)*100, IF(L22="KRW_000",ROUND(K22/1000,0)*1000, IF(L22="VND_000",ROUND(K22/1000,0)*1000, IF(OR(L22="USD_99",L22="EUR_99",L22="GBP_99",L22="CAD_99",L22="AUD_99",L22="PLN_99"),MAX(0.49,ROUND(K22,0)-0.01), IF(L22="MXN_00",ROUND(K22,0),IF(L22="THB_00",ROUND(K22,0),ROUND(K22,2))))))))))) -> 6.61 | N22: =M22/J22 -> 0.48963543 | P22: =IFERROR(__xludf.DUMMYFUNCTION("GOOGLEFINANCE(""CURRENCY:USDBWP"")"),13.49984) -> 13.49984
A23: Brezilya | B23: Brazil | C23: BR | D23: BRL | E23: 0.35 | F23: =IF(E23>=0.8,"A",IF(E23>=0.6,"B",IF(E23>=0.4,"C",IF(E23>=0.2,"D","E")))) -> D | G23: =Dashboard!$B$3 -> 1 | H23: =MAX(Dashboard!$B$4,G23*E23) -> 0.49 | I23: 0.85 | J23: =IFERROR(__xludf.DUMMYFUNCTION("GOOGLEFINANCE(""CURRENCY:USDBRL"")"),4.9113) -> 4.9113 | K23: =H23*I23*J23 -> 2.0455564 | L23: BRL_90 | M23: =IF(L23="TRY_TIERS",IF(K23<25,19,IF(K23<35,29,IF(K23<45,39,IF(K23<60,49,79)))), IF(L23="INR_TIERS",IF(K23<40,29,IF(K23<70,49,99)), IF(L23="BRL_90",IF(K23<3,2.9,IF(K23<6,4.9,IF(K23<10,6.9,9.9))), IF(L23="IDR_000",ROUND(K23/1000,0)*1000, IF(L23="JPY_00",ROUND(K23/100,0)*100, IF(L23="KRW_000",ROUND(K23/1000,0)*1000, IF(L23="VND_000",ROUND(K23/1000,0)*1000, IF(OR(L23="USD_99",L23="EUR_99",L23="GBP_99",L23="CAD_99",L23="AUD_99",L23="PLN_99"),MAX(0.49,ROUND(K23,0)-0.01), IF(L23="MXN_00",ROUND(K23,0),IF(L23="THB_00",ROUND(K23,0),ROUND(K23,2))))))))))) -> 2.9 | N23: =M23/J23 -> 0.59047503 | O23: =IF(N23<Dashboard!$B$4,"Below global min",IF(AND(E23>=0.8,N23<Dashboard!$B$5),"Raise high-PPP floor","OK")) -> OK | P23: =IFERROR(__xludf.DUMMYFUNCTION("GOOGLEFINANCE(""CURRENCY:USDBRL"")"),4.9113) -> 4.9113
A24: Bulgaristan | B24: Bulgaria | C24: BG | D24: BGN | E24: 0.4 | F24: D | G24: =Dashboard!$B$3 -> 1 | H24: =MAX(Dashboard!$B$4,G24*E24) -> 0.49 | I24: 1 | J24: =IFERROR(__xludf.DUMMYFUNCTION("GOOGLEFINANCE(""CURRENCY:USDBGN"")"),"#N/A") -> #N/A | K24: =H24*I24*J24 -> #N/A | M24: =IF(L24="TRY_TIERS",IF(K24<25,19,IF(K24<35,29,IF(K24<45,39,IF(K24<60,49,79)))), IF(L24="INR_TIERS",IF(K24<40,29,IF(K24<70,49,99)), IF(L24="BRL_90",IF(K24<3,2.9,IF(K24<6,4.9,IF(K24<10,6.9,9.9))), IF(L24="IDR_000",ROUND(K24/1000,0)*1000, IF(L24="JPY_00",ROUND(K24/100,0)*100, IF(L24="KRW_000",ROUND(K24/1000,0)*1000, IF(L24="VND_000",ROUND(K24/1000,0)*1000, IF(OR(L24="USD_99",L24="EUR_99",L24="GBP_99",L24="CAD_99",L24="AUD_99",L24="PLN_99"),MAX(0.49,ROUND(K24,0)-0.01), IF(L24="MXN_00",ROUND(K24,0),IF(L24="THB_00",ROUND(K24,0),ROUND(K24,2))))))))))) -> #N/A | N24: =M24/J24 -> #N/A | P24: =IFERROR(__xludf.DUMMYFUNCTION("GOOGLEFINANCE(""CURRENCY:USDBGN"")"),"#N/A") -> #N/A
A25: Burkina Faso | B25: Burkina Faso | C25: BF | D25: XOF | E25: 0.18 | F25: E | G25: =Dashboard!$B$3 -> 1 | H25: =MAX(Dashboard!$B$4,G25*E25) -> 0.49 | I25: 1 | J25: =IFERROR(__xludf.DUMMYFUNCTION("GOOGLEFINANCE(""CURRENCY:USDXOF"")"),558.7654) -> 558.7654 | K25: =H25*I25*J25 -> 273.79505 | M25: =IF(L25="TRY_TIERS",IF(K25<25,19,IF(K25<35,29,IF(K25<45,39,IF(K25<60,49,79)))), IF(L25="INR_TIERS",IF(K25<40,29,IF(K25<70,49,99)), IF(L25="BRL_90",IF(K25<3,2.9,IF(K25<6,4.9,IF(K25<10,6.9,9.9))), IF(L25="IDR_000",ROUND(K25/1000,0)*1000, IF(L25="JPY_00",ROUND(K25/100,0)*100, IF(L25="KRW_000",ROUND(K25/1000,0)*1000, IF(L25="VND_000",ROUND(K25/1000,0)*1000, IF(OR(L25="USD_99",L25="EUR_99",L25="GBP_99",L25="CAD_99",L25="AUD_99",L25="PLN_99"),MAX(0.49,ROUND(K25,0)-0.01), IF(L25="MXN_00",ROUND(K25,0),IF(L25="THB_00",ROUND(K25,0),ROUND(K25,2))))))))))) -> 273.8 | N25: =M25/J25 -> 0.49000887 | P25: =IFERROR(__xludf.DUMMYFUNCTION("GOOGLEFINANCE(""CURRENCY:USDXOF"")"),558.7654) -> 558.7654
A26: Cabo Verde | B26: Cabo Verde | C26: CV | D26: CVE | E26: 0.3 | F26: D | G26: =Dashboard!$B$3 -> 1 | H26: =MAX(Dashboard!$B$4,G26*E26) -> 0.49 | I26: 1 | J26: =IFERROR(__xludf.DUMMYFUNCTION("GOOGLEFINANCE(""CURRENCY:USDCVE"")"),93.92769000000001) -> 93.92769 | K26: =H26*I26*J26 -> 46.024568 | M26: =IF(L26="TRY_TIERS",IF(K26<25,19,IF(K26<35,29,IF(K26<45,39,IF(K26<60,49,79)))), IF(L26="INR_TIERS",IF(K26<40,29,IF(K26<70,49,99)), IF(L26="BRL_90",IF(K26<3,2.9,IF(K26<6,4.9,IF(K26<10,6.9,9.9))), IF(L26="IDR_000",ROUND(K26/1000,0)*1000, IF(L26="JPY_00",ROUND(K26/100,0)*100, IF(L26="KRW_000",ROUND(K26/1000,0)*1000, IF(L26="VND_000",ROUND(K26/1000,0)*1000, IF(OR(L26="USD_99",L26="EUR_99",L26="GBP_99",L26="CAD_99",L26="AUD_99",L26="PLN_99"),MAX(0.49,ROUND(K26,0)-0.01), IF(L26="MXN_00",ROUND(K26,0),IF(L26="THB_00",ROUND(K26,0),ROUND(K26,2))))))))))) -> 46.02 | N26: =M26/J26 -> 0.48995137 | P26: =IFERROR(__xludf.DUMMYFUNCTION("GOOGLEFINANCE(""CURRENCY:USDCVE"")"),93.92769000000001) -> 93.92769
A27: Kamboçya | B27: Cambodia | C27: KH | D27: KHR | E27: 0.2 | F27: E | G27: =Dashboard!$B$3 -> 1 | H27: =MAX(Dashboard!$B$4,G27*E27) -> 0.49 | I27: 1 | J27: =IFERROR(__xludf.DUMMYFUNCTION("GOOGLEFINANCE(""CURRENCY:USDKHR"")"),4012.13) -> 4012.13 | K27: =H27*I27*J27 -> 1965.9437 | M27: =IF(L27="TRY_TIERS",IF(K27<25,19,IF(K27<35,29,IF(K27<45,39,IF(K27<60,49,79)))), IF(L27="INR_TIERS",IF(K27<40,29,IF(K27<70,49,99)), IF(L27="BRL_90",IF(K27<3,2.9,IF(K27<6,4.9,IF(K27<10,6.9,9.9))), IF(L27="IDR_000",ROUND(K27/1000,0)*1000, IF(L27="JPY_00",ROUND(K27/100,0)*100, IF(L27="KRW_000",ROUND(K27/1000,0)*1000, IF(L27="VND_000",ROUND(K27/1000,0)*1000, IF(OR(L27="USD_99",L27="EUR_99",L27="GBP_99",L27="CAD_99",L27="AUD_99",L27="PLN_99"),MAX(0.49,ROUND(K27,0)-0.01), IF(L27="MXN_00",ROUND(K27,0),IF(L27="THB_00",ROUND(K27,0),ROUND(K27,2))))))))))) -> 1965.94 | N27: =M27/J27 -> 0.48999908 | P27: =IFERROR(__xludf.DUMMYFUNCTION("GOOGLEFINANCE(""CURRENCY:USDKHR"")"),4012.13) -> 4012.13
A28: Kamerun | B28: Cameroon | C28: CM | D28: XAF | E28: 0.12 | F28: E | G28: =Dashboard!$B$3 -> 1 | H28: =MAX(Dashboard!$B$4,G28*E28) -> 0.49 | I28: 1 | J28: =IFERROR(__xludf.DUMMYFUNCTION("GOOGLEFINANCE(""CURRENCY:USDXAF"")"),558.7654) -> 558.7654 | K28: =H28*I28*J28 -> 273.79505 | M28: =IF(L28="TRY_TIERS",IF(K28<25,19,IF(K28<35,29,IF(K28<45,39,IF(K28<60,49,79)))), IF(L28="INR_TIERS",IF(K28<40,29,IF(K28<70,49,99)), IF(L28="BRL_90",IF(K28<3,2.9,IF(K28<6,4.9,IF(K28<10,6.9,9.9))), IF(L28="IDR_000",ROUND(K28/1000,0)*1000, IF(L28="JPY_00",ROUND(K28/100,0)*100, IF(L28="KRW_000",ROUND(K28/1000,0)*1000, IF(L28="VND_000",ROUND(K28/1000,0)*1000, IF(OR(L28="USD_99",L28="EUR_99",L28="GBP_99",L28="CAD_99",L28="AUD_99",L28="PLN_99"),MAX(0.49,ROUND(K28,0)-0.01), IF(L28="MXN_00",ROUND(K28,0),IF(L28="THB_00",ROUND(K28,0),ROUND(K28,2))))))))))) -> 273.8 | N28: =M28/J28 -> 0.49000887 | P28: =IFERROR(__xludf.DUMMYFUNCTION("GOOGLEFINANCE(""CURRENCY:USDXAF"")"),558.7654) -> 558.7654
A29: Kanada | B29: Canada | C29: CA | D29: CAD | E29: 0.85 | F29: =IF(E29>=0.8,"A",IF(E29>=0.6,"B",IF(E29>=0.4,"C",IF(E29>=0.2,"D","E")))) -> A | G29: =Dashboard!$B$3 -> 1 | H29: =MAX(Dashboard!$B$4,G29*E29) -> 0.85 | I29: 1 | J29: =IFERROR(__xludf.DUMMYFUNCTION("GOOGLEFINANCE(""CURRENCY:USDCAD"")"),1.369425) -> 1.369425 | K29: =H29*I29*J29 -> 1.1640112 | L29: CAD_99 | M29: =IF(L29="TRY_TIERS",IF(K29<25,19,IF(K29<35,29,IF(K29<45,39,IF(K29<60,49,79)))), IF(L29="INR_TIERS",IF(K29<40,29,IF(K29<70,49,99)), IF(L29="BRL_90",IF(K29<3,2.9,IF(K29<6,4.9,IF(K29<10,6.9,9.9))), IF(L29="IDR_000",ROUND(K29/1000,0)*1000, IF(L29="JPY_00",ROUND(K29/100,0)*100, IF(L29="KRW_000",ROUND(K29/1000,0)*1000, IF(L29="VND_000",ROUND(K29/1000,0)*1000, IF(OR(L29="USD_99",L29="EUR_99",L29="GBP_99",L29="CAD_99",L29="AUD_99",L29="PLN_99"),MAX(0.49,ROUND(K29,0)-0.01), IF(L29="MXN_00",ROUND(K29,0),IF(L29="THB_00",ROUND(K29,0),ROUND(K29,2))))))))))) -> 0.99 | N29: =M29/J29 -> 0.72293116 | O29: =IF(N29<Dashboard!$B$4,"Below global min",IF(AND(E29>=0.8,N29<Dashboard!$B$5),"Raise high-PPP floor","OK")) -> Raise high-PPP floor | P29: =IFERROR(__xludf.DUMMYFUNCTION("GOOGLEFINANCE(""CURRENCY:USDCAD"")"),1.369425) -> 1.369425
A30: Cayman Adaları | B30: Cayman Islands | C30: KY | D30: KYD | E30: 1 | F30: A | G30: =Dashboard!$B$3 -> 1 | H30: =MAX(Dashboard!$B$4,G30*E30) -> 1 | I30: 1 | J30: =IFERROR(__xludf.DUMMYFUNCTION("GOOGLEFINANCE(""CURRENCY:USDKYD"")"),0.8334256) -> 0.8334256 | K30: =H30*I30*J30 -> 0.8334256 | M30: =IF(L30="TRY_TIERS",IF(K30<25,19,IF(K30<35,29,IF(K30<45,39,IF(K30<60,49,79)))), IF(L30="INR_TIERS",IF(K30<40,29,IF(K30<70,49,99)), IF(L30="BRL_90",IF(K30<3,2.9,IF(K30<6,4.9,IF(K30<10,6.9,9.9))), IF(L30="IDR_000",ROUND(K30/1000,0)*1000, IF(L30="JPY_00",ROUND(K30/100,0)*100, IF(L30="KRW_000",ROUND(K30/1000,0)*1000, IF(L30="VND_000",ROUND(K30/1000,0)*1000, IF(OR(L30="USD_99",L30="EUR_99",L30="GBP_99",L30="CAD_99",L30="AUD_99",L30="PLN_99"),MAX(0.49,ROUND(K30,0)-0.01), IF(L30="MXN_00",ROUND(K30,0),IF(L30="THB_00",ROUND(K30,0),ROUND(K30,2))))))))))) -> 0.83 | N30: =M30/J30 -> 0.99588974 | P30: =IFERROR(__xludf.DUMMYFUNCTION("GOOGLEFINANCE(""CURRENCY:USDKYD"")"),0.8334256) -> 0.8334256
A31: Orta Afrika Cumhuriyeti | B31: Central African Republic | C31: CF | D31: XAF | E31: 0.12 | F31: E | G31: =Dashboard!$B$3 -> 1 | H31: =MAX(Dashboard!$B$4,G31*E31) -> 0.49 | I31: 1 | J31: =IFERROR(__xludf.DUMMYFUNCTION("GOOGLEFINANCE(""CURRENCY:USDXAF"")"),558.7654) -> 558.7654 | K31: =H31*I31*J31 -> 273.79505 | M31: =IF(L31="TRY_TIERS",IF(K31<25,19,IF(K31<35,29,IF(K31<45,39,IF(K31<60,49,79)))), IF(L31="INR_TIERS",IF(K31<40,29,IF(K31<70,49,99)), IF(L31="BRL_90",IF(K31<3,2.9,IF(K31<6,4.9,IF(K31<10,6.9,9.9))), IF(L31="IDR_000",ROUND(K31/1000,0)*1000, IF(L31="JPY_00",ROUND(K31/100,0)*100, IF(L31="KRW_000",ROUND(K31/1000,0)*1000, IF(L31="VND_000",ROUND(K31/1000,0)*1000, IF(OR(L31="USD_99",L31="EUR_99",L31="GBP_99",L31="CAD_99",L31="AUD_99",L31="PLN_99"),MAX(0.49,ROUND(K31,0)-0.01), IF(L31="MXN_00",ROUND(K31,0),IF(L31="THB_00",ROUND(K31,0),ROUND(K31,2))))))))))) -> 273.8 | N31: =M31/J31 -> 0.49000887 | P31: =IFERROR(__xludf.DUMMYFUNCTION("GOOGLEFINANCE(""CURRENCY:USDXAF"")"),558.7654) -> 558.7654
A32: Çad | B32: Chad | C32: TD | D32: XAF | E32: 0.12 | F32: E | G32: =Dashboard!$B$3 -> 1 | H32: =MAX(Dashboard!$B$4,G32*E32) -> 0.49 | I32: 1 | J32: =IFERROR(__xludf.DUMMYFUNCTION("GOOGLEFINANCE(""CURRENCY:USDXAF"")"),558.7654) -> 558.7654 | K32: =H32*I32*J32 -> 273.79505 | M32: =IF(L32="TRY_TIERS",IF(K32<25,19,IF(K32<35,29,IF(K32<45,39,IF(K32<60,49,79)))), IF(L32="INR_TIERS",IF(K32<40,29,IF(K32<70,49,99)), IF(L32="BRL_90",IF(K32<3,2.9,IF(K32<6,4.9,IF(K32<10,6.9,9.9))), IF(L32="IDR_000",ROUND(K32/1000,0)*1000, IF(L32="JPY_00",ROUND(K32/100,0)*100, IF(L32="KRW_000",ROUND(K32/1000,0)*1000, IF(L32="VND_000",ROUND(K32/1000,0)*1000, IF(OR(L32="USD_99",L32="EUR_99",L32="GBP_99",L32="CAD_99",L32="AUD_99",L32="PLN_99"),MAX(0.49,ROUND(K32,0)-0.01), IF(L32="MXN_00",ROUND(K32,0),IF(L32="THB_00",ROUND(K32,0),ROUND(K32,2))))))))))) -> 273.8 | N32: =M32/J32 -> 0.49000887 | P32: =IFERROR(__xludf.DUMMYFUNCTION("GOOGLEFINANCE(""CURRENCY:USDXAF"")"),558.7654) -> 558.7654
A33: Şili | B33: Chile | C33: CL | D33: CLP | E33: 0.6 | F33: C | G33: =Dashboard!$B$3 -> 1 | H33: =MAX(Dashboard!$B$4,G33*E33) -> 0.6 | I33: 1 | J33: =IFERROR(__xludf.DUMMYFUNCTION("GOOGLEFINANCE(""CURRENCY:USDCLP"")"),892.857143) -> 892.85714 | K33: =H33*I33*J33 -> 535.71429 | M33: =IF(L33="TRY_TIERS",IF(K33<25,19,IF(K33<35,29,IF(K33<45,39,IF(K33<60,49,79)))), IF(L33="INR_TIERS",IF(K33<40,29,IF(K33<70,49,99)), IF(L33="BRL_90",IF(K33<3,2.9,IF(K33<6,4.9,IF(K33<10,6.9,9.9))), IF(L33="IDR_000",ROUND(K33/1000,0)*1000, IF(L33="JPY_00",ROUND(K33/100,0)*100, IF(L33="KRW_000",ROUND(K33/1000,0)*1000, IF(L33="VND_000",ROUND(K33/1000,0)*1000, IF(OR(L33="USD_99",L33="EUR_99",L33="GBP_99",L33="CAD_99",L33="AUD_99",L33="PLN_99"),MAX(0.49,ROUND(K33,0)-0.01), IF(L33="MXN_00",ROUND(K33,0),IF(L33="THB_00",ROUND(K33,0),ROUND(K33,2))))))))))) -> 535.71 | N33: =M33/J33 -> 0.5999952 | P33: =IFERROR(__xludf.DUMMYFUNCTION("GOOGLEFINANCE(""CURRENCY:USDCLP"")"),892.857143) -> 892.85714
A34: Kolombiya | B34: Colombia | C34: CO | D34: COP-COU | E34: 0.38 | F34: D | G34: =Dashboard!$B$3 -> 1 | H34: =MAX(Dashboard!$B$4,G34*E34) -> 0.49 | I34: 1 | J34: =IFERROR(__xludf.DUMMYFUNCTION("GOOGLEFINANCE(""CURRENCY:USDCOP"")"),3752.41843) -> 3752.4184 | K34: =H34*I34*J34 -> 1838.685 | M34: =IF(L34="TRY_TIERS",IF(K34<25,19,IF(K34<35,29,IF(K34<45,39,IF(K34<60,49,79)))), IF(L34="INR_TIERS",IF(K34<40,29,IF(K34<70,49,99)), IF(L34="BRL_90",IF(K34<3,2.9,IF(K34<6,4.9,IF(K34<10,6.9,9.9))), IF(L34="IDR_000",ROUND(K34/1000,0)*1000, IF(L34="JPY_00",ROUND(K34/100,0)*100, IF(L34="KRW_000",ROUND(K34/1000,0)*1000, IF(L34="VND_000",ROUND(K34/1000,0)*1000, IF(OR(L34="USD_99",L34="EUR_99",L34="GBP_99",L34="CAD_99",L34="AUD_99",L34="PLN_99"),MAX(0.49,ROUND(K34,0)-0.01), IF(L34="MXN_00",ROUND(K34,0),IF(L34="THB_00",ROUND(K34,0),ROUND(K34,2))))))))))) -> 1838.69 | N34: =M34/J34 -> 0.49000132 | P34: =IFERROR(__xludf.DUMMYFUNCTION("GOOGLEFINANCE(""CURRENCY:USDCOP"")"),3752.41843) -> 3752.4184
A35: Komorlar | B35: Comoros | C35: KM | D35: KMF | E35: 0.18 | F35: E | G35: =Dashboard!$B$3 -> 1 | H35: =MAX(Dashboard!$B$4,G35*E35) -> 0.49 | I35: 1 | J35: =IFERROR(__xludf.DUMMYFUNCTION("GOOGLEFINANCE(""CURRENCY:USDKMF"")"),420.0) -> 420 | K35: =H35*I35*J35 -> 205.8 | M35: =IF(L35="TRY_TIERS",IF(K35<25,19,IF(K35<35,29,IF(K35<45,39,IF(K35<60,49,79)))), IF(L35="INR_TIERS",IF(K35<40,29,IF(K35<70,49,99)), IF(L35="BRL_90",IF(K35<3,2.9,IF(K35<6,4.9,IF(K35<10,6.9,9.9))), IF(L35="IDR_000",ROUND(K35/1000,0)*1000, IF(L35="JPY_00",ROUND(K35/100,0)*100, IF(L35="KRW_000",ROUND(K35/1000,0)*1000, IF(L35="VND_000",ROUND(K35/1000,0)*1000, IF(OR(L35="USD_99",L35="EUR_99",L35="GBP_99",L35="CAD_99",L35="AUD_99",L35="PLN_99"),MAX(0.49,ROUND(K35,0)-0.01), IF(L35="MXN_00",ROUND(K35,0),IF(L35="THB_00",ROUND(K35,0),ROUND(K35,2))))))))))) -> 205.8 | N35: =M35/J35 -> 0.49 | P35: =IFERROR(__xludf.DUMMYFUNCTION("GOOGLEFINANCE(""CURRENCY:USDKMF"")"),420.0) -> 420
A36: Kongo-Brazavil | B36: Congo | C36: CG | D36: XAF | E36: 0.22 | F36: E | G36: =Dashboard!$B$3 -> 1 | H36: =MAX(Dashboard!$B$4,G36*E36) -> 0.49 | I36: 1 | J36: =IFERROR(__xludf.DUMMYFUNCTION("GOOGLEFINANCE(""CURRENCY:USDXAF"")"),558.7654) -> 558.7654 | K36: =H36*I36*J36 -> 273.79505 | M36: =IF(L36="TRY_TIERS",IF(K36<25,19,IF(K36<35,29,IF(K36<45,39,IF(K36<60,49,79)))), IF(L36="INR_TIERS",IF(K36<40,29,IF(K36<70,49,99)), IF(L36="BRL_90",IF(K36<3,2.9,IF(K36<6,4.9,IF(K36<10,6.9,9.9))), IF(L36="IDR_000",ROUND(K36/1000,0)*1000, IF(L36="JPY_00",ROUND(K36/100,0)*100, IF(L36="KRW_000",ROUND(K36/1000,0)*1000, IF(L36="VND_000",ROUND(K36/1000,0)*1000, IF(OR(L36="USD_99",L36="EUR_99",L36="GBP_99",L36="CAD_99",L36="AUD_99",L36="PLN_99"),MAX(0.49,ROUND(K36,0)-0.01), IF(L36="MXN_00",ROUND(K36,0),IF(L36="THB_00",ROUND(K36,0),ROUND(K36,2))))))))))) -> 273.8 | N36: =M36/J36 -> 0.49000887 | P36: =IFERROR(__xludf.DUMMYFUNCTION("GOOGLEFINANCE(""CURRENCY:USDXAF"")"),558.7654) -> 558.7654
A37: Kongo-Kinşasa | B37: Congo (the Democratic Republic of the) | C37: CD | D37: CDF | E37: 0.15 | F37: E | G37: =Dashboard!$B$3 -> 1 | H37: =MAX(Dashboard!$B$4,G37*E37) -> 0.49 | I37: 1 | J37: =IFERROR(__xludf.DUMMYFUNCTION("GOOGLEFINANCE(""CURRENCY:USDCDF"")"),2280.07117) -> 2280.0712 | K37: =H37*I37*J37 -> 1117.2349 | M37: =IF(L37="TRY_TIERS",IF(K37<25,19,IF(K37<35,29,IF(K37<45,39,IF(K37<60,49,79)))), IF(L37="INR_TIERS",IF(K37<40,29,IF(K37<70,49,99)), IF(L37="BRL_90",IF(K37<3,2.9,IF(K37<6,4.9,IF(K37<10,6.9,9.9))), IF(L37="IDR_000",ROUND(K37/1000,0)*1000, IF(L37="JPY_00",ROUND(K37/100,0)*100, IF(L37="KRW_000",ROUND(K37/1000,0)*1000, IF(L37="VND_000",ROUND(K37/1000,0)*1000, IF(OR(L37="USD_99",L37="EUR_99",L37="GBP_99",L37="CAD_99",L37="AUD_99",L37="PLN_99"),MAX(0.49,ROUND(K37,0)-0.01), IF(L37="MXN_00",ROUND(K37,0),IF(L37="THB_00",ROUND(K37,0),ROUND(K37,2))))))))))) -> 1117.23 | N37: =M37/J37 -> 0.48999786 | P37: =IFERROR(__xludf.DUMMYFUNCTION("GOOGLEFINANCE(""CURRENCY:USDCDF"")"),2280.07117) -> 2280.0712
A38: KostaRika | B38: Costa Rica | C38: CR | D38: CRC | E38: 0.5 | F38: C | G38: =Dashboard!$B$3 -> 1 | H38: =MAX(Dashboard!$B$4,G38*E38) -> 0.5 | I38: 1 | J38: =IFERROR(__xludf.DUMMYFUNCTION("GOOGLEFINANCE(""CURRENCY:USDCRC"")"),456.4117) -> 456.4117 | K38: =H38*I38*J38 -> 228.20585 | M38: =IF(L38="TRY_TIERS",IF(K38<25,19,IF(K38<35,29,IF(K38<45,39,IF(K38<60,49,79)))), IF(L38="INR_TIERS",IF(K38<40,29,IF(K38<70,49,99)), IF(L38="BRL_90",IF(K38<3,2.9,IF(K38<6,4.9,IF(K38<10,6.9,9.9))), IF(L38="IDR_000",ROUND(K38/1000,0)*1000, IF(L38="JPY_00",ROUND(K38/100,0)*100, IF(L38="KRW_000",ROUND(K38/1000,0)*1000, IF(L38="VND_000",ROUND(K38/1000,0)*1000, IF(OR(L38="USD_99",L38="EUR_99",L38="GBP_99",L38="CAD_99",L38="AUD_99",L38="PLN_99"),MAX(0.49,ROUND(K38,0)-0.01), IF(L38="MXN_00",ROUND(K38,0),IF(L38="THB_00",ROUND(K38,0),ROUND(K38,2))))))))))) -> 228.21 | N38: =M38/J38 -> 0.50000909 | P38: =IFERROR(__xludf.DUMMYFUNCTION("GOOGLEFINANCE(""CURRENCY:USDCRC"")"),456.4117) -> 456.4117
A39: Côte d’Ivoire | B39: Côte d’Ivoire | C39: CI | D39: XOF | E39: 0.25 | F39: E | G39: =Dashboard!$B$3 -> 1 | H39: =MAX(Dashboard!$B$4,G39*E39) -> 0.49 | I39: 1 | J39: =IFERROR(__xludf.DUMMYFUNCTION("GOOGLEFINANCE(""CURRENCY:USDXOF"")"),558.7654) -> 558.7654 | K39: =H39*I39*J39 -> 273.79505 | M39: =IF(L39="TRY_TIERS",IF(K39<25,19,IF(K39<35,29,IF(K39<45,39,IF(K39<60,49,79)))), IF(L39="INR_TIERS",IF(K39<40,29,IF(K39<70,49,99)), IF(L39="BRL_90",IF(K39<3,2.9,IF(K39<6,4.9,IF(K39<10,6.9,9.9))), IF(L39="IDR_000",ROUND(K39/1000,0)*1000, IF(L39="JPY_00",ROUND(K39/100,0)*100, IF(L39="KRW_000",ROUND(K39/1000,0)*1000, IF(L39="VND_000",ROUND(K39/1000,0)*1000, IF(OR(L39="USD_99",L39="EUR_99",L39="GBP_99",L39="CAD_99",L39="AUD_99",L39="PLN_99"),MAX(0.49,ROUND(K39,0)-0.01), IF(L39="MXN_00",ROUND(K39,0),IF(L39="THB_00",ROUND(K39,0),ROUND(K39,2))))))))))) -> 273.8 | N39: =M39/J39 -> 0.49000887 | P39: =IFERROR(__xludf.DUMMYFUNCTION("GOOGLEFINANCE(""CURRENCY:USDXOF"")"),558.7654) -> 558.7654
A40: Hırvatistan | B40: Croaita | C40: HR | D40: EUR | E40: 0.55 | F40: C | G40: =Dashboard!$B$3 -> 1 | H40: =MAX(Dashboard!$B$4,G40*E40) -> 0.55 | I40: 1 | J40: =IFERROR(__xludf.DUMMYFUNCTION("GOOGLEFINANCE(""CURRENCY:USDEUR"")"),0.8519) -> 0.8519 | K40: =H40*I40*J40 -> 0.468545 | M40: =IF(L40="TRY_TIERS",IF(K40<25,19,IF(K40<35,29,IF(K40<45,39,IF(K40<60,49,79)))), IF(L40="INR_TIERS",IF(K40<40,29,IF(K40<70,49,99)), IF(L40="BRL_90",IF(K40<3,2.9,IF(K40<6,4.9,IF(K40<10,6.9,9.9))), IF(L40="IDR_000",ROUND(K40/1000,0)*1000, IF(L40="JPY_00",ROUND(K40/100,0)*100, IF(L40="KRW_000",ROUND(K40/1000,0)*1000, IF(L40="VND_000",ROUND(K40/1000,0)*1000, IF(OR(L40="USD_99",L40="EUR_99",L40="GBP_99",L40="CAD_99",L40="AUD_99",L40="PLN_99"),MAX(0.49,ROUND(K40,0)-0.01), IF(L40="MXN_00",ROUND(K40,0),IF(L40="THB_00",ROUND(K40,0),ROUND(K40,2))))))))))) -> 0.47 | N40: =M40/J40 -> 0.55170795 | P40: =IFERROR(__xludf.DUMMYFUNCTION("GOOGLEFINANCE(""CURRENCY:USDEUR"")"),0.8519) -> 0.8519
A41: Kıbrıs | B41: Cyprus | C41: CY | D41: EUR | E41: 0.7 | F41: B | G41: =Dashboard!$B$3 -> 1 | H41: =MAX(Dashboard!$B$4,G41*E41) -> 0.7 | I41: 1 | J41: =IFERROR(__xludf.DUMMYFUNCTION("GOOGLEFINANCE(""CURRENCY:USDEUR"")"),0.8519) -> 0.8519 | K41: =H41*I41*J41 -> 0.59633 | M41: =IF(L41="TRY_TIERS",IF(K41<25,19,IF(K41<35,29,IF(K41<45,39,IF(K41<60,49,79)))), IF(L41="INR_TIERS",IF(K41<40,29,IF(K41<70,49,99)), IF(L41="BRL_90",IF(K41<3,2.9,IF(K41<6,4.9,IF(K41<10,6.9,9.9))), IF(L41="IDR_000",ROUND(K41/1000,0)*1000, IF(L41="JPY_00",ROUND(K41/100,0)*100, IF(L41="KRW_000",ROUND(K41/1000,0)*1000, IF(L41="VND_000",ROUND(K41/1000,0)*1000, IF(OR(L41="USD_99",L41="EUR_99",L41="GBP_99",L41="CAD_99",L41="AUD_99",L41="PLN_99"),MAX(0.49,ROUND(K41,0)-0.01), IF(L41="MXN_00",ROUND(K41,0),IF(L41="THB_00",ROUND(K41,0),ROUND(K41,2))))))))))) -> 0.6 | N41: =M41/J41 -> 0.70430802 | P41: =IFERROR(__xludf.DUMMYFUNCTION("GOOGLEFINANCE(""CURRENCY:USDEUR"")"),0.8519) -> 0.8519
A42: Çekya | B42: czechia | C42: CZ | D42: CZK | E42: 0.6 | F42: C | G42: =Dashboard!$B$3 -> 1 | H42: =MAX(Dashboard!$B$4,G42*E42) -> 0.6 | I42: 1 | J42: =IFERROR(__xludf.DUMMYFUNCTION("GOOGLEFINANCE(""CURRENCY:USDCZK"")"),20.7329) -> 20.7329 | K42: =H42*I42*J42 -> 12.43974 | M42: =IF(L42="TRY_TIERS",IF(K42<25,19,IF(K42<35,29,IF(K42<45,39,IF(K42<60,49,79)))), IF(L42="INR_TIERS",IF(K42<40,29,IF(K42<70,49,99)), IF(L42="BRL_90",IF(K42<3,2.9,IF(K42<6,4.9,IF(K42<10,6.9,9.9))), IF(L42="IDR_000",ROUND(K42/1000,0)*1000, IF(L42="JPY_00",ROUND(K42/100,0)*100, IF(L42="KRW_000",ROUND(K42/1000,0)*1000, IF(L42="VND_000",ROUND(K42/1000,0)*1000, IF(OR(L42="USD_99",L42="EUR_99",L42="GBP_99",L42="CAD_99",L42="AUD_99",L42="PLN_99"),MAX(0.49,ROUND(K42,0)-0.01), IF(L42="MXN_00",ROUND(K42,0),IF(L42="THB_00",ROUND(K42,0),ROUND(K42,2))))))))))) -> 12.44 | N42: =M42/J42 -> 0.60001254 | P42: =IFERROR(__xludf.DUMMYFUNCTION("GOOGLEFINANCE(""CURRENCY:USDCZK"")"),20.7329) -> 20.7329
A43: Danimarka | B43: Denmark | C43: DK | D43: DKK | E43: 0.92 | F43: A | G43: =Dashboard!$B$3 -> 1 | H43: =MAX(Dashboard!$B$4,G43*E43) -> 0.92 | I43: 1 | J43: =IFERROR(__xludf.DUMMYFUNCTION("GOOGLEFINANCE(""CURRENCY:USDDKK"")"),6.36478) -> 6.36478 | K43: =H43*I43*J43 -> 5.8555976 | M43: =IF(L43="TRY_TIERS",IF(K43<25,19,IF(K43<35,29,IF(K43<45,39,IF(K43<60,49,79)))), IF(L43="INR_TIERS",IF(K43<40,29,IF(K43<70,49,99)), IF(L43="BRL_90",IF(K43<3,2.9,IF(K43<6,4.9,IF(K43<10,6.9,9.9))), IF(L43="IDR_000",ROUND(K43/1000,0)*1000, IF(L43="JPY_00",ROUND(K43/100,0)*100, IF(L43="KRW_000",ROUND(K43/1000,0)*1000, IF(L43="VND_000",ROUND(K43/1000,0)*1000, IF(OR(L43="USD_99",L43="EUR_99",L43="GBP_99",L43="CAD_99",L43="AUD_99",L43="PLN_99"),MAX(0.49,ROUND(K43,0)-0.01), IF(L43="MXN_00",ROUND(K43,0),IF(L43="THB_00",ROUND(K43,0),ROUND(K43,2))))))))))) -> 5.86 | N43: =M43/J43 -> 0.92069168 | P43: =IFERROR(__xludf.DUMMYFUNCTION("GOOGLEFINANCE(""CURRENCY:USDDKK"")"),6.36478) -> 6.36478
A44: Cibuti | B44: Djibouti | C44: DJ | D44: DJF | E44: 0.25 | F44: E | G44: =Dashboard!$B$3 -> 1 | H44: =MAX(Dashboard!$B$4,G44*E44) -> 0.49 | I44: 1 | J44: =IFERROR(__xludf.DUMMYFUNCTION("GOOGLEFINANCE(""CURRENCY:USDDJF"")"),178.0926) -> 178.0926 | K44: =H44*I44*J44 -> 87.265374 | M44: =IF(L44="TRY_TIERS",IF(K44<25,19,IF(K44<35,29,IF(K44<45,39,IF(K44<60,49,79)))), IF(L44="INR_TIERS",IF(K44<40,29,IF(K44<70,49,99)), IF(L44="BRL_90",IF(K44<3,2.9,IF(K44<6,4.9,IF(K44<10,6.9,9.9))), IF(L44="IDR_000",ROUND(K44/1000,0)*1000, IF(L44="JPY_00",ROUND(K44/100,0)*100, IF(L44="KRW_000",ROUND(K44/1000,0)*1000, IF(L44="VND_000",ROUND(K44/1000,0)*1000, IF(OR(L44="USD_99",L44="EUR_99",L44="GBP_99",L44="CAD_99",L44="AUD_99",L44="PLN_99"),MAX(0.49,ROUND(K44,0)-0.01), IF(L44="MXN_00",ROUND(K44,0),IF(L44="THB_00",ROUND(K44,0),ROUND(K44,2))))))))))) -> 87.27 | N44: =M44/J44 -> 0.49002598 | P44: =IFERROR(__xludf.DUMMYFUNCTION("GOOGLEFINANCE(""CURRENCY:USDDJF"")"),178.0926) -> 178.0926
A45: Dominika | B45: Dominica | C45: DO | D45: XCD | E45: 0.55 | F45: C | G45: =Dashboard!$B$3 -> 1 | H45: =MAX(Dashboard!$B$4,G45*E45) -> 0.55 | I45: 1 | J45: =IFERROR(__xludf.DUMMYFUNCTION("GOOGLEFINANCE(""CURRENCY:USDXCD"")"),2.70255) -> 2.70255 | K45: =H45*I45*J45 -> 1.4864025 | M45: =IF(L45="TRY_TIERS",IF(K45<25,19,IF(K45<35,29,IF(K45<45,39,IF(K45<60,49,79)))), IF(L45="INR_TIERS",IF(K45<40,29,IF(K45<70,49,99)), IF(L45="BRL_90",IF(K45<3,2.9,IF(K45<6,4.9,IF(K45<10,6.9,9.9))), IF(L45="IDR_000",ROUND(K45/1000,0)*1000, IF(L45="JPY_00",ROUND(K45/100,0)*100, IF(L45="KRW_000",ROUND(K45/1000,0)*1000, IF(L45="VND_000",ROUND(K45/1000,0)*1000, IF(OR(L45="USD_99",L45="EUR_99",L45="GBP_99",L45="CAD_99",L45="AUD_99",L45="PLN_99"),MAX(0.49,ROUND(K45,0)-0.01), IF(L45="MXN_00",ROUND(K45,0),IF(L45="THB_00",ROUND(K45,0),ROUND(K45,2))))))))))) -> 1.49 | N45: =M45/J45 -> 0.55133115 | P45: =IFERROR(__xludf.DUMMYFUNCTION("GOOGLEFINANCE(""CURRENCY:USDXCD"")"),2.70255) -> 2.70255
A46: Dominik Cumhuriyeti | B46: Dominican Republic | C46: DO | D46: DOP | E46: 0.35 | F46: D | G46: =Dashboard!$B$3 -> 1 | H46: =MAX(Dashboard!$B$4,G46*E46) -> 0.49 | I46: 1 | J46: =IFERROR(__xludf.DUMMYFUNCTION("GOOGLEFINANCE(""CURRENCY:USDDOP"")"),59.02346000000001) -> 59.02346 | K46: =H46*I46*J46 -> 28.921495 | M46: =IF(L46="TRY_TIERS",IF(K46<25,19,IF(K46<35,29,IF(K46<45,39,IF(K46<60,49,79)))), IF(L46="INR_TIERS",IF(K46<40,29,IF(K46<70,49,99)), IF(L46="BRL_90",IF(K46<3,2.9,IF(K46<6,4.9,IF(K46<10,6.9,9.9))), IF(L46="IDR_000",ROUND(K46/1000,0)*1000, IF(L46="JPY_00",ROUND(K46/100,0)*100, IF(L46="KRW_000",ROUND(K46/1000,0)*1000, IF(L46="VND_000",ROUND(K46/1000,0)*1000, IF(OR(L46="USD_99",L46="EUR_99",L46="GBP_99",L46="CAD_99",L46="AUD_99",L46="PLN_99"),MAX(0.49,ROUND(K46,0)-0.01), IF(L46="MXN_00",ROUND(K46,0),IF(L46="THB_00",ROUND(K46,0),ROUND(K46,2))))))))))) -> 28.92 | N46: =M46/J46 -> 0.48997466 | P46: =IFERROR(__xludf.DUMMYFUNCTION("GOOGLEFINANCE(""CURRENCY:USDDOP"")"),59.02346000000001) -> 59.02346
A47: Ekvador | B47: Ecuador | C47: EC | D47: USD | E47: 0.4 | F47: D | G47: =Dashboard!$B$3 -> 1 | H47: =MAX(Dashboard!$B$4,G47*E47) -> 0.49 | I47: 1 | J47: =IFERROR(__xludf.DUMMYFUNCTION("GOOGLEFINANCE(""CURRENCY:USDUSD"")"),"#N/A") -> #N/A | K47: =H47*I47*J47 -> #N/A | M47: =IF(L47="TRY_TIERS",IF(K47<25,19,IF(K47<35,29,IF(K47<45,39,IF(K47<60,49,79)))), IF(L47="INR_TIERS",IF(K47<40,29,IF(K47<70,49,99)), IF(L47="BRL_90",IF(K47<3,2.9,IF(K47<6,4.9,IF(K47<10,6.9,9.9))), IF(L47="IDR_000",ROUND(K47/1000,0)*1000, IF(L47="JPY_00",ROUND(K47/100,0)*100, IF(L47="KRW_000",ROUND(K47/1000,0)*1000, IF(L47="VND_000",ROUND(K47/1000,0)*1000, IF(OR(L47="USD_99",L47="EUR_99",L47="GBP_99",L47="CAD_99",L47="AUD_99",L47="PLN_99"),MAX(0.49,ROUND(K47,0)-0.01), IF(L47="MXN_00",ROUND(K47,0),IF(L47="THB_00",ROUND(K47,0),ROUND(K47,2))))))))))) -> #N/A | N47: =M47/J47 -> #N/A | P47: =IFERROR(__xludf.DUMMYFUNCTION("GOOGLEFINANCE(""CURRENCY:USDUSD"")"),"#N/A") -> #N/A
A48: Mısır | B48: Egypt | C48: EG | D48: EGP | E48: 0.25 | F48: E | G48: =Dashboard!$B$3 -> 1 | H48: =MAX(Dashboard!$B$4,G48*E48) -> 0.49 | I48: 1 | J48: =IFERROR(__xludf.DUMMYFUNCTION("GOOGLEFINANCE(""CURRENCY:USDEGP"")"),52.9003) -> 52.9003 | K48: =H48*I48*J48 -> 25.921147 | M48: =IF(L48="TRY_TIERS",IF(K48<25,19,IF(K48<35,29,IF(K48<45,39,IF(K48<60,49,79)))), IF(L48="INR_TIERS",IF(K48<40,29,IF(K48<70,49,99)), IF(L48="BRL_90",IF(K48<3,2.9,IF(K48<6,4.9,IF(K48<10,6.9,9.9))), IF(L48="IDR_000",ROUND(K48/1000,0)*1000, IF(L48="JPY_00",ROUND(K48/100,0)*100, IF(L48="KRW_000",ROUND(K48/1000,0)*1000, IF(L48="VND_000",ROUND(K48/1000,0)*1000, IF(OR(L48="USD_99",L48="EUR_99",L48="GBP_99",L48="CAD_99",L48="AUD_99",L48="PLN_99"),MAX(0.49,ROUND(K48,0)-0.01), IF(L48="MXN_00",ROUND(K48,0),IF(L48="THB_00",ROUND(K48,0),ROUND(K48,2))))))))))) -> 25.92 | N48: =M48/J48 -> 0.48997832 | P48: =IFERROR(__xludf.DUMMYFUNCTION("GOOGLEFINANCE(""CURRENCY:USDEGP"")"),52.9003) -> 52.9003
A49: El Salvador | B49: El Salvador | C49: SV | D49: SVC-USD | E49: 0.3 | F49: D | G49: =Dashboard!$B$3 -> 1 | H49: =MAX(Dashboard!$B$4,G49*E49) -> 0.49 | I49: 1 | J49: =IFERROR(__xludf.DUMMYFUNCTION("GOOGLEFINANCE(""CURRENCY:USDSVC"")"),8.750798999999999) -> 8.750799 | K49: =H49*I49*J49 -> 4.2878915 | M49: =IF(L49="TRY_TIERS",IF(K49<25,19,IF(K49<35,29,IF(K49<45,39,IF(K49<60,49,79)))), IF(L49="INR_TIERS",IF(K49<40,29,IF(K49<70,49,99)), IF(L49="BRL_90",IF(K49<3,2.9,IF(K49<6,4.9,IF(K49<10,6.9,9.9))), IF(L49="IDR_000",ROUND(K49/1000,0)*1000, IF(L49="JPY_00",ROUND(K49/100,0)*100, IF(L49="KRW_000",ROUND(K49/1000,0)*1000, IF(L49="VND_000",ROUND(K49/1000,0)*1000, IF(OR(L49="USD_99",L49="EUR_99",L49="GBP_99",L49="CAD_99",L49="AUD_99",L49="PLN_99"),MAX(0.49,ROUND(K49,0)-0.01), IF(L49="MXN_00",ROUND(K49,0),IF(L49="THB_00",ROUND(K49,0),ROUND(K49,2))))))))))) -> 4.29 | N49: =M49/J49 -> 0.49024095 | P49: =IFERROR(__xludf.DUMMYFUNCTION("GOOGLEFINANCE(""CURRENCY:USDSVC"")"),8.750798999999999) -> 8.750799
A50: Eritre | B50: Eritrea | C50: ER | D50: ERN | E50: 0.15 | F50: E | G50: =Dashboard!$B$3 -> 1 | H50: =MAX(Dashboard!$B$4,G50*E50) -> 0.49 | I50: 1 | J50: =IFERROR(__xludf.DUMMYFUNCTION("GOOGLEFINANCE(""CURRENCY:USDERN"")"),"#N/A") -> #N/A | K50: =H50*I50*J50 -> #N/A | M50: =IF(L50="TRY_TIERS",IF(K50<25,19,IF(K50<35,29,IF(K50<45,39,IF(K50<60,49,79)))), IF(L50="INR_TIERS",IF(K50<40,29,IF(K50<70,49,99)), IF(L50="BRL_90",IF(K50<3,2.9,IF(K50<6,4.9,IF(K50<10,6.9,9.9))), IF(L50="IDR_000",ROUND(K50/1000,0)*1000, IF(L50="JPY_00",ROUND(K50/100,0)*100, IF(L50="KRW_000",ROUND(K50/1000,0)*1000, IF(L50="VND_000",ROUND(K50/1000,0)*1000, IF(OR(L50="USD_99",L50="EUR_99",L50="GBP_99",L50="CAD_99",L50="AUD_99",L50="PLN_99"),MAX(0.49,ROUND(K50,0)-0.01), IF(L50="MXN_00",ROUND(K50,0),IF(L50="THB_00",ROUND(K50,0),ROUND(K50,2))))))))))) -> #N/A | N50: =M50/J50 -> #N/A | P50: =IFERROR(__xludf.DUMMYFUNCTION("GOOGLEFINANCE(""CURRENCY:USDERN"")"),"#N/A") -> #N/A
A51: Estonya | B51: Estonia | C51: EE | D51: EUR | E51: 0.65 | F51: B | G51: =Dashboard!$B$3 -> 1 | H51: =MAX(Dashboard!$B$4,G51*E51) -> 0.65 | I51: 1 | J51: =IFERROR(__xludf.DUMMYFUNCTION("GOOGLEFINANCE(""CURRENCY:USDEUR"")"),0.8519) -> 0.8519 | K51: =H51*I51*J51 -> 0.553735 | M51: =IF(L51="TRY_TIERS",IF(K51<25,19,IF(K51<35,29,IF(K51<45,39,IF(K51<60,49,79)))), IF(L51="INR_TIERS",IF(K51<40,29,IF(K51<70,49,99)), IF(L51="BRL_90",IF(K51<3,2.9,IF(K51<6,4.9,IF(K51<10,6.9,9.9))), IF(L51="IDR_000",ROUND(K51/1000,0)*1000, IF(L51="JPY_00",ROUND(K51/100,0)*100, IF(L51="KRW_000",ROUND(K51/1000,0)*1000, IF(L51="VND_000",ROUND(K51/1000,0)*1000, IF(OR(L51="USD_99",L51="EUR_99",L51="GBP_99",L51="CAD_99",L51="AUD_99",L51="PLN_99"),MAX(0.49,ROUND(K51,0)-0.01), IF(L51="MXN_00",ROUND(K51,0),IF(L51="THB_00",ROUND(K51,0),ROUND(K51,2))))))))))) -> 0.55 | N51: =M51/J51 -> 0.64561568 | P51: =IFERROR(__xludf.DUMMYFUNCTION("GOOGLEFINANCE(""CURRENCY:USDEUR"")"),0.8519) -> 0.8519
A52: Fiji | B52: Fiji | C52: FJ | D52: FJD | E52: 0.4 | F52: D | G52: =Dashboard!$B$3 -> 1 | H52: =MAX(Dashboard!$B$4,G52*E52) -> 0.49 | I52: 1 | J52: =IFERROR(__xludf.DUMMYFUNCTION("GOOGLEFINANCE(""CURRENCY:USDFJD"")"),2.1853499999999997) -> 2.18535 | K52: =H52*I52*J52 -> 1.0708215 | M52: =IF(L52="TRY_TIERS",IF(K52<25,19,IF(K52<35,29,IF(K52<45,39,IF(K52<60,49,79)))), IF(L52="INR_TIERS",IF(K52<40,29,IF(K52<70,49,99)), IF(L52="BRL_90",IF(K52<3,2.9,IF(K52<6,4.9,IF(K52<10,6.9,9.9))), IF(L52="IDR_000",ROUND(K52/1000,0)*1000, IF(L52="JPY_00",ROUND(K52/100,0)*100, IF(L52="KRW_000",ROUND(K52/1000,0)*1000, IF(L52="VND_000",ROUND(K52/1000,0)*1000, IF(OR(L52="USD_99",L52="EUR_99",L52="GBP_99",L52="CAD_99",L52="AUD_99",L52="PLN_99"),MAX(0.49,ROUND(K52,0)-0.01), IF(L52="MXN_00",ROUND(K52,0),IF(L52="THB_00",ROUND(K52,0),ROUND(K52,2))))))))))) -> 1.07 | N52: =M52/J52 -> 0.48962409 | P52: =IFERROR(__xludf.DUMMYFUNCTION("GOOGLEFINANCE(""CURRENCY:USDFJD"")"),2.1853499999999997) -> 2.18535
A53: Finlandiya | B53: Finland | C53: FI | D53: EUR | E53: 0.85 | F53: A | G53: =Dashboard!$B$3 -> 1 | H53: =MAX(Dashboard!$B$4,G53*E53) -> 0.85 | I53: 1 | J53: =IFERROR(__xludf.DUMMYFUNCTION("GOOGLEFINANCE(""CURRENCY:USDEUR"")"),0.8519) -> 0.8519 | K53: =H53*I53*J53 -> 0.724115 | M53: =IF(L53="TRY_TIERS",IF(K53<25,19,IF(K53<35,29,IF(K53<45,39,IF(K53<60,49,79)))), IF(L53="INR_TIERS",IF(K53<40,29,IF(K53<70,49,99)), IF(L53="BRL_90",IF(K53<3,2.9,IF(K53<6,4.9,IF(K53<10,6.9,9.9))), IF(L53="IDR_000",ROUND(K53/1000,0)*1000, IF(L53="JPY_00",ROUND(K53/100,0)*100, IF(L53="KRW_000",ROUND(K53/1000,0)*1000, IF(L53="VND_000",ROUND(K53/1000,0)*1000, IF(OR(L53="USD_99",L53="EUR_99",L53="GBP_99",L53="CAD_99",L53="AUD_99",L53="PLN_99"),MAX(0.49,ROUND(K53,0)-0.01), IF(L53="MXN_00",ROUND(K53,0),IF(L53="THB_00",ROUND(K53,0),ROUND(K53,2))))))))))) -> 0.72 | N53: =M53/J53 -> 0.84516962 | P53: =IFERROR(__xludf.DUMMYFUNCTION("GOOGLEFINANCE(""CURRENCY:USDEUR"")"),0.8519) -> 0.8519
A54: Fransa | B54: France | C54: FR | D54: EUR | E54: 0.82 | F54: A | G54: =Dashboard!$B$3 -> 1 | H54: =MAX(Dashboard!$B$4,G54*E54) -> 0.82 | I54: 1 | J54: =IFERROR(__xludf.DUMMYFUNCTION("GOOGLEFINANCE(""CURRENCY:USDEUR"")"),0.8519) -> 0.8519 | K54: =H54*I54*J54 -> 0.698558 | M54: =IF(L54="TRY_TIERS",IF(K54<25,19,IF(K54<35,29,IF(K54<45,39,IF(K54<60,49,79)))), IF(L54="INR_TIERS",IF(K54<40,29,IF(K54<70,49,99)), IF(L54="BRL_90",IF(K54<3,2.9,IF(K54<6,4.9,IF(K54<10,6.9,9.9))), IF(L54="IDR_000",ROUND(K54/1000,0)*1000, IF(L54="JPY_00",ROUND(K54/100,0)*100, IF(L54="KRW_000",ROUND(K54/1000,0)*1000, IF(L54="VND_000",ROUND(K54/1000,0)*1000, IF(OR(L54="USD_99",L54="EUR_99",L54="GBP_99",L54="CAD_99",L54="AUD_99",L54="PLN_99"),MAX(0.49,ROUND(K54,0)-0.01), IF(L54="MXN_00",ROUND(K54,0),IF(L54="THB_00",ROUND(K54,0),ROUND(K54,2))))))))))) -> 0.7 | N54: =M54/J54 -> 0.82169269 | P54: =IFERROR(__xludf.DUMMYFUNCTION("GOOGLEFINANCE(""CURRENCY:USDEUR"")"),0.8519) -> 0.8519
A55: Gabon | B55: Gabon | C55: GA | D55: XAF | E55: 0.4 | F55: D | G55: =Dashboard!$B$3 -> 1 | H55: =MAX(Dashboard!$B$4,G55*E55) -> 0.49 | I55: 1 | J55: =IFERROR(__xludf.DUMMYFUNCTION("GOOGLEFINANCE(""CURRENCY:USDXAF"")"),558.7654) -> 558.7654 | K55: =H55*I55*J55 -> 273.79505 | M55: =IF(L55="TRY_TIERS",IF(K55<25,19,IF(K55<35,29,IF(K55<45,39,IF(K55<60,49,79)))), IF(L55="INR_TIERS",IF(K55<40,29,IF(K55<70,49,99)), IF(L55="BRL_90",IF(K55<3,2.9,IF(K55<6,4.9,IF(K55<10,6.9,9.9))), IF(L55="IDR_000",ROUND(K55/1000,0)*1000, IF(L55="JPY_00",ROUND(K55/100,0)*100, IF(L55="KRW_000",ROUND(K55/1000,0)*1000, IF(L55="VND_000",ROUND(K55/1000,0)*1000, IF(OR(L55="USD_99",L55="EUR_99",L55="GBP_99",L55="CAD_99",L55="AUD_99",L55="PLN_99"),MAX(0.49,ROUND(K55,0)-0.01), IF(L55="MXN_00",ROUND(K55,0),IF(L55="THB_00",ROUND(K55,0),ROUND(K55,2))))))))))) -> 273.8 | N55: =M55/J55 -> 0.49000887 | P55: =IFERROR(__xludf.DUMMYFUNCTION("GOOGLEFINANCE(""CURRENCY:USDXAF"")"),558.7654) -> 558.7654
A56: Gambiya | B56: Gambia | C56: GM | D56: GMD | E56: 0.18 | F56: E | G56: =Dashboard!$B$3 -> 1 | H56: =MAX(Dashboard!$B$4,G56*E56) -> 0.49 | I56: 1 | J56: =IFERROR(__xludf.DUMMYFUNCTION("GOOGLEFINANCE(""CURRENCY:USDGMD"")"),73.5) -> 73.5 | K56: =H56*I56*J56 -> 36.015 | M56: =IF(L56="TRY_TIERS",IF(K56<25,19,IF(K56<35,29,IF(K56<45,39,IF(K56<60,49,79)))), IF(L56="INR_TIERS",IF(K56<40,29,IF(K56<70,49,99)), IF(L56="BRL_90",IF(K56<3,2.9,IF(K56<6,4.9,IF(K56<10,6.9,9.9))), IF(L56="IDR_000",ROUND(K56/1000,0)*1000, IF(L56="JPY_00",ROUND(K56/100,0)*100, IF(L56="KRW_000",ROUND(K56/1000,0)*1000, IF(L56="VND_000",ROUND(K56/1000,0)*1000, IF(OR(L56="USD_99",L56="EUR_99",L56="GBP_99",L56="CAD_99",L56="AUD_99",L56="PLN_99"),MAX(0.49,ROUND(K56,0)-0.01), IF(L56="MXN_00",ROUND(K56,0),IF(L56="THB_00",ROUND(K56,0),ROUND(K56,2))))))))))) -> 36.02 | N56: =M56/J56 -> 0.49006803 | P56: =IFERROR(__xludf.DUMMYFUNCTION("GOOGLEFINANCE(""CURRENCY:USDGMD"")"),73.5) -> 73.5
A57: Gürcistan | B57: Georgia | C57: GE | D57: GEL | E57: 0.35 | F57: D | G57: =Dashboard!$B$3 -> 1 | H57: =MAX(Dashboard!$B$4,G57*E57) -> 0.49 | I57: 1 | J57: =IFERROR(__xludf.DUMMYFUNCTION("GOOGLEFINANCE(""CURRENCY:USDGEL"")"),2.67) -> 2.67 | K57: =H57*I57*J57 -> 1.3083 | M57: =IF(L57="TRY_TIERS",IF(K57<25,19,IF(K57<35,29,IF(K57<45,39,IF(K57<60,49,79)))), IF(L57="INR_TIERS",IF(K57<40,29,IF(K57<70,49,99)), IF(L57="BRL_90",IF(K57<3,2.9,IF(K57<6,4.9,IF(K57<10,6.9,9.9))), IF(L57="IDR_000",ROUND(K57/1000,0)*1000, IF(L57="JPY_00",ROUND(K57/100,0)*100, IF(L57="KRW_000",ROUND(K57/1000,0)*1000, IF(L57="VND_000",ROUND(K57/1000,0)*1000, IF(OR(L57="USD_99",L57="EUR_99",L57="GBP_99",L57="CAD_99",L57="AUD_99",L57="PLN_99"),MAX(0.49,ROUND(K57,0)-0.01), IF(L57="MXN_00",ROUND(K57,0),IF(L57="THB_00",ROUND(K57,0),ROUND(K57,2))))))))))) -> 1.31 | N57: =M57/J57 -> 0.4906367 | P57: =IFERROR(__xludf.DUMMYFUNCTION("GOOGLEFINANCE(""CURRENCY:USDGEL"")"),2.67) -> 2.67
A58: Almanya | B58: Germany | C58: DE | D58: EUR | E58: 0.85 | F58: =IF(E58>=0.8,"A",IF(E58>=0.6,"B",IF(E58>=0.4,"C",IF(E58>=0.2,"D","E")))) -> A | G58: =Dashboard!$B$3 -> 1 | H58: =MAX(Dashboard!$B$4,G58*E58) -> 0.85 | I58: 1 | J58: =IFERROR(__xludf.DUMMYFUNCTION("GOOGLEFINANCE(""CURRENCY:USDEUR"")"),0.8519) -> 0.8519 | K58: =H58*I58*J58 -> 0.724115 | L58: EUR_99 | M58: =IF(L58="TRY_TIERS",IF(K58<25,19,IF(K58<35,29,IF(K58<45,39,IF(K58<60,49,79)))), IF(L58="INR_TIERS",IF(K58<40,29,IF(K58<70,49,99)), IF(L58="BRL_90",IF(K58<3,2.9,IF(K58<6,4.9,IF(K58<10,6.9,9.9))), IF(L58="IDR_000",ROUND(K58/1000,0)*1000, IF(L58="JPY_00",ROUND(K58/100,0)*100, IF(L58="KRW_000",ROUND(K58/1000,0)*1000, IF(L58="VND_000",ROUND(K58/1000,0)*1000, IF(OR(L58="USD_99",L58="EUR_99",L58="GBP_99",L58="CAD_99",L58="AUD_99",L58="PLN_99"),MAX(0.49,ROUND(K58,0)-0.01), IF(L58="MXN_00",ROUND(K58,0),IF(L58="THB_00",ROUND(K58,0),ROUND(K58,2))))))))))) -> 0.99 | N58: =M58/J58 -> 1.1621082 | O58: =IF(N58<Dashboard!$B$4,"Below global min",IF(AND(E58>=0.8,N58<Dashboard!$B$5),"Raise high-PPP floor","OK")) -> Raise high-PPP floor | P58: =IFERROR(__xludf.DUMMYFUNCTION("GOOGLEFINANCE(""CURRENCY:USDEUR"")"),0.8519) -> 0.8519 | Q58: EU premium market
A59: Gana | B59: Ghana | C59: GH | D59: GHS | E59: 0.22 | F59: E | G59: =Dashboard!$B$3 -> 1 | H59: =MAX(Dashboard!$B$4,G59*E59) -> 0.49 | I59: 1 | J59: =IFERROR(__xludf.DUMMYFUNCTION("GOOGLEFINANCE(""CURRENCY:USDGHS"")"),11.29109) -> 11.29109 | K59: =H59*I59*J59 -> 5.5326341 | M59: =IF(L59="TRY_TIERS",IF(K59<25,19,IF(K59<35,29,IF(K59<45,39,IF(K59<60,49,79)))), IF(L59="INR_TIERS",IF(K59<40,29,IF(K59<70,49,99)), IF(L59="BRL_90",IF(K59<3,2.9,IF(K59<6,4.9,IF(K59<10,6.9,9.9))), IF(L59="IDR_000",ROUND(K59/1000,0)*1000, IF(L59="JPY_00",ROUND(K59/100,0)*100, IF(L59="KRW_000",ROUND(K59/1000,0)*1000, IF(L59="VND_000",ROUND(K59/1000,0)*1000, IF(OR(L59="USD_99",L59="EUR_99",L59="GBP_99",L59="CAD_99",L59="AUD_99",L59="PLN_99"),MAX(0.49,ROUND(K59,0)-0.01), IF(L59="MXN_00",ROUND(K59,0),IF(L59="THB_00",ROUND(K59,0),ROUND(K59,2))))))))))) -> 5.53 | N59: =M59/J59 -> 0.48976671 | P59: =IFERROR(__xludf.DUMMYFUNCTION("GOOGLEFINANCE(""CURRENCY:USDGHS"")"),11.29109) -> 11.29109
A60: Cebelitarık | B60: Gibraltar | C60: GI | D60: GIP | E60: 0.9 | F60: A | G60: =Dashboard!$B$3 -> 1 | H60: =MAX(Dashboard!$B$4,G60*E60) -> 0.9 | I60: 1 | J60: =IFERROR(__xludf.DUMMYFUNCTION("GOOGLEFINANCE(""CURRENCY:USDGIP"")"),"#N/A") -> #N/A | K60: =H60*I60*J60 -> #N/A | M60: =IF(L60="TRY_TIERS",IF(K60<25,19,IF(K60<35,29,IF(K60<45,39,IF(K60<60,49,79)))), IF(L60="INR_TIERS",IF(K60<40,29,IF(K60<70,49,99)), IF(L60="BRL_90",IF(K60<3,2.9,IF(K60<6,4.9,IF(K60<10,6.9,9.9))), IF(L60="IDR_000",ROUND(K60/1000,0)*1000, IF(L60="JPY_00",ROUND(K60/100,0)*100, IF(L60="KRW_000",ROUND(K60/1000,0)*1000, IF(L60="VND_000",ROUND(K60/1000,0)*1000, IF(OR(L60="USD_99",L60="EUR_99",L60="GBP_99",L60="CAD_99",L60="AUD_99",L60="PLN_99"),MAX(0.49,ROUND(K60,0)-0.01), IF(L60="MXN_00",ROUND(K60,0),IF(L60="THB_00",ROUND(K60,0),ROUND(K60,2))))))))))) -> #N/A | N60: =M60/J60 -> #N/A | P60: =IFERROR(__xludf.DUMMYFUNCTION("GOOGLEFINANCE(""CURRENCY:USDGIP"")"),"#N/A") -> #N/A
A61: Yunanistan | B61: Greece | C61: GR | D61: EUR | E61: 0.65 | F61: B | G61: =Dashboard!$B$3 -> 1 | H61: =MAX(Dashboard!$B$4,G61*E61) -> 0.65 | I61: 1 | J61: =IFERROR(__xludf.DUMMYFUNCTION("GOOGLEFINANCE(""CURRENCY:USDEUR"")"),0.8519) -> 0.8519 | K61: =H61*I61*J61 -> 0.553735 | M61: =IF(L61="TRY_TIERS",IF(K61<25,19,IF(K61<35,29,IF(K61<45,39,IF(K61<60,49,79)))), IF(L61="INR_TIERS",IF(K61<40,29,IF(K61<70,49,99)), IF(L61="BRL_90",IF(K61<3,2.9,IF(K61<6,4.9,IF(K61<10,6.9,9.9))), IF(L61="IDR_000",ROUND(K61/1000,0)*1000, IF(L61="JPY_00",ROUND(K61/100,0)*100, IF(L61="KRW_000",ROUND(K61/1000,0)*1000, IF(L61="VND_000",ROUND(K61/1000,0)*1000, IF(OR(L61="USD_99",L61="EUR_99",L61="GBP_99",L61="CAD_99",L61="AUD_99",L61="PLN_99"),MAX(0.49,ROUND(K61,0)-0.01), IF(L61="MXN_00",ROUND(K61,0),IF(L61="THB_00",ROUND(K61,0),ROUND(K61,2))))))))))) -> 0.55 | N61: =M61/J61 -> 0.64561568 | P61: =IFERROR(__xludf.DUMMYFUNCTION("GOOGLEFINANCE(""CURRENCY:USDEUR"")"),0.8519) -> 0.8519
A62: Grenada | B62: Grenada | C62: GD | D62: XCD | E62: 0.55 | F62: C | G62: =Dashboard!$B$3 -> 1 | H62: =MAX(Dashboard!$B$4,G62*E62) -> 0.55 | I62: 1 | J62: =IFERROR(__xludf.DUMMYFUNCTION("GOOGLEFINANCE(""CURRENCY:USDXCD"")"),2.70255) -> 2.70255 | K62: =H62*I62*J62 -> 1.4864025 | M62: =IF(L62="TRY_TIERS",IF(K62<25,19,IF(K62<35,29,IF(K62<45,39,IF(K62<60,49,79)))), IF(L62="INR_TIERS",IF(K62<40,29,IF(K62<70,49,99)), IF(L62="BRL_90",IF(K62<3,2.9,IF(K62<6,4.9,IF(K62<10,6.9,9.9))), IF(L62="IDR_000",ROUND(K62/1000,0)*1000, IF(L62="JPY_00",ROUND(K62/100,0)*100, IF(L62="KRW_000",ROUND(K62/1000,0)*1000, IF(L62="VND_000",ROUND(K62/1000,0)*1000, IF(OR(L62="USD_99",L62="EUR_99",L62="GBP_99",L62="CAD_99",L62="AUD_99",L62="PLN_99"),MAX(0.49,ROUND(K62,0)-0.01), IF(L62="MXN_00",ROUND(K62,0),IF(L62="THB_00",ROUND(K62,0),ROUND(K62,2))))))))))) -> 1.49 | N62: =M62/J62 -> 0.55133115 | P62: =IFERROR(__xludf.DUMMYFUNCTION("GOOGLEFINANCE(""CURRENCY:USDXCD"")"),2.70255) -> 2.70255
A63: Guatemala | B63: Guatemala | C63: GT | D63: GTQ | E63: 0.3 | F63: D | G63: =Dashboard!$B$3 -> 1 | H63: =MAX(Dashboard!$B$4,G63*E63) -> 0.49 | I63: 1 | J63: =IFERROR(__xludf.DUMMYFUNCTION("GOOGLEFINANCE(""CURRENCY:USDGTQ"")"),7.630745999999999) -> 7.630746 | K63: =H63*I63*J63 -> 3.7390655 | M63: =IF(L63="TRY_TIERS",IF(K63<25,19,IF(K63<35,29,IF(K63<45,39,IF(K63<60,49,79)))), IF(L63="INR_TIERS",IF(K63<40,29,IF(K63<70,49,99)), IF(L63="BRL_90",IF(K63<3,2.9,IF(K63<6,4.9,IF(K63<10,6.9,9.9))), IF(L63="IDR_000",ROUND(K63/1000,0)*1000, IF(L63="JPY_00",ROUND(K63/100,0)*100, IF(L63="KRW_000",ROUND(K63/1000,0)*1000, IF(L63="VND_000",ROUND(K63/1000,0)*1000, IF(OR(L63="USD_99",L63="EUR_99",L63="GBP_99",L63="CAD_99",L63="AUD_99",L63="PLN_99"),MAX(0.49,ROUND(K63,0)-0.01), IF(L63="MXN_00",ROUND(K63,0),IF(L63="THB_00",ROUND(K63,0),ROUND(K63,2))))))))))) -> 3.74 | N63: =M63/J63 -> 0.49012246 | P63: =IFERROR(__xludf.DUMMYFUNCTION("GOOGLEFINANCE(""CURRENCY:USDGTQ"")"),7.630745999999999) -> 7.630746
A64: Gine | B64: Guinea | C64: GN | D64: GNF | E64: 0.15 | F64: E | G64: =Dashboard!$B$3 -> 1 | H64: =MAX(Dashboard!$B$4,G64*E64) -> 0.49 | I64: 1 | J64: =IFERROR(__xludf.DUMMYFUNCTION("GOOGLEFINANCE(""CURRENCY:USDGNF"")"),8775.576000000001) -> 8775.576 | K64: =H64*I64*J64 -> 4300.0322 | M64: =IF(L64="TRY_TIERS",IF(K64<25,19,IF(K64<35,29,IF(K64<45,39,IF(K64<60,49,79)))), IF(L64="INR_TIERS",IF(K64<40,29,IF(K64<70,49,99)), IF(L64="BRL_90",IF(K64<3,2.9,IF(K64<6,4.9,IF(K64<10,6.9,9.9))), IF(L64="IDR_000",ROUND(K64/1000,0)*1000, IF(L64="JPY_00",ROUND(K64/100,0)*100, IF(L64="KRW_000",ROUND(K64/1000,0)*1000, IF(L64="VND_000",ROUND(K64/1000,0)*1000, IF(OR(L64="USD_99",L64="EUR_99",L64="GBP_99",L64="CAD_99",L64="AUD_99",L64="PLN_99"),MAX(0.49,ROUND(K64,0)-0.01), IF(L64="MXN_00",ROUND(K64,0),IF(L64="THB_00",ROUND(K64,0),ROUND(K64,2))))))))))) -> 4300.03 | N64: =M64/J64 -> 0.48999974 | P64: =IFERROR(__xludf.DUMMYFUNCTION("GOOGLEFINANCE(""CURRENCY:USDGNF"")"),8775.576000000001) -> 8775.576
A65: Gine-Bissau | B65: Guinea-Bissau | C65: GW | D65: XOF | E65: 0.15 | F65: E | G65: =Dashboard!$B$3 -> 1 | H65: =MAX(Dashboard!$B$4,G65*E65) -> 0.49 | I65: 1 | J65: =IFERROR(__xludf.DUMMYFUNCTION("GOOGLEFINANCE(""CURRENCY:USDXOF"")"),558.7654) -> 558.7654 | K65: =H65*I65*J65 -> 273.79505 | M65: =IF(L65="TRY_TIERS",IF(K65<25,19,IF(K65<35,29,IF(K65<45,39,IF(K65<60,49,79)))), IF(L65="INR_TIERS",IF(K65<40,29,IF(K65<70,49,99)), IF(L65="BRL_90",IF(K65<3,2.9,IF(K65<6,4.9,IF(K65<10,6.9,9.9))), IF(L65="IDR_000",ROUND(K65/1000,0)*1000, IF(L65="JPY_00",ROUND(K65/100,0)*100, IF(L65="KRW_000",ROUND(K65/1000,0)*1000, IF(L65="VND_000",ROUND(K65/1000,0)*1000, IF(OR(L65="USD_99",L65="EUR_99",L65="GBP_99",L65="CAD_99",L65="AUD_99",L65="PLN_99"),MAX(0.49,ROUND(K65,0)-0.01), IF(L65="MXN_00",ROUND(K65,0),IF(L65="THB_00",ROUND(K65,0),ROUND(K65,2))))))))))) -> 273.8 | N65: =M65/J65 -> 0.49000887 | P65: =IFERROR(__xludf.DUMMYFUNCTION("GOOGLEFINANCE(""CURRENCY:USDXOF"")"),558.7654) -> 558.7654
A66: Haiti | B66: Haiti | C66: HT | D66: HTG | E66: 0.15 | F66: E | G66: =Dashboard!$B$3 -> 1 | H66: =MAX(Dashboard!$B$4,G66*E66) -> 0.49 | I66: 1 | J66: =IFERROR(__xludf.DUMMYFUNCTION("GOOGLEFINANCE(""CURRENCY:USDHTG"")"),130.6626) -> 130.6626 | K66: =H66*I66*J66 -> 64.024674 | M66: =IF(L66="TRY_TIERS",IF(K66<25,19,IF(K66<35,29,IF(K66<45,39,IF(K66<60,49,79)))), IF(L66="INR_TIERS",IF(K66<40,29,IF(K66<70,49,99)), IF(L66="BRL_90",IF(K66<3,2.9,IF(K66<6,4.9,IF(K66<10,6.9,9.9))), IF(L66="IDR_000",ROUND(K66/1000,0)*1000, IF(L66="JPY_00",ROUND(K66/100,0)*100, IF(L66="KRW_000",ROUND(K66/1000,0)*1000, IF(L66="VND_000",ROUND(K66/1000,0)*1000, IF(OR(L66="USD_99",L66="EUR_99",L66="GBP_99",L66="CAD_99",L66="AUD_99",L66="PLN_99"),MAX(0.49,ROUND(K66,0)-0.01), IF(L66="MXN_00",ROUND(K66,0),IF(L66="THB_00",ROUND(K66,0),ROUND(K66,2))))))))))) -> 64.02 | N66: =M66/J66 -> 0.48996423 | P66: =IFERROR(__xludf.DUMMYFUNCTION("GOOGLEFINANCE(""CURRENCY:USDHTG"")"),130.6626) -> 130.6626
A67: Honduras | B67: Honduras | C67: HN | D67: HNL | E67: 0.25 | F67: E | G67: =Dashboard!$B$3 -> 1 | H67: =MAX(Dashboard!$B$4,G67*E67) -> 0.49 | I67: 1 | J67: =IFERROR(__xludf.DUMMYFUNCTION("GOOGLEFINANCE(""CURRENCY:USDHNL"")"),26.5942) -> 26.5942 | K67: =H67*I67*J67 -> 13.031158 | M67: =IF(L67="TRY_TIERS",IF(K67<25,19,IF(K67<35,29,IF(K67<45,39,IF(K67<60,49,79)))), IF(L67="INR_TIERS",IF(K67<40,29,IF(K67<70,49,99)), IF(L67="BRL_90",IF(K67<3,2.9,IF(K67<6,4.9,IF(K67<10,6.9,9.9))), IF(L67="IDR_000",ROUND(K67/1000,0)*1000, IF(L67="JPY_00",ROUND(K67/100,0)*100, IF(L67="KRW_000",ROUND(K67/1000,0)*1000, IF(L67="VND_000",ROUND(K67/1000,0)*1000, IF(OR(L67="USD_99",L67="EUR_99",L67="GBP_99",L67="CAD_99",L67="AUD_99",L67="PLN_99"),MAX(0.49,ROUND(K67,0)-0.01), IF(L67="MXN_00",ROUND(K67,0),IF(L67="THB_00",ROUND(K67,0),ROUND(K67,2))))))))))) -> 13.03 | N67: =M67/J67 -> 0.48995646 | P67: =IFERROR(__xludf.DUMMYFUNCTION("GOOGLEFINANCE(""CURRENCY:USDHNL"")"),26.5942) -> 26.5942
A68: HongKong | B68: HongKong | C68: HK | D68: HKD | E68: 0.95 | F68: A | G68: =Dashboard!$B$3 -> 1 | H68: =MAX(Dashboard!$B$4,G68*E68) -> 0.95 | I68: 1 | J68: =IFERROR(__xludf.DUMMYFUNCTION("GOOGLEFINANCE(""CURRENCY:USDHKD"")"),7.82905) -> 7.82905 | K68: =H68*I68*J68 -> 7.4375975 | M68: =IF(L68="TRY_TIERS",IF(K68<25,19,IF(K68<35,29,IF(K68<45,39,IF(K68<60,49,79)))), IF(L68="INR_TIERS",IF(K68<40,29,IF(K68<70,49,99)), IF(L68="BRL_90",IF(K68<3,2.9,IF(K68<6,4.9,IF(K68<10,6.9,9.9))), IF(L68="IDR_000",ROUND(K68/1000,0)*1000, IF(L68="JPY_00",ROUND(K68/100,0)*100, IF(L68="KRW_000",ROUND(K68/1000,0)*1000, IF(L68="VND_000",ROUND(K68/1000,0)*1000, IF(OR(L68="USD_99",L68="EUR_99",L68="GBP_99",L68="CAD_99",L68="AUD_99",L68="PLN_99"),MAX(0.49,ROUND(K68,0)-0.01), IF(L68="MXN_00",ROUND(K68,0),IF(L68="THB_00",ROUND(K68,0),ROUND(K68,2))))))))))) -> 7.44 | N68: =M68/J68 -> 0.95030687 | P68: =IFERROR(__xludf.DUMMYFUNCTION("GOOGLEFINANCE(""CURRENCY:USDHKD"")"),7.82905) -> 7.82905
A69: Macaristan | B69: Hungary | C69: HU | D69: HUF | E69: 0.5 | F69: C | G69: =Dashboard!$B$3 -> 1 | H69: =MAX(Dashboard!$B$4,G69*E69) -> 0.5 | I69: 1 | J69: =IFERROR(__xludf.DUMMYFUNCTION("GOOGLEFINANCE(""CURRENCY:USDHUF"")"),304.6995) -> 304.6995 | K69: =H69*I69*J69 -> 152.34975 | M69: =IF(L69="TRY_TIERS",IF(K69<25,19,IF(K69<35,29,IF(K69<45,39,IF(K69<60,49,79)))), IF(L69="INR_TIERS",IF(K69<40,29,IF(K69<70,49,99)), IF(L69="BRL_90",IF(K69<3,2.9,IF(K69<6,4.9,IF(K69<10,6.9,9.9))), IF(L69="IDR_000",ROUND(K69/1000,0)*1000, IF(L69="JPY_00",ROUND(K69/100,0)*100, IF(L69="KRW_000",ROUND(K69/1000,0)*1000, IF(L69="VND_000",ROUND(K69/1000,0)*1000, IF(OR(L69="USD_99",L69="EUR_99",L69="GBP_99",L69="CAD_99",L69="AUD_99",L69="PLN_99"),MAX(0.49,ROUND(K69,0)-0.01), IF(L69="MXN_00",ROUND(K69,0),IF(L69="THB_00",ROUND(K69,0),ROUND(K69,2))))))))))) -> 152.35 | N69: =M69/J69 -> 0.50000082 | P69: =IFERROR(__xludf.DUMMYFUNCTION("GOOGLEFINANCE(""CURRENCY:USDHUF"")"),304.6995) -> 304.6995
A70: İzlanda | B70: Iceland | C70: IS | D70: ISK | E70: 0.95 | F70: A | G70: =Dashboard!$B$3 -> 1 | H70: =MAX(Dashboard!$B$4,G70*E70) -> 0.95 | I70: 1 | J70: =IFERROR(__xludf.DUMMYFUNCTION("GOOGLEFINANCE(""CURRENCY:USDISK"")"),122.34) -> 122.34 | K70: =H70*I70*J70 -> 116.223 | M70: =IF(L70="TRY_TIERS",IF(K70<25,19,IF(K70<35,29,IF(K70<45,39,IF(K70<60,49,79)))), IF(L70="INR_TIERS",IF(K70<40,29,IF(K70<70,49,99)), IF(L70="BRL_90",IF(K70<3,2.9,IF(K70<6,4.9,IF(K70<10,6.9,9.9))), IF(L70="IDR_000",ROUND(K70/1000,0)*1000, IF(L70="JPY_00",ROUND(K70/100,0)*100, IF(L70="KRW_000",ROUND(K70/1000,0)*1000, IF(L70="VND_000",ROUND(K70/1000,0)*1000, IF(OR(L70="USD_99",L70="EUR_99",L70="GBP_99",L70="CAD_99",L70="AUD_99",L70="PLN_99"),MAX(0.49,ROUND(K70,0)-0.01), IF(L70="MXN_00",ROUND(K70,0),IF(L70="THB_00",ROUND(K70,0),ROUND(K70,2))))))))))) -> 116.22 | N70: =M70/J70 -> 0.94997548 | P70: =IFERROR(__xludf.DUMMYFUNCTION("GOOGLEFINANCE(""CURRENCY:USDISK"")"),122.34) -> 122.34
A71: Hindistan | B71: India | C71: IN | D71: INR | E71: 0.2 | F71: =IF(E71>=0.8,"A",IF(E71>=0.6,"B",IF(E71>=0.4,"C",IF(E71>=0.2,"D","E")))) -> D | G71: =Dashboard!$B$3 -> 1 | H71: =MAX(Dashboard!$B$4,G71*E71) -> 0.49 | I71: 0.8 | J71: =IFERROR(__xludf.DUMMYFUNCTION("GOOGLEFINANCE(""CURRENCY:USDINR"")"),95.6405) -> 95.6405 | K71: =H71*I71*J71 -> 37.491076 | L71: INR_TIERS | M71: =IF(L71="TRY_TIERS",IF(K71<25,19,IF(K71<35,29,IF(K71<45,39,IF(K71<60,49,79)))), IF(L71="INR_TIERS",IF(K71<40,29,IF(K71<70,49,99)), IF(L71="BRL_90",IF(K71<3,2.9,IF(K71<6,4.9,IF(K71<10,6.9,9.9))), IF(L71="IDR_000",ROUND(K71/1000,0)*1000, IF(L71="JPY_00",ROUND(K71/100,0)*100, IF(L71="KRW_000",ROUND(K71/1000,0)*1000, IF(L71="VND_000",ROUND(K71/1000,0)*1000, IF(OR(L71="USD_99",L71="EUR_99",L71="GBP_99",L71="CAD_99",L71="AUD_99",L71="PLN_99"),MAX(0.49,ROUND(K71,0)-0.01), IF(L71="MXN_00",ROUND(K71,0),IF(L71="THB_00",ROUND(K71,0),ROUND(K71,2))))))))))) -> 29 | N71: =M71/J71 -> 0.30321882 | O71: =IF(N71<Dashboard!$B$4,"Below global min",IF(AND(E71>=0.8,N71<Dashboard!$B$5),"Raise high-PPP floor","OK")) -> Below global min | P71: =IFERROR(__xludf.DUMMYFUNCTION("GOOGLEFINANCE(""CURRENCY:USDINR"")"),95.6405) -> 95.6405 | Q71: Volume market
A72: Endonezya | B72: Indonesia | C72: ID | D72: IDR | E72: 0.25 | F72: =IF(E72>=0.8,"A",IF(E72>=0.6,"B",IF(E72>=0.4,"C",IF(E72>=0.2,"D","E")))) -> D | G72: =Dashboard!$B$3 -> 1 | H72: =MAX(Dashboard!$B$4,G72*E72) -> 0.49 | I72: 0.8 | J72: =IFERROR(__xludf.DUMMYFUNCTION("GOOGLEFINANCE(""CURRENCY:USDIDR"")"),17547.0) -> 17547 | K72: =H72*I72*J72 -> 6878.424 | L72: IDR_000 | M72: =IF(L72="TRY_TIERS",IF(K72<25,19,IF(K72<35,29,IF(K72<45,39,IF(K72<60,49,79)))), IF(L72="INR_TIERS",IF(K72<40,29,IF(K72<70,49,99)), IF(L72="BRL_90",IF(K72<3,2.9,IF(K72<6,4.9,IF(K72<10,6.9,9.9))), IF(L72="IDR_000",ROUND(K72/1000,0)*1000, IF(L72="JPY_00",ROUND(K72/100,0)*100, IF(L72="KRW_000",ROUND(K72/1000,0)*1000, IF(L72="VND_000",ROUND(K72/1000,0)*1000, IF(OR(L72="USD_99",L72="EUR_99",L72="GBP_99",L72="CAD_99",L72="AUD_99",L72="PLN_99"),MAX(0.49,ROUND(K72,0)-0.01), IF(L72="MXN_00",ROUND(K72,0),IF(L72="THB_00",ROUND(K72,0),ROUND(K72,2))))))))))) -> 7000 | N72: =M72/J72 -> 0.39892859 | O72: =IF(N72<Dashboard!$B$4,"Below global min",IF(AND(E72>=0.8,N72<Dashboard!$B$5),"Raise high-PPP floor","OK")) -> Below global min | P72: =IFERROR(__xludf.DUMMYFUNCTION("GOOGLEFINANCE(""CURRENCY:USDIDR"")"),17547.0) -> 17547
A73: Irak | B73: Iraq | C73: IQ | D73: IQD | E73: 0.3 | F73: D | G73: =Dashboard!$B$3 -> 1 | H73: =MAX(Dashboard!$B$4,G73*E73) -> 0.49 | I73: 1 | J73: =IFERROR(__xludf.DUMMYFUNCTION("GOOGLEFINANCE(""CURRENCY:USDIQD"")"),1310.107) -> 1310.107 | K73: =H73*I73*J73 -> 641.95243 | M73: =IF(L73="TRY_TIERS",IF(K73<25,19,IF(K73<35,29,IF(K73<45,39,IF(K73<60,49,79)))), IF(L73="INR_TIERS",IF(K73<40,29,IF(K73<70,49,99)), IF(L73="BRL_90",IF(K73<3,2.9,IF(K73<6,4.9,IF(K73<10,6.9,9.9))), IF(L73="IDR_000",ROUND(K73/1000,0)*1000, IF(L73="JPY_00",ROUND(K73/100,0)*100, IF(L73="KRW_000",ROUND(K73/1000,0)*1000, IF(L73="VND_000",ROUND(K73/1000,0)*1000, IF(OR(L73="USD_99",L73="EUR_99",L73="GBP_99",L73="CAD_99",L73="AUD_99",L73="PLN_99"),MAX(0.49,ROUND(K73,0)-0.01), IF(L73="MXN_00",ROUND(K73,0),IF(L73="THB_00",ROUND(K73,0),ROUND(K73,2))))))))))) -> 641.95 | N73: =M73/J73 -> 0.48999815 | P73: =IFERROR(__xludf.DUMMYFUNCTION("GOOGLEFINANCE(""CURRENCY:USDIQD"")"),1310.107) -> 1310.107
A74: İrlanda | B74: Ireland | C74: IE | D74: EUR | E74: 0.9 | F74: A | G74: =Dashboard!$B$3 -> 1 | H74: =MAX(Dashboard!$B$4,G74*E74) -> 0.9 | I74: 1 | J74: =IFERROR(__xludf.DUMMYFUNCTION("GOOGLEFINANCE(""CURRENCY:USDEUR"")"),0.8519) -> 0.8519 | K74: =H74*I74*J74 -> 0.76671 | M74: =IF(L74="TRY_TIERS",IF(K74<25,19,IF(K74<35,29,IF(K74<45,39,IF(K74<60,49,79)))), IF(L74="INR_TIERS",IF(K74<40,29,IF(K74<70,49,99)), IF(L74="BRL_90",IF(K74<3,2.9,IF(K74<6,4.9,IF(K74<10,6.9,9.9))), IF(L74="IDR_000",ROUND(K74/1000,0)*1000, IF(L74="JPY_00",ROUND(K74/100,0)*100, IF(L74="KRW_000",ROUND(K74/1000,0)*1000, IF(L74="VND_000",ROUND(K74/1000,0)*1000, IF(OR(L74="USD_99",L74="EUR_99",L74="GBP_99",L74="CAD_99",L74="AUD_99",L74="PLN_99"),MAX(0.49,ROUND(K74,0)-0.01), IF(L74="MXN_00",ROUND(K74,0),IF(L74="THB_00",ROUND(K74,0),ROUND(K74,2))))))))))) -> 0.77 | N74: =M74/J74 -> 0.90386196 | P74: =IFERROR(__xludf.DUMMYFUNCTION("GOOGLEFINANCE(""CURRENCY:USDEUR"")"),0.8519) -> 0.8519
A75: İsrail | B75: Israel | C75: IL | D75: ILS | E75: 0.9 | F75: A | G75: =Dashboard!$B$3 -> 1 | H75: =MAX(Dashboard!$B$4,G75*E75) -> 0.9 | I75: 1 | J75: =IFERROR(__xludf.DUMMYFUNCTION("GOOGLEFINANCE(""CURRENCY:USDILS"")"),2.91395) -> 2.91395 | K75: =H75*I75*J75 -> 2.622555 | M75: =IF(L75="TRY_TIERS",IF(K75<25,19,IF(K75<35,29,IF(K75<45,39,IF(K75<60,49,79)))), IF(L75="INR_TIERS",IF(K75<40,29,IF(K75<70,49,99)), IF(L75="BRL_90",IF(K75<3,2.9,IF(K75<6,4.9,IF(K75<10,6.9,9.9))), IF(L75="IDR_000",ROUND(K75/1000,0)*1000, IF(L75="JPY_00",ROUND(K75/100,0)*100, IF(L75="KRW_000",ROUND(K75/1000,0)*1000, IF(L75="VND_000",ROUND(K75/1000,0)*1000, IF(OR(L75="USD_99",L75="EUR_99",L75="GBP_99",L75="CAD_99",L75="AUD_99",L75="PLN_99"),MAX(0.49,ROUND(K75,0)-0.01), IF(L75="MXN_00",ROUND(K75,0),IF(L75="THB_00",ROUND(K75,0),ROUND(K75,2))))))))))) -> 2.62 | N75: =M75/J75 -> 0.89912318 | P75: =IFERROR(__xludf.DUMMYFUNCTION("GOOGLEFINANCE(""CURRENCY:USDILS"")"),2.91395) -> 2.91395
A76: İtalya | B76: Italy | C76: IT | D76: EUR | E76: 0.78 | F76: B | G76: =Dashboard!$B$3 -> 1 | H76: =MAX(Dashboard!$B$4,G76*E76) -> 0.78 | I76: 1 | J76: =IFERROR(__xludf.DUMMYFUNCTION("GOOGLEFINANCE(""CURRENCY:USDEUR"")"),0.8519) -> 0.8519 | K76: =H76*I76*J76 -> 0.664482 | M76: =IF(L76="TRY_TIERS",IF(K76<25,19,IF(K76<35,29,IF(K76<45,39,IF(K76<60,49,79)))), IF(L76="INR_TIERS",IF(K76<40,29,IF(K76<70,49,99)), IF(L76="BRL_90",IF(K76<3,2.9,IF(K76<6,4.9,IF(K76<10,6.9,9.9))), IF(L76="IDR_000",ROUND(K76/1000,0)*1000, IF(L76="JPY_00",ROUND(K76/100,0)*100, IF(L76="KRW_000",ROUND(K76/1000,0)*1000, IF(L76="VND_000",ROUND(K76/1000,0)*1000, IF(OR(L76="USD_99",L76="EUR_99",L76="GBP_99",L76="CAD_99",L76="AUD_99",L76="PLN_99"),MAX(0.49,ROUND(K76,0)-0.01), IF(L76="MXN_00",ROUND(K76,0),IF(L76="THB_00",ROUND(K76,0),ROUND(K76,2))))))))))) -> 0.66 | N76: =M76/J76 -> 0.77473882 | P76: =IFERROR(__xludf.DUMMYFUNCTION("GOOGLEFINANCE(""CURRENCY:USDEUR"")"),0.8519) -> 0.8519
A77: Jamaika | B77: Jamaica | C77: JM | D77: JMD | E77: 0.45 | F77: C | G77: =Dashboard!$B$3 -> 1 | H77: =MAX(Dashboard!$B$4,G77*E77) -> 0.49 | I77: 1 | J77: =IFERROR(__xludf.DUMMYFUNCTION("GOOGLEFINANCE(""CURRENCY:USDJMD"")"),158.0319) -> 158.0319 | K77: =H77*I77*J77 -> 77.435631 | M77: =IF(L77="TRY_TIERS",IF(K77<25,19,IF(K77<35,29,IF(K77<45,39,IF(K77<60,49,79)))), IF(L77="INR_TIERS",IF(K77<40,29,IF(K77<70,49,99)), IF(L77="BRL_90",IF(K77<3,2.9,IF(K77<6,4.9,IF(K77<10,6.9,9.9))), IF(L77="IDR_000",ROUND(K77/1000,0)*1000, IF(L77="JPY_00",ROUND(K77/100,0)*100, IF(L77="KRW_000",ROUND(K77/1000,0)*1000, IF(L77="VND_000",ROUND(K77/1000,0)*1000, IF(OR(L77="USD_99",L77="EUR_99",L77="GBP_99",L77="CAD_99",L77="AUD_99",L77="PLN_99"),MAX(0.49,ROUND(K77,0)-0.01), IF(L77="MXN_00",ROUND(K77,0),IF(L77="THB_00",ROUND(K77,0),ROUND(K77,2))))))))))) -> 77.44 | N77: =M77/J77 -> 0.49002765 | P77: =IFERROR(__xludf.DUMMYFUNCTION("GOOGLEFINANCE(""CURRENCY:USDJMD"")"),158.0319) -> 158.0319
A78: Japonya | B78: Japan | C78: JP | D78: JPY | E78: 0.75 | F78: =IF(E78>=0.8,"A",IF(E78>=0.6,"B",IF(E78>=0.4,"C",IF(E78>=0.2,"D","E")))) -> B | G78: =Dashboard!$B$3 -> 1 | H78: =MAX(Dashboard!$B$4,G78*E78) -> 0.75 | I78: 1 | J78: =IFERROR(__xludf.DUMMYFUNCTION("GOOGLEFINANCE(""CURRENCY:USDJPY"")"),157.6045) -> 157.6045 | K78: =H78*I78*J78 -> 118.20337 | L78: JPY_00 | M78: =IF(L78="TRY_TIERS",IF(K78<25,19,IF(K78<35,29,IF(K78<45,39,IF(K78<60,49,79)))), IF(L78="INR_TIERS",IF(K78<40,29,IF(K78<70,49,99)), IF(L78="BRL_90",IF(K78<3,2.9,IF(K78<6,4.9,IF(K78<10,6.9,9.9))), IF(L78="IDR_000",ROUND(K78/1000,0)*1000, IF(L78="JPY_00",ROUND(K78/100,0)*100, IF(L78="KRW_000",ROUND(K78/1000,0)*1000, IF(L78="VND_000",ROUND(K78/1000,0)*1000, IF(OR(L78="USD_99",L78="EUR_99",L78="GBP_99",L78="CAD_99",L78="AUD_99",L78="PLN_99"),MAX(0.49,ROUND(K78,0)-0.01), IF(L78="MXN_00",ROUND(K78,0),IF(L78="THB_00",ROUND(K78,0),ROUND(K78,2))))))))))) -> 100 | N78: =M78/J78 -> 0.63449965 | O78: =IF(N78<Dashboard!$B$4,"Below global min",IF(AND(E78>=0.8,N78<Dashboard!$B$5),"Raise high-PPP floor","OK")) -> OK | P78: =IFERROR(__xludf.DUMMYFUNCTION("GOOGLEFINANCE(""CURRENCY:USDJPY"")"),157.6045) -> 157.6045
A79: Ürdün | B79: Jordan | C79: JO | D79: JOD | E79: 0.45 | F79: C | G79: =Dashboard!$B$3 -> 1 | H79: =MAX(Dashboard!$B$4,G79*E79) -> 0.49 | I79: 1 | J79: =IFERROR(__xludf.DUMMYFUNCTION("GOOGLEFINANCE(""CURRENCY:USDJOD"")"),0.709) -> 0.709 | K79: =H79*I79*J79 -> 0.34741 | M79: =IF(L79="TRY_TIERS",IF(K79<25,19,IF(K79<35,29,IF(K79<45,39,IF(K79<60,49,79)))), IF(L79="INR_TIERS",IF(K79<40,29,IF(K79<70,49,99)), IF(L79="BRL_90",IF(K79<3,2.9,IF(K79<6,4.9,IF(K79<10,6.9,9.9))), IF(L79="IDR_000",ROUND(K79/1000,0)*1000, IF(L79="JPY_00",ROUND(K79/100,0)*100, IF(L79="KRW_000",ROUND(K79/1000,0)*1000, IF(L79="VND_000",ROUND(K79/1000,0)*1000, IF(OR(L79="USD_99",L79="EUR_99",L79="GBP_99",L79="CAD_99",L79="AUD_99",L79="PLN_99"),MAX(0.49,ROUND(K79,0)-0.01), IF(L79="MXN_00",ROUND(K79,0),IF(L79="THB_00",ROUND(K79,0),ROUND(K79,2))))))))))) -> 0.35 | N79: =M79/J79 -> 0.49365303 | P79: =IFERROR(__xludf.DUMMYFUNCTION("GOOGLEFINANCE(""CURRENCY:USDJOD"")"),0.709) -> 0.709
A80: Kazakistan | B80: Kazakhstan | C80: KZ | D80: KZT | E80: 0.45 | F80: C | G80: =Dashboard!$B$3 -> 1 | H80: =MAX(Dashboard!$B$4,G80*E80) -> 0.49 | I80: 1 | J80: =IFERROR(__xludf.DUMMYFUNCTION("GOOGLEFINANCE(""CURRENCY:USDKZT"")"),463.8784) -> 463.8784 | K80: =H80*I80*J80 -> 227.30042 | M80: =IF(L80="TRY_TIERS",IF(K80<25,19,IF(K80<35,29,IF(K80<45,39,IF(K80<60,49,79)))), IF(L80="INR_TIERS",IF(K80<40,29,IF(K80<70,49,99)), IF(L80="BRL_90",IF(K80<3,2.9,IF(K80<6,4.9,IF(K80<10,6.9,9.9))), IF(L80="IDR_000",ROUND(K80/1000,0)*1000, IF(L80="JPY_00",ROUND(K80/100,0)*100, IF(L80="KRW_000",ROUND(K80/1000,0)*1000, IF(L80="VND_000",ROUND(K80/1000,0)*1000, IF(OR(L80="USD_99",L80="EUR_99",L80="GBP_99",L80="CAD_99",L80="AUD_99",L80="PLN_99"),MAX(0.49,ROUND(K80,0)-0.01), IF(L80="MXN_00",ROUND(K80,0),IF(L80="THB_00",ROUND(K80,0),ROUND(K80,2))))))))))) -> 227.3 | N80: =M80/J80 -> 0.4899991 | P80: =IFERROR(__xludf.DUMMYFUNCTION("GOOGLEFINANCE(""CURRENCY:USDKZT"")"),463.8784) -> 463.8784
A81: Kenya | B81: Kenya | C81: KE | D81: KES | E81: 0.22 | F81: E | G81: =Dashboard!$B$3 -> 1 | H81: =MAX(Dashboard!$B$4,G81*E81) -> 0.49 | I81: 1 | J81: =IFERROR(__xludf.DUMMYFUNCTION("GOOGLEFINANCE(""CURRENCY:USDKES"")"),129.16) -> 129.16 | K81: =H81*I81*J81 -> 63.2884 | M81: =IF(L81="TRY_TIERS",IF(K81<25,19,IF(K81<35,29,IF(K81<45,39,IF(K81<60,49,79)))), IF(L81="INR_TIERS",IF(K81<40,29,IF(K81<70,49,99)), IF(L81="BRL_90",IF(K81<3,2.9,IF(K81<6,4.9,IF(K81<10,6.9,9.9))), IF(L81="IDR_000",ROUND(K81/1000,0)*1000, IF(L81="JPY_00",ROUND(K81/100,0)*100, IF(L81="KRW_000",ROUND(K81/1000,0)*1000, IF(L81="VND_000",ROUND(K81/1000,0)*1000, IF(OR(L81="USD_99",L81="EUR_99",L81="GBP_99",L81="CAD_99",L81="AUD_99",L81="PLN_99"),MAX(0.49,ROUND(K81,0)-0.01), IF(L81="MXN_00",ROUND(K81,0),IF(L81="THB_00",ROUND(K81,0),ROUND(K81,2))))))))))) -> 63.29 | N81: =M81/J81 -> 0.49001239 | P81: =IFERROR(__xludf.DUMMYFUNCTION("GOOGLEFINANCE(""CURRENCY:USDKES"")"),129.16) -> 129.16
A82: Kuveyt | B82: Kuwait | C82: KW | D82: KWD | E82: 0.9 | F82: A | G82: =Dashboard!$B$3 -> 1 | H82: =MAX(Dashboard!$B$4,G82*E82) -> 0.9 | I82: 1 | J82: =IFERROR(__xludf.DUMMYFUNCTION("GOOGLEFINANCE(""CURRENCY:USDKWD"")"),0.3081) -> 0.3081 | K82: =H82*I82*J82 -> 0.27729 | M82: =IF(L82="TRY_TIERS",IF(K82<25,19,IF(K82<35,29,IF(K82<45,39,IF(K82<60,49,79)))), IF(L82="INR_TIERS",IF(K82<40,29,IF(K82<70,49,99)), IF(L82="BRL_90",IF(K82<3,2.9,IF(K82<6,4.9,IF(K82<10,6.9,9.9))), IF(L82="IDR_000",ROUND(K82/1000,0)*1000, IF(L82="JPY_00",ROUND(K82/100,0)*100, IF(L82="KRW_000",ROUND(K82/1000,0)*1000, IF(L82="VND_000",ROUND(K82/1000,0)*1000, IF(OR(L82="USD_99",L82="EUR_99",L82="GBP_99",L82="CAD_99",L82="AUD_99",L82="PLN_99"),MAX(0.49,ROUND(K82,0)-0.01), IF(L82="MXN_00",ROUND(K82,0),IF(L82="THB_00",ROUND(K82,0),ROUND(K82,2))))))))))) -> 0.28 | N82: =M82/J82 -> 0.90879585 | P82: =IFERROR(__xludf.DUMMYFUNCTION("GOOGLEFINANCE(""CURRENCY:USDKWD"")"),0.3081) -> 0.3081
A83: Kırgızistan | B83: Kyrgyzstan | C83: KG | D83: KGS | E83: 0.25 | F83: D | G83: =Dashboard!$B$3 -> 1 | H83: =MAX(Dashboard!$B$4,G83*E83) -> 0.49 | I83: 1 | J83: =IFERROR(__xludf.DUMMYFUNCTION("GOOGLEFINANCE(""CURRENCY:USDKGS"")"),87.45) -> 87.45 | K83: =H83*I83*J83 -> 42.8505 | M83: =IF(L83="TRY_TIERS",IF(K83<25,19,IF(K83<35,29,IF(K83<45,39,IF(K83<60,49,79)))), IF(L83="INR_TIERS",IF(K83<40,29,IF(K83<70,49,99)), IF(L83="BRL_90",IF(K83<3,2.9,IF(K83<6,4.9,IF(K83<10,6.9,9.9))), IF(L83="IDR_000",ROUND(K83/1000,0)*1000, IF(L83="JPY_00",ROUND(K83/100,0)*100, IF(L83="KRW_000",ROUND(K83/1000,0)*1000, IF(L83="VND_000",ROUND(K83/1000,0)*1000, IF(OR(L83="USD_99",L83="EUR_99",L83="GBP_99",L83="CAD_99",L83="AUD_99",L83="PLN_99"),MAX(0.49,ROUND(K83,0)-0.01), IF(L83="MXN_00",ROUND(K83,0),IF(L83="THB_00",ROUND(K83,0),ROUND(K83,2))))))))))) -> 42.85 | N83: =M83/J83 -> 0.48999428 | P83: =IFERROR(__xludf.DUMMYFUNCTION("GOOGLEFINANCE(""CURRENCY:USDKGS"")"),87.45) -> 87.45
A84: Laos | B84: Lao People's Democratic Republic | C84: LA | D84: LAK | E84: 0.18 | F84: E | G84: =Dashboard!$B$3 -> 1 | H84: =MAX(Dashboard!$B$4,G84*E84) -> 0.49 | I84: 1 | J84: =IFERROR(__xludf.DUMMYFUNCTION("GOOGLEFINANCE(""CURRENCY:USDLAK"")"),21924.27) -> 21924.27 | K84: =H84*I84*J84 -> 10742.892 | M84: =IF(L84="TRY_TIERS",IF(K84<25,19,IF(K84<35,29,IF(K84<45,39,IF(K84<60,49,79)))), IF(L84="INR_TIERS",IF(K84<40,29,IF(K84<70,49,99)), IF(L84="BRL_90",IF(K84<3,2.9,IF(K84<6,4.9,IF(K84<10,6.9,9.9))), IF(L84="IDR_000",ROUND(K84/1000,0)*1000, IF(L84="JPY_00",ROUND(K84/100,0)*100, IF(L84="KRW_000",ROUND(K84/1000,0)*1000, IF(L84="VND_000",ROUND(K84/1000,0)*1000, IF(OR(L84="USD_99",L84="EUR_99",L84="GBP_99",L84="CAD_99",L84="AUD_99",L84="PLN_99"),MAX(0.49,ROUND(K84,0)-0.01), IF(L84="MXN_00",ROUND(K84,0),IF(L84="THB_00",ROUND(K84,0),ROUND(K84,2))))))))))) -> 10742.89 | N84: =M84/J84 -> 0.4899999 | P84: =IFERROR(__xludf.DUMMYFUNCTION("GOOGLEFINANCE(""CURRENCY:USDLAK"")"),21924.27) -> 21924.27
A85: Letonya | B85: Latvia | C85: LV | D85: EUR | E85: 0.6 | F85: C | G85: =Dashboard!$B$3 -> 1 | H85: =MAX(Dashboard!$B$4,G85*E85) -> 0.6 | I85: 1 | J85: =IFERROR(__xludf.DUMMYFUNCTION("GOOGLEFINANCE(""CURRENCY:USDEUR"")"),0.8519) -> 0.8519 | K85: =H85*I85*J85 -> 0.51114 | M85: =IF(L85="TRY_TIERS",IF(K85<25,19,IF(K85<35,29,IF(K85<45,39,IF(K85<60,49,79)))), IF(L85="INR_TIERS",IF(K85<40,29,IF(K85<70,49,99)), IF(L85="BRL_90",IF(K85<3,2.9,IF(K85<6,4.9,IF(K85<10,6.9,9.9))), IF(L85="IDR_000",ROUND(K85/1000,0)*1000, IF(L85="JPY_00",ROUND(K85/100,0)*100, IF(L85="KRW_000",ROUND(K85/1000,0)*1000, IF(L85="VND_000",ROUND(K85/1000,0)*1000, IF(OR(L85="USD_99",L85="EUR_99",L85="GBP_99",L85="CAD_99",L85="AUD_99",L85="PLN_99"),MAX(0.49,ROUND(K85,0)-0.01), IF(L85="MXN_00",ROUND(K85,0),IF(L85="THB_00",ROUND(K85,0),ROUND(K85,2))))))))))) -> 0.51 | N85: =M85/J85 -> 0.59866181 | P85: =IFERROR(__xludf.DUMMYFUNCTION("GOOGLEFINANCE(""CURRENCY:USDEUR"")"),0.8519) -> 0.8519
A86: Lübnan | B86: Lebanon | C86: LB | D86: LBP | E86: 0.4 | F86: D | G86: =Dashboard!$B$3 -> 1 | H86: =MAX(Dashboard!$B$4,G86*E86) -> 0.49 | I86: 1 | J86: =IFERROR(__xludf.DUMMYFUNCTION("GOOGLEFINANCE(""CURRENCY:USDLBP"")"),89559.52) -> 89559.52 | K86: =H86*I86*J86 -> 43884.165 | M86: =IF(L86="TRY_TIERS",IF(K86<25,19,IF(K86<35,29,IF(K86<45,39,IF(K86<60,49,79)))), IF(L86="INR_TIERS",IF(K86<40,29,IF(K86<70,49,99)), IF(L86="BRL_90",IF(K86<3,2.9,IF(K86<6,4.9,IF(K86<10,6.9,9.9))), IF(L86="IDR_000",ROUND(K86/1000,0)*1000, IF(L86="JPY_00",ROUND(K86/100,0)*100, IF(L86="KRW_000",ROUND(K86/1000,0)*1000, IF(L86="VND_000",ROUND(K86/1000,0)*1000, IF(OR(L86="USD_99",L86="EUR_99",L86="GBP_99",L86="CAD_99",L86="AUD_99",L86="PLN_99"),MAX(0.49,ROUND(K86,0)-0.01), IF(L86="MXN_00",ROUND(K86,0),IF(L86="THB_00",ROUND(K86,0),ROUND(K86,2))))))))))) -> 43884.16 | N86: =M86/J86 -> 0.48999995 | P86: =IFERROR(__xludf.DUMMYFUNCTION("GOOGLEFINANCE(""CURRENCY:USDLBP"")"),89559.52) -> 89559.52
A87: Liberya | B87: Liberia | C87: LR | D87: LRD | E87: 0.18 | F87: E | G87: =Dashboard!$B$3 -> 1 | H87: =MAX(Dashboard!$B$4,G87*E87) -> 0.49 | I87: 1 | J87: =IFERROR(__xludf.DUMMYFUNCTION("GOOGLEFINANCE(""CURRENCY:USDLRD"")"),183.0247) -> 183.0247 | K87: =H87*I87*J87 -> 89.682103 | M87: =IF(L87="TRY_TIERS",IF(K87<25,19,IF(K87<35,29,IF(K87<45,39,IF(K87<60,49,79)))), IF(L87="INR_TIERS",IF(K87<40,29,IF(K87<70,49,99)), IF(L87="BRL_90",IF(K87<3,2.9,IF(K87<6,4.9,IF(K87<10,6.9,9.9))), IF(L87="IDR_000",ROUND(K87/1000,0)*1000, IF(L87="JPY_00",ROUND(K87/100,0)*100, IF(L87="KRW_000",ROUND(K87/1000,0)*1000, IF(L87="VND_000",ROUND(K87/1000,0)*1000, IF(OR(L87="USD_99",L87="EUR_99",L87="GBP_99",L87="CAD_99",L87="AUD_99",L87="PLN_99"),MAX(0.49,ROUND(K87,0)-0.01), IF(L87="MXN_00",ROUND(K87,0),IF(L87="THB_00",ROUND(K87,0),ROUND(K87,2))))))))))) -> 89.68 | N87: =M87/J87 -> 0.48998851 | P87: =IFERROR(__xludf.DUMMYFUNCTION("GOOGLEFINANCE(""CURRENCY:USDLRD"")"),183.0247) -> 183.0247
A88: Libya | B88: Libya | C88: LY | D88: LYD | E88: 0.35 | F88: D | G88: =Dashboard!$B$3 -> 1 | H88: =MAX(Dashboard!$B$4,G88*E88) -> 0.49 | I88: 1 | J88: =IFERROR(__xludf.DUMMYFUNCTION("GOOGLEFINANCE(""CURRENCY:USDLYD"")"),6.3274099999999995) -> 6.32741 | K88: =H88*I88*J88 -> 3.1004309 | M88: =IF(L88="TRY_TIERS",IF(K88<25,19,IF(K88<35,29,IF(K88<45,39,IF(K88<60,49,79)))), IF(L88="INR_TIERS",IF(K88<40,29,IF(K88<70,49,99)), IF(L88="BRL_90",IF(K88<3,2.9,IF(K88<6,4.9,IF(K88<10,6.9,9.9))), IF(L88="IDR_000",ROUND(K88/1000,0)*1000, IF(L88="JPY_00",ROUND(K88/100,0)*100, IF(L88="KRW_000",ROUND(K88/1000,0)*1000, IF(L88="VND_000",ROUND(K88/1000,0)*1000, IF(OR(L88="USD_99",L88="EUR_99",L88="GBP_99",L88="CAD_99",L88="AUD_99",L88="PLN_99"),MAX(0.49,ROUND(K88,0)-0.01), IF(L88="MXN_00",ROUND(K88,0),IF(L88="THB_00",ROUND(K88,0),ROUND(K88,2))))))))))) -> 3.1 | N88: =M88/J88 -> 0.4899319 | P88: =IFERROR(__xludf.DUMMYFUNCTION("GOOGLEFINANCE(""CURRENCY:USDLYD"")"),6.3274099999999995) -> 6.32741
A89: Liechtenstan | B89: Liechtenstein | C89: LI | D89: CHF | E89: 1 | F89: A | G89: =Dashboard!$B$3 -> 1 | H89: =MAX(Dashboard!$B$4,G89*E89) -> 1 | I89: 1 | J89: =IFERROR(__xludf.DUMMYFUNCTION("GOOGLEFINANCE(""CURRENCY:USDCHF"")"),0.78042) -> 0.78042 | K89: =H89*I89*J89 -> 0.78042 | M89: =IF(L89="TRY_TIERS",IF(K89<25,19,IF(K89<35,29,IF(K89<45,39,IF(K89<60,49,79)))), IF(L89="INR_TIERS",IF(K89<40,29,IF(K89<70,49,99)), IF(L89="BRL_90",IF(K89<3,2.9,IF(K89<6,4.9,IF(K89<10,6.9,9.9))), IF(L89="IDR_000",ROUND(K89/1000,0)*1000, IF(L89="JPY_00",ROUND(K89/100,0)*100, IF(L89="KRW_000",ROUND(K89/1000,0)*1000, IF(L89="VND_000",ROUND(K89/1000,0)*1000, IF(OR(L89="USD_99",L89="EUR_99",L89="GBP_99",L89="CAD_99",L89="AUD_99",L89="PLN_99"),MAX(0.49,ROUND(K89,0)-0.01), IF(L89="MXN_00",ROUND(K89,0),IF(L89="THB_00",ROUND(K89,0),ROUND(K89,2))))))))))) -> 0.78 | N89: =M89/J89 -> 0.99946183 | P89: =IFERROR(__xludf.DUMMYFUNCTION("GOOGLEFINANCE(""CURRENCY:USDCHF"")"),0.78042) -> 0.78042
A90: Litvanya | B90: Lithuania | C90: LT | D90: EUR | E90: 0.65 | F90: B | G90: =Dashboard!$B$3 -> 1 | H90: =MAX(Dashboard!$B$4,G90*E90) -> 0.65 | I90: 1 | J90: =IFERROR(__xludf.DUMMYFUNCTION("GOOGLEFINANCE(""CURRENCY:USDEUR"")"),0.8519) -> 0.8519 | K90: =H90*I90*J90 -> 0.553735 | M90: =IF(L90="TRY_TIERS",IF(K90<25,19,IF(K90<35,29,IF(K90<45,39,IF(K90<60,49,79)))), IF(L90="INR_TIERS",IF(K90<40,29,IF(K90<70,49,99)), IF(L90="BRL_90",IF(K90<3,2.9,IF(K90<6,4.9,IF(K90<10,6.9,9.9))), IF(L90="IDR_000",ROUND(K90/1000,0)*1000, IF(L90="JPY_00",ROUND(K90/100,0)*100, IF(L90="KRW_000",ROUND(K90/1000,0)*1000, IF(L90="VND_000",ROUND(K90/1000,0)*1000, IF(OR(L90="USD_99",L90="EUR_99",L90="GBP_99",L90="CAD_99",L90="AUD_99",L90="PLN_99"),MAX(0.49,ROUND(K90,0)-0.01), IF(L90="MXN_00",ROUND(K90,0),IF(L90="THB_00",ROUND(K90,0),ROUND(K90,2))))))))))) -> 0.55 | N90: =M90/J90 -> 0.64561568 | P90: =IFERROR(__xludf.DUMMYFUNCTION("GOOGLEFINANCE(""CURRENCY:USDEUR"")"),0.8519) -> 0.8519
A91: Lüksemburg | B91: Luxembourg | C91: LU | D91: EUR | E91: 1 | F91: A | G91: =Dashboard!$B$3 -> 1 | H91: =MAX(Dashboard!$B$4,G91*E91) -> 1 | I91: 1 | J91: =IFERROR(__xludf.DUMMYFUNCTION("GOOGLEFINANCE(""CURRENCY:USDEUR"")"),0.8519) -> 0.8519 | K91: =H91*I91*J91 -> 0.8519 | M91: =IF(L91="TRY_TIERS",IF(K91<25,19,IF(K91<35,29,IF(K91<45,39,IF(K91<60,49,79)))), IF(L91="INR_TIERS",IF(K91<40,29,IF(K91<70,49,99)), IF(L91="BRL_90",IF(K91<3,2.9,IF(K91<6,4.9,IF(K91<10,6.9,9.9))), IF(L91="IDR_000",ROUND(K91/1000,0)*1000, IF(L91="JPY_00",ROUND(K91/100,0)*100, IF(L91="KRW_000",ROUND(K91/1000,0)*1000, IF(L91="VND_000",ROUND(K91/1000,0)*1000, IF(OR(L91="USD_99",L91="EUR_99",L91="GBP_99",L91="CAD_99",L91="AUD_99",L91="PLN_99"),MAX(0.49,ROUND(K91,0)-0.01), IF(L91="MXN_00",ROUND(K91,0),IF(L91="THB_00",ROUND(K91,0),ROUND(K91,2))))))))))) -> 0.85 | N91: =M91/J91 -> 0.99776969 | P91: =IFERROR(__xludf.DUMMYFUNCTION("GOOGLEFINANCE(""CURRENCY:USDEUR"")"),0.8519) -> 0.8519
A92: Makao | B92: Macao | C92: MO | D92: MOP | E92: 0.85 | F92: A | G92: =Dashboard!$B$3 -> 1 | H92: =MAX(Dashboard!$B$4,G92*E92) -> 0.85 | I92: 1 | J92: =IFERROR(__xludf.DUMMYFUNCTION("GOOGLEFINANCE(""CURRENCY:USDMOP"")"),8.064551999999999) -> 8.064552 | K92: =H92*I92*J92 -> 6.8548692 | M92: =IF(L92="TRY_TIERS",IF(K92<25,19,IF(K92<35,29,IF(K92<45,39,IF(K92<60,49,79)))), IF(L92="INR_TIERS",IF(K92<40,29,IF(K92<70,49,99)), IF(L92="BRL_90",IF(K92<3,2.9,IF(K92<6,4.9,IF(K92<10,6.9,9.9))), IF(L92="IDR_000",ROUND(K92/1000,0)*1000, IF(L92="JPY_00",ROUND(K92/100,0)*100, IF(L92="KRW_000",ROUND(K92/1000,0)*1000, IF(L92="VND_000",ROUND(K92/1000,0)*1000, IF(OR(L92="USD_99",L92="EUR_99",L92="GBP_99",L92="CAD_99",L92="AUD_99",L92="PLN_99"),MAX(0.49,ROUND(K92,0)-0.01), IF(L92="MXN_00",ROUND(K92,0),IF(L92="THB_00",ROUND(K92,0),ROUND(K92,2))))))))))) -> 6.85 | N92: =M92/J92 -> 0.84939622 | P92: =IFERROR(__xludf.DUMMYFUNCTION("GOOGLEFINANCE(""CURRENCY:USDMOP"")"),8.064551999999999) -> 8.064552
A93: Malezya | B93: Malaysia | C93: MY | D93: MYR | E93: 0.5 | F93: C | G93: =Dashboard!$B$3 -> 1 | H93: =MAX(Dashboard!$B$4,G93*E93) -> 0.5 | I93: 1 | J93: =IFERROR(__xludf.DUMMYFUNCTION("GOOGLEFINANCE(""CURRENCY:USDMYR"")"),3.9339999999999997) -> 3.934 | K93: =H93*I93*J93 -> 1.967 | M93: =IF(L93="TRY_TIERS",IF(K93<25,19,IF(K93<35,29,IF(K93<45,39,IF(K93<60,49,79)))), IF(L93="INR_TIERS",IF(K93<40,29,IF(K93<70,49,99)), IF(L93="BRL_90",IF(K93<3,2.9,IF(K93<6,4.9,IF(K93<10,6.9,9.9))), IF(L93="IDR_000",ROUND(K93/1000,0)*1000, IF(L93="JPY_00",ROUND(K93/100,0)*100, IF(L93="KRW_000",ROUND(K93/1000,0)*1000, IF(L93="VND_000",ROUND(K93/1000,0)*1000, IF(OR(L93="USD_99",L93="EUR_99",L93="GBP_99",L93="CAD_99",L93="AUD_99",L93="PLN_99"),MAX(0.49,ROUND(K93,0)-0.01), IF(L93="MXN_00",ROUND(K93,0),IF(L93="THB_00",ROUND(K93,0),ROUND(K93,2))))))))))) -> 1.97 | N93: =M93/J93 -> 0.50076258 | P93: =IFERROR(__xludf.DUMMYFUNCTION("GOOGLEFINANCE(""CURRENCY:USDMYR"")"),3.9339999999999997) -> 3.934
A94: Maldivler | B94: Maldives | C94: MV | D94: MVR | E94: 0.45 | F94: C | G94: =Dashboard!$B$3 -> 1 | H94: =MAX(Dashboard!$B$4,G94*E94) -> 0.49 | I94: 1 | J94: =IFERROR(__xludf.DUMMYFUNCTION("GOOGLEFINANCE(""CURRENCY:USDMVR"")"),15.400000000000002) -> 15.4 | K94: =H94*I94*J94 -> 7.546 | M94: =IF(L94="TRY_TIERS",IF(K94<25,19,IF(K94<35,29,IF(K94<45,39,IF(K94<60,49,79)))), IF(L94="INR_TIERS",IF(K94<40,29,IF(K94<70,49,99)), IF(L94="BRL_90",IF(K94<3,2.9,IF(K94<6,4.9,IF(K94<10,6.9,9.9))), IF(L94="IDR_000",ROUND(K94/1000,0)*1000, IF(L94="JPY_00",ROUND(K94/100,0)*100, IF(L94="KRW_000",ROUND(K94/1000,0)*1000, IF(L94="VND_000",ROUND(K94/1000,0)*1000, IF(OR(L94="USD_99",L94="EUR_99",L94="GBP_99",L94="CAD_99",L94="AUD_99",L94="PLN_99"),MAX(0.49,ROUND(K94,0)-0.01), IF(L94="MXN_00",ROUND(K94,0),IF(L94="THB_00",ROUND(K94,0),ROUND(K94,2))))))))))) -> 7.55 | N94: =M94/J94 -> 0.49025974 | P94: =IFERROR(__xludf.DUMMYFUNCTION("GOOGLEFINANCE(""CURRENCY:USDMVR"")"),15.400000000000002) -> 15.4
A95: Mali | B95: Mali | C95: ML | D95: XOF | E95: 0.15 | F95: E | G95: =Dashboard!$B$3 -> 1 | H95: =MAX(Dashboard!$B$4,G95*E95) -> 0.49 | I95: 1 | J95: =IFERROR(__xludf.DUMMYFUNCTION("GOOGLEFINANCE(""CURRENCY:USDXOF"")"),558.7654) -> 558.7654 | K95: =H95*I95*J95 -> 273.79505 | M95: =IF(L95="TRY_TIERS",IF(K95<25,19,IF(K95<35,29,IF(K95<45,39,IF(K95<60,49,79)))), IF(L95="INR_TIERS",IF(K95<40,29,IF(K95<70,49,99)), IF(L95="BRL_90",IF(K95<3,2.9,IF(K95<6,4.9,IF(K95<10,6.9,9.9))), IF(L95="IDR_000",ROUND(K95/1000,0)*1000, IF(L95="JPY_00",ROUND(K95/100,0)*100, IF(L95="KRW_000",ROUND(K95/1000,0)*1000, IF(L95="VND_000",ROUND(K95/1000,0)*1000, IF(OR(L95="USD_99",L95="EUR_99",L95="GBP_99",L95="CAD_99",L95="AUD_99",L95="PLN_99"),MAX(0.49,ROUND(K95,0)-0.01), IF(L95="MXN_00",ROUND(K95,0),IF(L95="THB_00",ROUND(K95,0),ROUND(K95,2))))))))))) -> 273.8 | N95: =M95/J95 -> 0.49000887 | P95: =IFERROR(__xludf.DUMMYFUNCTION("GOOGLEFINANCE(""CURRENCY:USDXOF"")"),558.7654) -> 558.7654
A96: Malta | B96: Malta | C96: MT | D96: EUR | E96: 0.75 | F96: B | G96: =Dashboard!$B$3 -> 1 | H96: =MAX(Dashboard!$B$4,G96*E96) -> 0.75 | I96: 1 | J96: =IFERROR(__xludf.DUMMYFUNCTION("GOOGLEFINANCE(""CURRENCY:USDEUR"")"),0.8519) -> 0.8519 | K96: =H96*I96*J96 -> 0.638925 | M96: =IF(L96="TRY_TIERS",IF(K96<25,19,IF(K96<35,29,IF(K96<45,39,IF(K96<60,49,79)))), IF(L96="INR_TIERS",IF(K96<40,29,IF(K96<70,49,99)), IF(L96="BRL_90",IF(K96<3,2.9,IF(K96<6,4.9,IF(K96<10,6.9,9.9))), IF(L96="IDR_000",ROUND(K96/1000,0)*1000, IF(L96="JPY_00",ROUND(K96/100,0)*100, IF(L96="KRW_000",ROUND(K96/1000,0)*1000, IF(L96="VND_000",ROUND(K96/1000,0)*1000, IF(OR(L96="USD_99",L96="EUR_99",L96="GBP_99",L96="CAD_99",L96="AUD_99",L96="PLN_99"),MAX(0.49,ROUND(K96,0)-0.01), IF(L96="MXN_00",ROUND(K96,0),IF(L96="THB_00",ROUND(K96,0),ROUND(K96,2))))))))))) -> 0.64 | N96: =M96/J96 -> 0.75126189 | P96: =IFERROR(__xludf.DUMMYFUNCTION("GOOGLEFINANCE(""CURRENCY:USDEUR"")"),0.8519) -> 0.8519
A97: Mauritius | B97: Mauritius | C97: MU | D97: MUR | E97: 0.22 | F97: E | G97: =Dashboard!$B$3 -> 1 | H97: =MAX(Dashboard!$B$4,G97*E97) -> 0.49 | I97: 1 | J97: =IFERROR(__xludf.DUMMYFUNCTION("GOOGLEFINANCE(""CURRENCY:USDMUR"")"),46.7) -> 46.7 | K97: =H97*I97*J97 -> 22.883 | M97: =IF(L97="TRY_TIERS",IF(K97<25,19,IF(K97<35,29,IF(K97<45,39,IF(K97<60,49,79)))), IF(L97="INR_TIERS",IF(K97<40,29,IF(K97<70,49,99)), IF(L97="BRL_90",IF(K97<3,2.9,IF(K97<6,4.9,IF(K97<10,6.9,9.9))), IF(L97="IDR_000",ROUND(K97/1000,0)*1000, IF(L97="JPY_00",ROUND(K97/100,0)*100, IF(L97="KRW_000",ROUND(K97/1000,0)*1000, IF(L97="VND_000",ROUND(K97/1000,0)*1000, IF(OR(L97="USD_99",L97="EUR_99",L97="GBP_99",L97="CAD_99",L97="AUD_99",L97="PLN_99"),MAX(0.49,ROUND(K97,0)-0.01), IF(L97="MXN_00",ROUND(K97,0),IF(L97="THB_00",ROUND(K97,0),ROUND(K97,2))))))))))) -> 22.88 | N97: =M97/J97 -> 0.48993576 | P97: =IFERROR(__xludf.DUMMYFUNCTION("GOOGLEFINANCE(""CURRENCY:USDMUR"")"),46.7) -> 46.7
A98: Meksika | B98: Mexico | C98: MX | D98: MXN | E98: 0.45 | F98: =IF(E98>=0.8,"A",IF(E98>=0.6,"B",IF(E98>=0.4,"C",IF(E98>=0.2,"D","E")))) -> C | G98: =Dashboard!$B$3 -> 1 | H98: =MAX(Dashboard!$B$4,G98*E98) -> 0.49 | I98: 0.9 | J98: =IFERROR(__xludf.DUMMYFUNCTION("GOOGLEFINANCE(""CURRENCY:USDMXN"")"),17.2269) -> 17.2269 | K98: =H98*I98*J98 -> 7.5970629 | L98: MXN_00 | M98: =IF(L98="TRY_TIERS",IF(K98<25,19,IF(K98<35,29,IF(K98<45,39,IF(K98<60,49,79)))), IF(L98="INR_TIERS",IF(K98<40,29,IF(K98<70,49,99)), IF(L98="BRL_90",IF(K98<3,2.9,IF(K98<6,4.9,IF(K98<10,6.9,9.9))), IF(L98="IDR_000",ROUND(K98/1000,0)*1000, IF(L98="JPY_00",ROUND(K98/100,0)*100, IF(L98="KRW_000",ROUND(K98/1000,0)*1000, IF(L98="VND_000",ROUND(K98/1000,0)*1000, IF(OR(L98="USD_99",L98="EUR_99",L98="GBP_99",L98="CAD_99",L98="AUD_99",L98="PLN_99"),MAX(0.49,ROUND(K98,0)-0.01), IF(L98="MXN_00",ROUND(K98,0),IF(L98="THB_00",ROUND(K98,0),ROUND(K98,2))))))))))) -> 8 | N98: =M98/J98 -> 0.46438999 | O98: =IF(N98<Dashboard!$B$4,"Below global min",IF(AND(E98>=0.8,N98<Dashboard!$B$5),"Raise high-PPP floor","OK")) -> Below global min | P98: =IFERROR(__xludf.DUMMYFUNCTION("GOOGLEFINANCE(""CURRENCY:USDMXN"")"),17.2269) -> 17.2269
A99: Mikronezya | B99: Micronesia (Federated States of) | C99: FM | D99: USD | E99: 0.3 | F99: D | G99: =Dashboard!$B$3 -> 1 | H99: =MAX(Dashboard!$B$4,G99*E99) -> 0.49 | I99: 1 | J99: =IFERROR(__xludf.DUMMYFUNCTION("GOOGLEFINANCE(""CURRENCY:USDUSD"")"),"#N/A") -> #N/A | K99: =H99*I99*J99 -> #N/A | M99: =IF(L99="TRY_TIERS",IF(K99<25,19,IF(K99<35,29,IF(K99<45,39,IF(K99<60,49,79)))), IF(L99="INR_TIERS",IF(K99<40,29,IF(K99<70,49,99)), IF(L99="BRL_90",IF(K99<3,2.9,IF(K99<6,4.9,IF(K99<10,6.9,9.9))), IF(L99="IDR_000",ROUND(K99/1000,0)*1000, IF(L99="JPY_00",ROUND(K99/100,0)*100, IF(L99="KRW_000",ROUND(K99/1000,0)*1000, IF(L99="VND_000",ROUND(K99/1000,0)*1000, IF(OR(L99="USD_99",L99="EUR_99",L99="GBP_99",L99="CAD_99",L99="AUD_99",L99="PLN_99"),MAX(0.49,ROUND(K99,0)-0.01), IF(L99="MXN_00",ROUND(K99,0),IF(L99="THB_00",ROUND(K99,0),ROUND(K99,2))))))))))) -> #N/A | N99: =M99/J99 -> #N/A | P99: =IFERROR(__xludf.DUMMYFUNCTION("GOOGLEFINANCE(""CURRENCY:USDUSD"")"),"#N/A") -> #N/A
A100: Moldova | B100: Moldova (the Republic of) | C100: MD | D100: MDL | E100: 0.3 | F100: D | G100: =Dashboard!$B$3 -> 1 | H100: =MAX(Dashboard!$B$4,G100*E100) -> 0.49 | I100: 1 | J100: =IFERROR(__xludf.DUMMYFUNCTION("GOOGLEFINANCE(""CURRENCY:USDMDL"")"),17.116570000000003) -> 17.11657 | K100: =H100*I100*J100 -> 8.3871193 | M100: =IF(L100="TRY_TIERS",IF(K100<25,19,IF(K100<35,29,IF(K100<45,39,IF(K100<60,49,79)))), IF(L100="INR_TIERS",IF(K100<40,29,IF(K100<70,49,99)), IF(L100="BRL_90",IF(K100<3,2.9,IF(K100<6,4.9,IF(K100<10,6.9,9.9))), IF(L100="IDR_000",ROUND(K100/1000,0)*1000, IF(L100="JPY_00",ROUND(K100/100,0)*100, IF(L100="KRW_000",ROUND(K100/1000,0)*1000, IF(L100="VND_000",ROUND(K100/1000,0)*1000, IF(OR(L100="USD_99",L100="EUR_99",L100="GBP_99",L100="CAD_99",L100="AUD_99",L100="PLN_99"),MAX(0.49,ROUND(K100,0)-0.01), IF(L100="MXN_00",ROUND(K100,0),IF(L100="THB_00",ROUND(K100,0),ROUND(K100,2))))))))))) -> 8.39 | N100: =M100/J100 -> 0.4901683 | P100: =IFERROR(__xludf.DUMMYFUNCTION("GOOGLEFINANCE(""CURRENCY:USDMDL"")"),17.116570000000003) -> 17.11657
...

Sheet countries
A1: S | B1: A | C1: B | D1: C | E1: D | F1: S | G1: 1.00
A2: Australia | B2: Austria | C2: Argentina | D2: Bangladesh | E2: Central African Republic | F2: A | G2: 0.80
A3: Canada | B3: Belgium | C3: Brazil | D3: Egypt | E3: Chad | F3: B | G3: 0.55
A4: Denmark | B4: Czech Republic | C4: Chile | D4: India | E4: Eritrea | F4: C | G4: 0.30
A5: France | B5: Finland | C5: Colombia | D5: Indonesia | E5: Liberia | F5: D | G5: 0.25
A6: Germany | B6: Ireland | C6: Hungary | D6: Nigeria | E6: Niger
A7: Japan | B7: Israel | C7: Malaysia | D7: Pakistan | E7: Sierra Leone
A8: Netherlands | B8: Italy | C8: Mexico | D8: Philippines | E8: Somalia
A9: New Zealand | B9: Poland | C9: Romania | D9: Vietnam
A10: Norway | B10: Portugal | C10: South Africa
A11: Singapore | B11: Saudi Arabia | C11: Thailand
A12: South Korea | B12: Spain | C12: Turkey
A13: Sweden | B13: Taiwan
A14: Switzerland
A15: UAE
A16: UK
A17: USA

Sheet PriceLast
D1: Currency | E1: PPP | F1: TIER | G1: MAX | H1: MIN | I1: TIER CONST | J1: $ | K1: USD/LOCAL CUR. | L1: LOCAL | M1: FLG
A2: Arnavutluk | B2: Albania | C2: AL | D2: ALL | E2: 0.35 | F2: D | G2: 3 | H2: 1.49 | I2: =IF(F2="S",1,IF(F2="A",0.8,IF(F2="B",0.55,IF(F2="C",0.3,IF(F2="D",0.25,0.25))))) -> 0.25 | J2: =MAX(H2,G2*I2) -> 1.49 | K2: =IFERROR(__xludf.DUMMYFUNCTION("GOOGLEFINANCE(""CURRENCY:USDALL"")"),81.26480000000001) -> 81.2648 | L2: =J2*K2 -> 121.08455 | M2: 119
A3: Cezayir | B3: Algeria | C3: DZ | D3: DZD | E3: 0.28 | F3: D | G3: 3 | H3: 1.49 | I3: =IF(F3="S",1,IF(F3="A",0.8,IF(F3="B",0.55,IF(F3="C",0.3,IF(F3="D",0.25,0.25))))) -> 0.25 | J3: =MAX(H3,G3*I3) -> 1.49 | K3: =IFERROR(__xludf.DUMMYFUNCTION("GOOGLEFINANCE(""CURRENCY:USDDZD"")"),132.3826) -> 132.3826 | L3: =J3*K3 -> 197.25007 | M3: 189
A4: Angola | B4: Angola | C4: AO | D4: AOA | E4: 0.22 | F4: D | G4: 3 | H4: 1.49 | I4: =IF(F4="S",1,IF(F4="A",0.8,IF(F4="B",0.55,IF(F4="C",0.3,IF(F4="D",0.25,0.25))))) -> 0.25 | J4: =MAX(H4,G4*I4) -> 1.49 | K4: =IFERROR(__xludf.DUMMYFUNCTION("GOOGLEFINANCE(""CURRENCY:USDAOA"")"),918.0) -> 918 | L4: =J4*K4 -> 1367.82 | M4: 1290
A5: Antigua ve Barbuda | B5: Antigua and Barbuda | C5: AG | D5: XCD | E5: 0.65 | F5: B | G5: 3 | H5: 1.49 | I5: =IF(F5="S",1,IF(F5="A",0.8,IF(F5="B",0.55,IF(F5="C",0.3,IF(F5="D",0.25,0.25))))) -> 0.55 | J5: =MAX(H5,G5*I5) -> 1.65 | K5: =IFERROR(__xludf.DUMMYFUNCTION("GOOGLEFINANCE(""CURRENCY:USDXCD"")"),2.70255) -> 2.70255 | L5: =J5*K5 -> 4.4592075 | M5: 3.9
A6: Arjantin | B6: Argentina | C6: AR | D6: ARS | E6: 0.3 | F6: B | G6: 3 | H6: 1.49 | I6: =IF(F6="S",1,IF(F6="A",0.8,IF(F6="B",0.55,IF(F6="C",0.3,IF(F6="D",0.25,0.25))))) -> 0.55 | J6: =MAX(H6,G6*I6) -> 1.65 | K6: =IFERROR(__xludf.DUMMYFUNCTION("GOOGLEFINANCE(""CURRENCY:USDARS"")"),1385.0) -> 1385 | L6: =J6*K6 -> 2285.25 | M6: 1990
A7: Ermenistan | B7: Armenia | C7: AM | D7: AMD | E7: 0.3 | F7: D | G7: 3 | H7: 1.49 | I7: =IF(F7="S",1,IF(F7="A",0.8,IF(F7="B",0.55,IF(F7="C",0.3,IF(F7="D",0.25,0.25))))) -> 0.25 | J7: =MAX(H7,G7*I7) -> 1.49 | K7: =IFERROR(__xludf.DUMMYFUNCTION("GOOGLEFINANCE(""CURRENCY:USDAMD"")"),368.0783) -> 368.0783 | L7: =J7*K7 -> 548.43667 | M7: 539
A8: Aruba | B8: Aruba | C8: AW | D8: AWG | E8: 0.75 | F8: A | G8: 3 | H8: 1.49 | I8: =IF(F8="S",1,IF(F8="A",0.8,IF(F8="B",0.55,IF(F8="C",0.3,IF(F8="D",0.25,0.25))))) -> 0.8 | J8: =MAX(H8,G8*I8) -> 2.4 | K8: =IFERROR(__xludf.DUMMYFUNCTION("GOOGLEFINANCE(""CURRENCY:USDAWG"")"),1.8025) -> 1.8025 | L8: =J8*K8 -> 4.326 | M8: 3.9
A9: Avustralya | B9: Australia | C9: AU | D9: AUD | E9: 0.95 | F9: S | G9: 3 | H9: 1.49 | I9: =IF(F9="S",1,IF(F9="A",0.8,IF(F9="B",0.55,IF(F9="C",0.3,IF(F9="D",0.25,0.25))))) -> 1 | J9: =MAX(H9,G9*I9) -> 3 | K9: =IFERROR(__xludf.DUMMYFUNCTION("GOOGLEFINANCE(""CURRENCY:USDAUD"")"),1.381082) -> 1.381082 | L9: =J9*K9 -> 4.143246 | M9: 3.9
A10: Avusturya | B10: Austria | C10: AT | D10: EUR | E10: 0.86 | F10: A | G10: 3 | H10: 1.49 | I10: =IF(F10="S",1,IF(F10="A",0.8,IF(F10="B",0.55,IF(F10="C",0.3,IF(F10="D",0.25,0.25))))) -> 0.8 | J10: =MAX(H10,G10*I10) -> 2.4 | K10: =IFERROR(__xludf.DUMMYFUNCTION("GOOGLEFINANCE(""CURRENCY:USDEUR"")"),0.8519) -> 0.8519 | L10: =J10*K10 -> 2.04456 | M10: 1.9
A11: Azerbaycan | B11: Azerbaijan | C11: AZ | D11: AZN | E11: 0.4 | F11: B | G11: 3 | H11: 1.49 | I11: =IF(F11="S",1,IF(F11="A",0.8,IF(F11="B",0.55,IF(F11="C",0.3,IF(F11="D",0.25,0.25))))) -> 0.55 | J11: =MAX(H11,G11*I11) -> 1.65 | K11: =IFERROR(__xludf.DUMMYFUNCTION("GOOGLEFINANCE(""CURRENCY:USDAZN"")"),1.7) -> 1.7 | L11: =J11*K11 -> 2.805 | M11: 2.49
A12: Bahamalar | B12: Bahamas | C12: BS | D12: BSD | E12: 0.75 | F12: A | G12: 3 | H12: 1.49 | I12: =IF(F12="S",1,IF(F12="A",0.8,IF(F12="B",0.55,IF(F12="C",0.3,IF(F12="D",0.25,0.25))))) -> 0.8 | J12: =MAX(H12,G12*I12) -> 2.4 | K12: =IFERROR(__xludf.DUMMYFUNCTION("GOOGLEFINANCE(""CURRENCY:USDBSD"")"),1.000136) -> 1.000136 | L12: =J12*K12 -> 2.4003264 | M12: 2.39
A13: Bahreyn | B13: Bahrain | C13: BH | D13: BHD | E13: 0.85 | F13: A | G13: 3 | H13: 1.49 | I13: =IF(F13="S",1,IF(F13="A",0.8,IF(F13="B",0.55,IF(F13="C",0.3,IF(F13="D",0.25,0.25))))) -> 0.8 | J13: =MAX(H13,G13*I13) -> 2.4 | K13: =IFERROR(__xludf.DUMMYFUNCTION("GOOGLEFINANCE(""CURRENCY:USDBHD"")"),0.3774469) -> 0.3774469 | L13: =J13*K13 -> 0.90587256 | M13: 0.89
A14: Bangladeş | B14: Bangladesh | C14: BD | D14: BDT | E14: 0.15 | F14: C | G14: 3 | H14: 1.49 | I14: =IF(F14="S",1,IF(F14="A",0.8,IF(F14="B",0.55,IF(F14="C",0.3,IF(F14="D",0.25,0.25))))) -> 0.3 | J14: =MAX(H14,G14*I14) -> 1.49 | K14: =IFERROR(__xludf.DUMMYFUNCTION("GOOGLEFINANCE(""CURRENCY:USDBDT"")"),122.9364) -> 122.9364 | L14: =J14*K14 -> 183.17524 | M14: 179
A15: Belarus | B15: Belarus | C15: BY | D15: BYN | E15: 0.4 | F15: B | G15: 3 | H15: 1.49 | I15: =IF(F15="S",1,IF(F15="A",0.8,IF(F15="B",0.55,IF(F15="C",0.3,IF(F15="D",0.25,0.25))))) -> 0.55 | J15: =MAX(H15,G15*I15) -> 1.65 | K15: =IFERROR(__xludf.DUMMYFUNCTION("GOOGLEFINANCE(""CURRENCY:USDBYN"")"),2.7962249999999997) -> 2.796225 | L15: =J15*K15 -> 4.6137713 | M15: 3.9
A16: Belçika | B16: Belgium | C16: BE | D16: EUR | E16: 0.84 | F16: A | G16: 3 | H16: 1.49 | I16: =IF(F16="S",1,IF(F16="A",0.8,IF(F16="B",0.55,IF(F16="C",0.3,IF(F16="D",0.25,0.25))))) -> 0.8 | J16: =MAX(H16,G16*I16) -> 2.4 | K16: =IFERROR(__xludf.DUMMYFUNCTION("GOOGLEFINANCE(""CURRENCY:USDEUR"")"),0.8519) -> 0.8519 | L16: =J16*K16 -> 2.04456 | M16: 1.9
A17: Belize | B17: Belize | C17: BZ | D17: BZD | E17: 0.35 | F17: C | G17: 3 | H17: 1.49 | I17: =IF(F17="S",1,IF(F17="A",0.8,IF(F17="B",0.55,IF(F17="C",0.3,IF(F17="D",0.25,0.25))))) -> 0.3 | J17: =MAX(H17,G17*I17) -> 1.49 | K17: =IFERROR(__xludf.DUMMYFUNCTION("GOOGLEFINANCE(""CURRENCY:USDBZD"")"),2.011432) -> 2.011432 | L17: =J17*K17 -> 2.9970337 | M17: 2.9
A18: Benin | B18: Benin | C18: BJ | D18: XOF | E18: 0.18 | F18: D | G18: 3 | H18: 1.49 | I18: =IF(F18="S",1,IF(F18="A",0.8,IF(F18="B",0.55,IF(F18="C",0.3,IF(F18="D",0.25,0.25))))) -> 0.25 | J18: =MAX(H18,G18*I18) -> 1.49 | K18: =IFERROR(__xludf.DUMMYFUNCTION("GOOGLEFINANCE(""CURRENCY:USDXOF"")"),558.7654) -> 558.7654 | L18: =J18*K18 -> 832.56045 | M18: 790
A19: Bermuda | B19: Bermuda | C19: BM | D19: BMD | E19: 1 | F19: A | G19: 3 | H19: 1.49 | I19: =IF(F19="S",1,IF(F19="A",0.8,IF(F19="B",0.55,IF(F19="C",0.3,IF(F19="D",0.25,0.25))))) -> 0.8 | J19: =MAX(H19,G19*I19) -> 2.4 | K19: =IFERROR(__xludf.DUMMYFUNCTION("GOOGLEFINANCE(""CURRENCY:USDBMD"")"),1.0) -> 1 | L19: =J19*K19 -> 2.4 | M19: 2.39
A20: Bolivya | B20: Bolivia | C20: BO | D20: BOB-BOV | E20: 0.3 | F20: D | G20: 3 | H20: 1.49 | I20: =IF(F20="S",1,IF(F20="A",0.8,IF(F20="B",0.55,IF(F20="C",0.3,IF(F20="D",0.25,0.25))))) -> 0.25 | J20: =MAX(H20,G20*I20) -> 1.49 | K20: =IFERROR(__xludf.DUMMYFUNCTION("GOOGLEFINANCE(""CURRENCY:USDBOB"")"),6.910945) -> 6.910945 | L20: =J20*K20 -> 10.297308 | M20: 9.9
A21: Bosna-Hersek | B21: Bosnia and Herzegovina | C21: BA | D21: BAM | E21: 0.45 | F21: B | G21: 3 | H21: 1.49 | I21: =IF(F21="S",1,IF(F21="A",0.8,IF(F21="B",0.55,IF(F21="C",0.3,IF(F21="D",0.25,0.25))))) -> 0.55 | J21: =MAX(H21,G21*I21) -> 1.65 | K21: =IFERROR(__xludf.DUMMYFUNCTION("GOOGLEFINANCE(""CURRENCY:USDBAM"")"),1.6660139999999999) -> 1.666014 | L21: =J21*K21 -> 2.7489231 | M21: 2.49
A22: Botsvana | B22: Botswana | C22: BW | D22: BWP | E22: 0.4 | F22: B | G22: 3 | H22: 1.49 | I22: =IF(F22="S",1,IF(F22="A",0.8,IF(F22="B",0.55,IF(F22="C",0.3,IF(F22="D",0.25,0.25))))) -> 0.55 | J22: =MAX(H22,G22*I22) -> 1.65 | K22: =IFERROR(__xludf.DUMMYFUNCTION("GOOGLEFINANCE(""CURRENCY:USDBWP"")"),13.49984) -> 13.49984 | L22: =J22*K22 -> 22.274736 | M22: 19.9
A23: Brezilya | B23: Brazil | C23: BR | D23: BRL | E23: 0.35 | F23: B | G23: 3 | H23: 1.49 | I23: =IF(F23="S",1,IF(F23="A",0.8,IF(F23="B",0.55,IF(F23="C",0.3,IF(F23="D",0.25,0.25))))) -> 0.55 | J23: =MAX(H23,G23*I23) -> 1.65 | K23: =IFERROR(__xludf.DUMMYFUNCTION("GOOGLEFINANCE(""CURRENCY:USDBRL"")"),4.9113) -> 4.9113 | L23: =J23*K23 -> 8.103645 | M23: 7.9
A24: Bulgaristan | B24: Bulgaria | C24: BG | D24: BGN | E24: 0.4 | F24: B | G24: 3 | H24: 1.49 | I24: =IF(F24="S",1,IF(F24="A",0.8,IF(F24="B",0.55,IF(F24="C",0.3,IF(F24="D",0.25,0.25))))) -> 0.55 | J24: =MAX(H24,G24*I24) -> 1.65 | K24: =IFERROR(__xludf.DUMMYFUNCTION("GOOGLEFINANCE(""CURRENCY:USDBGN"")"),"#N/A") -> #N/A | L24: =J24*K24 -> #N/A
A25: Burkina Faso | B25: Burkina Faso | C25: BF | D25: XOF | E25: 0.18 | F25: D | G25: 3 | H25: 1.49 | I25: =IF(F25="S",1,IF(F25="A",0.8,IF(F25="B",0.55,IF(F25="C",0.3,IF(F25="D",0.25,0.25))))) -> 0.25 | J25: =MAX(H25,G25*I25) -> 1.49 | K25: =IFERROR(__xludf.DUMMYFUNCTION("GOOGLEFINANCE(""CURRENCY:USDXOF"")"),558.7654) -> 558.7654 | L25: =J25*K25 -> 832.56045 | M25: 790
A26: Cabo Verde | B26: Cabo Verde | C26: CV | D26: CVE | E26: 0.3 | F26: D | G26: 3 | H26: 1.49 | I26: =IF(F26="S",1,IF(F26="A",0.8,IF(F26="B",0.55,IF(F26="C",0.3,IF(F26="D",0.25,0.25))))) -> 0.25 | J26: =MAX(H26,G26*I26) -> 1.49 | K26: =IFERROR(__xludf.DUMMYFUNCTION("GOOGLEFINANCE(""CURRENCY:USDCVE"")"),93.92769000000001) -> 93.92769 | L26: =J26*K26 -> 139.95226 | M26: 129
A27: Kamboçya | B27: Cambodia | C27: KH | D27: KHR | E27: 0.2 | F27: D | G27: 3 | H27: 1.49 | I27: =IF(F27="S",1,IF(F27="A",0.8,IF(F27="B",0.55,IF(F27="C",0.3,IF(F27="D",0.25,0.25))))) -> 0.25 | J27: =MAX(H27,G27*I27) -> 1.49 | K27: =IFERROR(__xludf.DUMMYFUNCTION("GOOGLEFINANCE(""CURRENCY:USDKHR"")"),4012.13) -> 4012.13 | L27: =J27*K27 -> 5978.0737 | M27: 4900
A28: Kamerun | B28: Cameroon | C28: CM | D28: XAF | E28: 0.12 | F28: D | G28: 3 | H28: 1.49 | I28: =IF(F28="S",1,IF(F28="A",0.8,IF(F28="B",0.55,IF(F28="C",0.3,IF(F28="D",0.25,0.25))))) -> 0.25 | J28: =MAX(H28,G28*I28) -> 1.49 | K28: =IFERROR(__xludf.DUMMYFUNCTION("GOOGLEFINANCE(""CURRENCY:USDXAF"")"),558.7654) -> 558.7654 | L28: =J28*K28 -> 832.56045 | M28: 790
A29: Kanada | B29: Canada | C29: CA | D29: CAD | E29: 0.95 | F29: S | G29: 3 | H29: 1.49 | I29: =IF(F29="S",1,IF(F29="A",0.8,IF(F29="B",0.55,IF(F29="C",0.3,IF(F29="D",0.25,0.25))))) -> 1 | J29: =MAX(H29,G29*I29) -> 3 | K29: =IFERROR(__xludf.DUMMYFUNCTION("GOOGLEFINANCE(""CURRENCY:USDCAD"")"),1.369425) -> 1.369425 | L29: =J29*K29 -> 4.108275 | M29: 3.9
A30: Cayman Adaları | B30: Cayman Islands | C30: KY | D30: KYD | E30: 1 | F30: S | G30: 3 | H30: 1.49 | I30: =IF(F30="S",1,IF(F30="A",0.8,IF(F30="B",0.55,IF(F30="C",0.3,IF(F30="D",0.25,0.25))))) -> 1 | J30: =MAX(H30,G30*I30) -> 3 | K30: =IFERROR(__xludf.DUMMYFUNCTION("GOOGLEFINANCE(""CURRENCY:USDKYD"")"),0.8334256) -> 0.8334256 | L30: =J30*K30 -> 2.5002768 | M30: 2.39
A31: Orta Afrika Cumhuriyeti | B31: Central African Republic | C31: CF | D31: XAF | E31: 0.12 | F31: D | G31: 3 | H31: 1.49 | I31: =IF(F31="S",1,IF(F31="A",0.8,IF(F31="B",0.55,IF(F31="C",0.3,IF(F31="D",0.25,0.25))))) -> 0.25 | J31: =MAX(H31,G31*I31) -> 1.49 | K31: =IFERROR(__xludf.DUMMYFUNCTION("GOOGLEFINANCE(""CURRENCY:USDXAF"")"),558.7654) -> 558.7654 | L31: =J31*K31 -> 832.56045 | M31: 790
A32: Çad | B32: Chad | C32: TD | D32: XAF | E32: 0.12 | F32: D | G32: 3 | H32: 1.49 | I32: =IF(F32="S",1,IF(F32="A",0.8,IF(F32="B",0.55,IF(F32="C",0.3,IF(F32="D",0.25,0.25))))) -> 0.25 | J32: =MAX(H32,G32*I32) -> 1.49 | K32: =IFERROR(__xludf.DUMMYFUNCTION("GOOGLEFINANCE(""CURRENCY:USDXAF"")"),558.7654) -> 558.7654 | L32: =J32*K32 -> 832.56045 | M32: 790
A33: Şili | B33: Chile | C33: CL | D33: CLP | E33: 0.6 | F33: B | G33: 3 | H33: 1.49 | I33: =IF(F33="S",1,IF(F33="A",0.8,IF(F33="B",0.55,IF(F33="C",0.3,IF(F33="D",0.25,0.25))))) -> 0.55 | J33: =MAX(H33,G33*I33) -> 1.65 | K33: =IFERROR(__xludf.DUMMYFUNCTION("GOOGLEFINANCE(""CURRENCY:USDCLP"")"),892.857143) -> 892.85714 | L33: =J33*K33 -> 1473.2143 | M33: 1390
A34: Kolombiya | B34: Colombia | C34: CO | D34: COP-COU | E34: 0.38 | F34: B | G34: 3 | H34: 1.49 | I34: =IF(F34="S",1,IF(F34="A",0.8,IF(F34="B",0.55,IF(F34="C",0.3,IF(F34="D",0.25,0.25))))) -> 0.55 | J34: =MAX(H34,G34*I34) -> 1.65 | K34: =IFERROR(__xludf.DUMMYFUNCTION("GOOGLEFINANCE(""CURRENCY:USDCOP"")"),3752.41843) -> 3752.4184 | L34: =J34*K34 -> 6191.4904 | M34: 5900
A35: Komorlar | B35: Comoros | C35: KM | D35: KMF | E35: 0.18 | F35: D | G35: 3 | H35: 1.49 | I35: =IF(F35="S",1,IF(F35="A",0.8,IF(F35="B",0.55,IF(F35="C",0.3,IF(F35="D",0.25,0.25))))) -> 0.25 | J35: =MAX(H35,G35*I35) -> 1.49 | K35: =IFERROR(__xludf.DUMMYFUNCTION("GOOGLEFINANCE(""CURRENCY:USDKMF"")"),420.0) -> 420 | L35: =J35*K35 -> 625.8 | M35: 590
A36: Kongo-Brazavil | B36: Congo | C36: CG | D36: XAF | E36: 0.22 | F36: D | G36: 3 | H36: 1.49 | I36: =IF(F36="S",1,IF(F36="A",0.8,IF(F36="B",0.55,IF(F36="C",0.3,IF(F36="D",0.25,0.25))))) -> 0.25 | J36: =MAX(H36,G36*I36) -> 1.49 | K36: =IFERROR(__xludf.DUMMYFUNCTION("GOOGLEFINANCE(""CURRENCY:USDXAF"")"),558.7654) -> 558.7654 | L36: =J36*K36 -> 832.56045 | M36: 790
A37: Kongo-Kinşasa | B37: Congo (the Democratic Republic of the) | C37: CD | D37: CDF | E37: 0.15 | F37: D | G37: 3 | H37: 1.49 | I37: =IF(F37="S",1,IF(F37="A",0.8,IF(F37="B",0.55,IF(F37="C",0.3,IF(F37="D",0.25,0.25))))) -> 0.25 | J37: =MAX(H37,G37*I37) -> 1.49 | K37: =IFERROR(__xludf.DUMMYFUNCTION("GOOGLEFINANCE(""CURRENCY:USDCDF"")"),2280.07117) -> 2280.0712 | L37: =J37*K37 -> 3397.306 | M37: 2900
A38: KostaRika | B38: Costa Rica | C38: CR | D38: CRC | E38: 0.5 | F38: D | G38: 3 | H38: 1.49 | I38: =IF(F38="S",1,IF(F38="A",0.8,IF(F38="B",0.55,IF(F38="C",0.3,IF(F38="D",0.25,0.25))))) -> 0.25 | J38: =MAX(H38,G38*I38) -> 1.49 | K38: =IFERROR(__xludf.DUMMYFUNCTION("GOOGLEFINANCE(""CURRENCY:USDCRC"")"),456.4117) -> 456.4117 | L38: =J38*K38 -> 680.05343 | M38: 649
A39: Côte d’Ivoire | B39: Côte d’Ivoire | C39: CI | D39: XOF | E39: 0.25 | F39: D | G39: 3 | H39: 1.49 | I39: =IF(F39="S",1,IF(F39="A",0.8,IF(F39="B",0.55,IF(F39="C",0.3,IF(F39="D",0.25,0.25))))) -> 0.25 | J39: =MAX(H39,G39*I39) -> 1.49 | K39: =IFERROR(__xludf.DUMMYFUNCTION("GOOGLEFINANCE(""CURRENCY:USDXOF"")"),558.7654) -> 558.7654 | L39: =J39*K39 -> 832.56045 | M39: 790
A40: Hırvatistan | B40: Croaita | C40: HR | D40: EUR | E40: 0.55 | F40: B | G40: 3 | H40: 1.49 | I40: =IF(F40="S",1,IF(F40="A",0.8,IF(F40="B",0.55,IF(F40="C",0.3,IF(F40="D",0.25,0.25))))) -> 0.55 | J40: =MAX(H40,G40*I40) -> 1.65 | K40: =IFERROR(__xludf.DUMMYFUNCTION("GOOGLEFINANCE(""CURRENCY:USDEUR"")"),0.8519) -> 0.8519 | L40: =J40*K40 -> 1.405635 | M40: 1.39
A41: Kıbrıs | B41: Cyprus | C41: CY | D41: EUR | E41: 0.7 | F41: A | G41: 3 | H41: 1.49 | I41: =IF(F41="S",1,IF(F41="A",0.8,IF(F41="B",0.55,IF(F41="C",0.3,IF(F41="D",0.25,0.25))))) -> 0.8 | J41: =MAX(H41,G41*I41) -> 2.4 | K41: =IFERROR(__xludf.DUMMYFUNCTION("GOOGLEFINANCE(""CURRENCY:USDEUR"")"),0.8519) -> 0.8519 | L41: =J41*K41 -> 2.04456 | M41: 1.9
A42: Çekya | B42: czechia | C42: CZ | D42: CZK | E42: 0.6 | F42: A | G42: 3 | H42: 1.49 | I42: =IF(F42="S",1,IF(F42="A",0.8,IF(F42="B",0.55,IF(F42="C",0.3,IF(F42="D",0.25,0.25))))) -> 0.8 | J42: =MAX(H42,G42*I42) -> 2.4 | K42: =IFERROR(__xludf.DUMMYFUNCTION("GOOGLEFINANCE(""CURRENCY:USDCZK"")"),20.7329) -> 20.7329 | L42: =J42*K42 -> 49.75896 | M42: 48.9
A43: Danimarka | B43: Denmark | C43: DK | D43: DKK | E43: 0.92 | F43: S | G43: 3 | H43: 1.49 | I43: =IF(F43="S",1,IF(F43="A",0.8,IF(F43="B",0.55,IF(F43="C",0.3,IF(F43="D",0.25,0.25))))) -> 1 | J43: =MAX(H43,G43*I43) -> 3 | K43: =IFERROR(__xludf.DUMMYFUNCTION("GOOGLEFINANCE(""CURRENCY:USDDKK"")"),6.36478) -> 6.36478 | L43: =J43*K43 -> 19.09434 | M43: 18.9
A44: Cibuti | B44: Djibouti | C44: DJ | D44: DJF | E44: 0.25 | F44: D | G44: 3 | H44: 1.49 | I44: =IF(F44="S",1,IF(F44="A",0.8,IF(F44="B",0.55,IF(F44="C",0.3,IF(F44="D",0.25,0.25))))) -> 0.25 | J44: =MAX(H44,G44*I44) -> 1.49 | K44: =IFERROR(__xludf.DUMMYFUNCTION("GOOGLEFINANCE(""CURRENCY:USDDJF"")"),178.0926) -> 178.0926 | L44: =J44*K44 -> 265.35797 | M44: 249
A45: Dominika | B45: Dominica | C45: DO | D45: XCD | E45: 0.55 | F45: B | G45: 3 | H45: 1.49 | I45: =IF(F45="S",1,IF(F45="A",0.8,IF(F45="B",0.55,IF(F45="C",0.3,IF(F45="D",0.25,0.25))))) -> 0.55 | J45: =MAX(H45,G45*I45) -> 1.65 | K45: =IFERROR(__xludf.DUMMYFUNCTION("GOOGLEFINANCE(""CURRENCY:USDXCD"")"),2.70255) -> 2.70255 | L45: =J45*K45 -> 4.4592075 | M45: 4.39
A46: Dominik Cumhuriyeti | B46: Dominican Republic | C46: DO | D46: DOP | E46: 0.35 | F46: C | G46: 3 | H46: 1.49 | I46: =IF(F46="S",1,IF(F46="A",0.8,IF(F46="B",0.55,IF(F46="C",0.3,IF(F46="D",0.25,0.25))))) -> 0.3 | J46: =MAX(H46,G46*I46) -> 1.49 | K46: =IFERROR(__xludf.DUMMYFUNCTION("GOOGLEFINANCE(""CURRENCY:USDDOP"")"),59.02346000000001) -> 59.02346 | L46: =J46*K46 -> 87.944955 | M46: 79
A47: Ekvador | B47: Ecuador | C47: EC | D47: USD | E47: 0.4 | F47: B | G47: 3 | H47: 1.49 | I47: =IF(F47="S",1,IF(F47="A",0.8,IF(F47="B",0.55,IF(F47="C",0.3,IF(F47="D",0.25,0.25))))) -> 0.55 | J47: =MAX(H47,G47*I47) -> 1.65 | K47: =IFERROR(__xludf.DUMMYFUNCTION("GOOGLEFINANCE(""CURRENCY:USDUSD"")"),"#N/A") -> #N/A | L47: =J47*K47 -> #N/A
A48: Mısır | B48: Egypt | C48: EG | D48: EGP | E48: 0.25 | F48: C | G48: 3 | H48: 1.49 | I48: =IF(F48="S",1,IF(F48="A",0.8,IF(F48="B",0.55,IF(F48="C",0.3,IF(F48="D",0.25,0.25))))) -> 0.3 | J48: =MAX(H48,G48*I48) -> 1.49 | K48: =IFERROR(__xludf.DUMMYFUNCTION("GOOGLEFINANCE(""CURRENCY:USDEGP"")"),52.9003) -> 52.9003 | L48: =J48*K48 -> 78.821447 | M48: 69
A49: El Salvador | B49: El Salvador | C49: SV | D49: SVC-USD | E49: 0.3 | F49: D | G49: 3 | H49: 1.49 | I49: =IF(F49="S",1,IF(F49="A",0.8,IF(F49="B",0.55,IF(F49="C",0.3,IF(F49="D",0.25,0.25))))) -> 0.25 | J49: =MAX(H49,G49*I49) -> 1.49 | K49: =IFERROR(__xludf.DUMMYFUNCTION("GOOGLEFINANCE(""CURRENCY:USDSVC"")"),8.750798999999999) -> 8.750799 | L49: =J49*K49 -> 13.038691 | M49: 12.9
A50: Eritre | B50: Eritrea | C50: ER | D50: ERN | E50: 0.15 | F50: D | G50: 3 | H50: 1.49 | I50: =IF(F50="S",1,IF(F50="A",0.8,IF(F50="B",0.55,IF(F50="C",0.3,IF(F50="D",0.25,0.25))))) -> 0.25 | J50: =MAX(H50,G50*I50) -> 1.49 | K50: =IFERROR(__xludf.DUMMYFUNCTION("GOOGLEFINANCE(""CURRENCY:USDERN"")"),"#N/A") -> #N/A | L50: =J50*K50 -> #N/A
A51: Estonya | B51: Estonia | C51: EE | D51: EUR | E51: 0.65 | F51: A | G51: 3 | H51: 1.49 | I51: =IF(F51="S",1,IF(F51="A",0.8,IF(F51="B",0.55,IF(F51="C",0.3,IF(F51="D",0.25,0.25))))) -> 0.8 | J51: =MAX(H51,G51*I51) -> 2.4 | K51: =IFERROR(__xludf.DUMMYFUNCTION("GOOGLEFINANCE(""CURRENCY:USDEUR"")"),0.8519) -> 0.8519 | L51: =J51*K51 -> 2.04456 | M51: 1.9
A52: Fiji | B52: Fiji | C52: FJ | D52: FJD | E52: 0.4 | F52: B | G52: 3 | H52: 1.49 | I52: =IF(F52="S",1,IF(F52="A",0.8,IF(F52="B",0.55,IF(F52="C",0.3,IF(F52="D",0.25,0.25))))) -> 0.55 | J52: =MAX(H52,G52*I52) -> 1.65 | K52: =IFERROR(__xludf.DUMMYFUNCTION("GOOGLEFINANCE(""CURRENCY:USDFJD"")"),2.1853499999999997) -> 2.18535 | L52: =J52*K52 -> 3.6058275 | M52: 3.49
A53: Finlandiya | B53: Finland | C53: FI | D53: EUR | E53: 0.85 | F53: A | G53: 3 | H53: 1.49 | I53: =IF(F53="S",1,IF(F53="A",0.8,IF(F53="B",0.55,IF(F53="C",0.3,IF(F53="D",0.25,0.25))))) -> 0.8 | J53: =MAX(H53,G53*I53) -> 2.4 | K53: =IFERROR(__xludf.DUMMYFUNCTION("GOOGLEFINANCE(""CURRENCY:USDEUR"")"),0.8519) -> 0.8519 | L53: =J53*K53 -> 2.04456 | M53: 1.9
A54: Fransa | B54: France | C54: FR | D54: EUR | E54: 0.82 | F54: S | G54: 3 | H54: 1.49 | I54: =IF(F54="S",1,IF(F54="A",0.8,IF(F54="B",0.55,IF(F54="C",0.3,IF(F54="D",0.25,0.25))))) -> 1 | J54: =MAX(H54,G54*I54) -> 3 | K54: =IFERROR(__xludf.DUMMYFUNCTION("GOOGLEFINANCE(""CURRENCY:USDEUR"")"),0.8519) -> 0.8519 | L54: =J54*K54 -> 2.5557 | M54: 2.49
A55: Gabon | B55: Gabon | C55: GA | D55: XAF | E55: 0.4 | F55: B | G55: 3 | H55: 1.49 | I55: =IF(F55="S",1,IF(F55="A",0.8,IF(F55="B",0.55,IF(F55="C",0.3,IF(F55="D",0.25,0.25))))) -> 0.55 | J55: =MAX(H55,G55*I55) -> 1.65 | K55: =IFERROR(__xludf.DUMMYFUNCTION("GOOGLEFINANCE(""CURRENCY:USDXAF"")"),558.7654) -> 558.7654 | L55: =J55*K55 -> 921.96291 | M55: 890
A56: Gambiya | B56: Gambia | C56: GM | D56: GMD | E56: 0.18 | F56: D | G56: 3 | H56: 1.49 | I56: =IF(F56="S",1,IF(F56="A",0.8,IF(F56="B",0.55,IF(F56="C",0.3,IF(F56="D",0.25,0.25))))) -> 0.25 | J56: =MAX(H56,G56*I56) -> 1.49 | K56: =IFERROR(__xludf.DUMMYFUNCTION("GOOGLEFINANCE(""CURRENCY:USDGMD"")"),73.5) -> 73.5 | L56: =J56*K56 -> 109.515 | M56: 89
A57: Gürcistan | B57: Georgia | C57: GE | D57: GEL | E57: 0.35 | F57: C | G57: 3 | H57: 1.49 | I57: =IF(F57="S",1,IF(F57="A",0.8,IF(F57="B",0.55,IF(F57="C",0.3,IF(F57="D",0.25,0.25))))) -> 0.3 | J57: =MAX(H57,G57*I57) -> 1.49 | K57: =IFERROR(__xludf.DUMMYFUNCTION("GOOGLEFINANCE(""CURRENCY:USDGEL"")"),2.67) -> 2.67 | L57: =J57*K57 -> 3.9783 | M57: 3.49
A58: Almanya | B58: Germany | C58: DE | D58: EUR | E58: 0.85 | F58: S | G58: 3 | H58: 1.49 | I58: =IF(F58="S",1,IF(F58="A",0.8,IF(F58="B",0.55,IF(F58="C",0.3,IF(F58="D",0.25,0.25))))) -> 1 | J58: =MAX(H58,G58*I58) -> 3 | K58: =IFERROR(__xludf.DUMMYFUNCTION("GOOGLEFINANCE(""CURRENCY:USDEUR"")"),0.8519) -> 0.8519 | L58: =J58*K58 -> 2.5557 | M58: 2.49
A59: Gana | B59: Ghana | C59: GH | D59: GHS | E59: 0.22 | F59: D | G59: 3 | H59: 1.49 | I59: =IF(F59="S",1,IF(F59="A",0.8,IF(F59="B",0.55,IF(F59="C",0.3,IF(F59="D",0.25,0.25))))) -> 0.25 | J59: =MAX(H59,G59*I59) -> 1.49 | K59: =IFERROR(__xludf.DUMMYFUNCTION("GOOGLEFINANCE(""CURRENCY:USDGHS"")"),11.29109) -> 11.29109 | L59: =J59*K59 -> 16.823724 | M59: 15.9
A60: Cebelitarık | B60: Gibraltar | C60: GI | D60: GIP | E60: 0.9 | F60: A | G60: 3 | H60: 1.49 | I60: =IF(F60="S",1,IF(F60="A",0.8,IF(F60="B",0.55,IF(F60="C",0.3,IF(F60="D",0.25,0.25))))) -> 0.8 | J60: =MAX(H60,G60*I60) -> 2.4 | K60: =IFERROR(__xludf.DUMMYFUNCTION("GOOGLEFINANCE(""CURRENCY:USDGIP"")"),"#N/A") -> #N/A | L60: =J60*K60 -> #N/A
A61: Yunanistan | B61: Greece | C61: GR | D61: EUR | E61: 0.65 | F61: A | G61: 3 | H61: 1.49 | I61: =IF(F61="S",1,IF(F61="A",0.8,IF(F61="B",0.55,IF(F61="C",0.3,IF(F61="D",0.25,0.25))))) -> 0.8 | J61: =MAX(H61,G61*I61) -> 2.4 | K61: =IFERROR(__xludf.DUMMYFUNCTION("GOOGLEFINANCE(""CURRENCY:USDEUR"")"),0.8519) -> 0.8519 | L61: =J61*K61 -> 2.04456 | M61: 1.9
A62: Grenada | B62: Grenada | C62: GD | D62: XCD | E62: 0.55 | F62: B | G62: 3 | H62: 1.49 | I62: =IF(F62="S",1,IF(F62="A",0.8,IF(F62="B",0.55,IF(F62="C",0.3,IF(F62="D",0.25,0.25))))) -> 0.55 | J62: =MAX(H62,G62*I62) -> 1.65 | K62: =IFERROR(__xludf.DUMMYFUNCTION("GOOGLEFINANCE(""CURRENCY:USDXCD"")"),2.70255) -> 2.70255 | L62: =J62*K62 -> 4.4592075 | M62: 4.39
A63: Guatemala | B63: Guatemala | C63: GT | D63: GTQ | E63: 0.3 | F63: D | G63: 3 | H63: 1.49 | I63: =IF(F63="S",1,IF(F63="A",0.8,IF(F63="B",0.55,IF(F63="C",0.3,IF(F63="D",0.25,0.25))))) -> 0.25 | J63: =MAX(H63,G63*I63) -> 1.49 | K63: =IFERROR(__xludf.DUMMYFUNCTION("GOOGLEFINANCE(""CURRENCY:USDGTQ"")"),7.630745999999999) -> 7.630746 | L63: =J63*K63 -> 11.369812 | M63: 9.9
A64: Gine | B64: Guinea | C64: GN | D64: GNF | E64: 0.15 | F64: D | G64: 3 | H64: 1.49 | I64: =IF(F64="S",1,IF(F64="A",0.8,IF(F64="B",0.55,IF(F64="C",0.3,IF(F64="D",0.25,0.25))))) -> 0.25 | J64: =MAX(H64,G64*I64) -> 1.49 | K64: =IFERROR(__xludf.DUMMYFUNCTION("GOOGLEFINANCE(""CURRENCY:USDGNF"")"),8775.576000000001) -> 8775.576 | L64: =J64*K64 -> 13075.608 | M64: 9900
A65: Gine-Bissau | B65: Guinea-Bissau | C65: GW | D65: XOF | E65: 0.15 | F65: D | G65: 3 | H65: 1.49 | I65: =IF(F65="S",1,IF(F65="A",0.8,IF(F65="B",0.55,IF(F65="C",0.3,IF(F65="D",0.25,0.25))))) -> 0.25 | J65: =MAX(H65,G65*I65) -> 1.49 | K65: =IFERROR(__xludf.DUMMYFUNCTION("GOOGLEFINANCE(""CURRENCY:USDXOF"")"),558.7654) -> 558.7654 | L65: =J65*K65 -> 832.56045 | M65: 790
A66: Haiti | B66: Haiti | C66: HT | D66: HTG | E66: 0.15 | F66: D | G66: 3 | H66: 1.49 | I66: =IF(F66="S",1,IF(F66="A",0.8,IF(F66="B",0.55,IF(F66="C",0.3,IF(F66="D",0.25,0.25))))) -> 0.25 | J66: =MAX(H66,G66*I66) -> 1.49 | K66: =IFERROR(__xludf.DUMMYFUNCTION("GOOGLEFINANCE(""CURRENCY:USDHTG"")"),130.6626) -> 130.6626 | L66: =J66*K66 -> 194.68727 | M66: 189
A67: Honduras | B67: Honduras | C67: HN | D67: HNL | E67: 0.25 | F67: D | G67: 3 | H67: 1.49 | I67: =IF(F67="S",1,IF(F67="A",0.8,IF(F67="B",0.55,IF(F67="C",0.3,IF(F67="D",0.25,0.25))))) -> 0.25 | J67: =MAX(H67,G67*I67) -> 1.49 | K67: =IFERROR(__xludf.DUMMYFUNCTION("GOOGLEFINANCE(""CURRENCY:USDHNL"")"),26.5942) -> 26.5942 | L67: =J67*K67 -> 39.625358 | M67: 38.9
A68: HongKong | B68: HongKong | C68: HK | D68: HKD | E68: 0.95 | F68: S | G68: 3 | H68: 1.49 | I68: =IF(F68="S",1,IF(F68="A",0.8,IF(F68="B",0.55,IF(F68="C",0.3,IF(F68="D",0.25,0.25))))) -> 1 | J68: =MAX(H68,G68*I68) -> 3 | K68: =IFERROR(__xludf.DUMMYFUNCTION("GOOGLEFINANCE(""CURRENCY:USDHKD"")"),7.82905) -> 7.82905 | L68: =J68*K68 -> 23.48715 | M68: 22.9
A69: Macaristan | B69: Hungary | C69: HU | D69: HUF | E69: 0.5 | F69: B | G69: 3 | H69: 1.49 | I69: =IF(F69="S",1,IF(F69="A",0.8,IF(F69="B",0.55,IF(F69="C",0.3,IF(F69="D",0.25,0.25))))) -> 0.55 | J69: =MAX(H69,G69*I69) -> 1.65 | K69: =IFERROR(__xludf.DUMMYFUNCTION("GOOGLEFINANCE(""CURRENCY:USDHUF"")"),304.6995) -> 304.6995 | L69: =J69*K69 -> 502.75417 | M69: 490
A70: İzlanda | B70: Iceland | C70: IS | D70: ISK | E70: 0.95 | F70: S | G70: 3 | H70: 1.49 | I70: =IF(F70="S",1,IF(F70="A",0.8,IF(F70="B",0.55,IF(F70="C",0.3,IF(F70="D",0.25,0.25))))) -> 1 | J70: =MAX(H70,G70*I70) -> 3 | K70: =IFERROR(__xludf.DUMMYFUNCTION("GOOGLEFINANCE(""CURRENCY:USDISK"")"),122.34) -> 122.34 | L70: =J70*K70 -> 367.02 | M70: 349
A71: Hindistan | B71: Indian | C71: IN | D71: INR | E71: 0.2 | F71: C | G71: 3 | H71: 1.49 | I71: =IF(F71="S",1,IF(F71="A",0.8,IF(F71="B",0.55,IF(F71="C",0.3,IF(F71="D",0.25,0.25))))) -> 0.3 | J71: =MAX(H71,G71*I71) -> 1.49 | K71: =IFERROR(__xludf.DUMMYFUNCTION("GOOGLEFINANCE(""CURRENCY:USDINR"")"),95.6405) -> 95.6405 | L71: =J71*K71 -> 142.50435 | M71: 139
A72: Endonezya | B72: Indonesia | C72: ID | D72: IDR | E72: 0.25 | F72: C | G72: 3 | H72: 1.49 | I72: =IF(F72="S",1,IF(F72="A",0.8,IF(F72="B",0.55,IF(F72="C",0.3,IF(F72="D",0.25,0.25))))) -> 0.3 | J72: =MAX(H72,G72*I72) -> 1.49 | K72: =IFERROR(__xludf.DUMMYFUNCTION("GOOGLEFINANCE(""CURRENCY:USDIDR"")"),17547.0) -> 17547 | L72: =J72*K72 -> 26145.03 | M72: 24900
A73: Irak | B73: Iraq | C73: IQ | D73: IQD | E73: 0.3 | F73: D | G73: 3 | H73: 1.49 | I73: =IF(F73="S",1,IF(F73="A",0.8,IF(F73="B",0.55,IF(F73="C",0.3,IF(F73="D",0.25,0.25))))) -> 0.25 | J73: =MAX(H73,G73*I73) -> 1.49 | K73: =IFERROR(__xludf.DUMMYFUNCTION("GOOGLEFINANCE(""CURRENCY:USDIQD"")"),1310.107) -> 1310.107 | L73: =J73*K73 -> 1952.0594 | M73: 1890
A74: İrlanda | B74: Ireland | C74: IE | D74: EUR | E74: 0.9 | F74: A | G74: 3 | H74: 1.49 | I74: =IF(F74="S",1,IF(F74="A",0.8,IF(F74="B",0.55,IF(F74="C",0.3,IF(F74="D",0.25,0.25))))) -> 0.8 | J74: =MAX(H74,G74*I74) -> 2.4 | K74: =IFERROR(__xludf.DUMMYFUNCTION("GOOGLEFINANCE(""CURRENCY:USDEUR"")"),0.8519) -> 0.8519 | L74: =J74*K74 -> 2.04456 | M74: 1.9
A75: İsrail | B75: Israel | C75: IL | D75: ILS | E75: 0.9 | F75: A | G75: 3 | H75: 1.49 | I75: =IF(F75="S",1,IF(F75="A",0.8,IF(F75="B",0.55,IF(F75="C",0.3,IF(F75="D",0.25,0.25))))) -> 0.8 | J75: =MAX(H75,G75*I75) -> 2.4 | K75: =IFERROR(__xludf.DUMMYFUNCTION("GOOGLEFINANCE(""CURRENCY:USDILS"")"),2.91395) -> 2.91395 | L75: =J75*K75 -> 6.99348 | M75: 6.9
A76: İtalya | B76: Italy | C76: IT | D76: EUR | E76: 0.78 | F76: A | G76: 3 | H76: 1.49 | I76: =IF(F76="S",1,IF(F76="A",0.8,IF(F76="B",0.55,IF(F76="C",0.3,IF(F76="D",0.25,0.25))))) -> 0.8 | J76: =MAX(H76,G76*I76) -> 2.4 | K76: =IFERROR(__xludf.DUMMYFUNCTION("GOOGLEFINANCE(""CURRENCY:USDEUR"")"),0.8519) -> 0.8519 | L76: =J76*K76 -> 2.04456 | M76: 1.9
A77: Jamaika | B77: Jamaica | C77: JM | D77: JMD | E77: 0.45 | F77: B | G77: 3 | H77: 1.49 | I77: =IF(F77="S",1,IF(F77="A",0.8,IF(F77="B",0.55,IF(F77="C",0.3,IF(F77="D",0.25,0.25))))) -> 0.55 | J77: =MAX(H77,G77*I77) -> 1.65 | K77: =IFERROR(__xludf.DUMMYFUNCTION("GOOGLEFINANCE(""CURRENCY:USDJMD"")"),158.0319) -> 158.0319 | L77: =J77*K77 -> 260.75263 | M77: 249
A78: Japonya | B78: Japan | C78: JP | D78: JPY | E78: 0.9 | F78: S | G78: 3 | H78: 1.49 | I78: =IF(F78="S",1,IF(F78="A",0.8,IF(F78="B",0.55,IF(F78="C",0.3,IF(F78="D",0.25,0.25))))) -> 1 | J78: =MAX(H78,G78*I78) -> 3 | K78: =IFERROR(__xludf.DUMMYFUNCTION("GOOGLEFINANCE(""CURRENCY:USDJPY"")"),157.6045) -> 157.6045 | L78: =J78*K78 -> 472.8135 | M78: 449
A79: Ürdün | B79: Jordan | C79: JO | D79: JOD | E79: 0.45 | F79: B | G79: 3 | H79: 1.49 | I79: =IF(F79="S",1,IF(F79="A",0.8,IF(F79="B",0.55,IF(F79="C",0.3,IF(F79="D",0.25,0.25))))) -> 0.55 | J79: =MAX(H79,G79*I79) -> 1.65 | K79: =IFERROR(__xludf.DUMMYFUNCTION("GOOGLEFINANCE(""CURRENCY:USDJOD"")"),0.709) -> 0.709 | L79: =J79*K79 -> 1.16985 | M79: 0.9
A80: Kazakistan | B80: Kazakhstan | C80: KZ | D80: KZT | E80: 0.45 | F80: B | G80: 3 | H80: 1.49 | I80: =IF(F80="S",1,IF(F80="A",0.8,IF(F80="B",0.55,IF(F80="C",0.3,IF(F80="D",0.25,0.25))))) -> 0.55 | J80: =MAX(H80,G80*I80) -> 1.65 | K80: =IFERROR(__xludf.DUMMYFUNCTION("GOOGLEFINANCE(""CURRENCY:USDKZT"")"),463.8784) -> 463.8784 | L80: =J80*K80 -> 765.39936 | M80: 749
A81: Kenya | B81: Kenya | C81: KE | D81: KES | E81: 0.22 | F81: D | G81: 3 | H81: 1.49 | I81: =IF(F81="S",1,IF(F81="A",0.8,IF(F81="B",0.55,IF(F81="C",0.3,IF(F81="D",0.25,0.25))))) -> 0.25 | J81: =MAX(H81,G81*I81) -> 1.49 | K81: =IFERROR(__xludf.DUMMYFUNCTION("GOOGLEFINANCE(""CURRENCY:USDKES"")"),129.16) -> 129.16 | L81: =J81*K81 -> 192.4484 | M81: 189
A82: Kuveyt | B82: Kuwait | C82: KW | D82: KWD | E82: 0.9 | F82: S | G82: 3 | H82: 1.49 | I82: =IF(F82="S",1,IF(F82="A",0.8,IF(F82="B",0.55,IF(F82="C",0.3,IF(F82="D",0.25,0.25))))) -> 1 | J82: =MAX(H82,G82*I82) -> 3 | K82: =IFERROR(__xludf.DUMMYFUNCTION("GOOGLEFINANCE(""CURRENCY:USDKWD"")"),0.3081) -> 0.3081 | L82: =J82*K82 -> 0.9243 | M82: 0.89
A83: Kırgızistan | B83: Kyrgyzstan | C83: KG | D83: KGS | E83: 0.25 | F83: D | G83: 3 | H83: 1.49 | I83: =IF(F83="S",1,IF(F83="A",0.8,IF(F83="B",0.55,IF(F83="C",0.3,IF(F83="D",0.25,0.25))))) -> 0.25 | J83: =MAX(H83,G83*I83) -> 1.49 | K83: =IFERROR(__xludf.DUMMYFUNCTION("GOOGLEFINANCE(""CURRENCY:USDKGS"")"),87.45) -> 87.45 | L83: =J83*K83 -> 130.3005 | M83: 119
A84: Laos | B84: Lao People's Democratic Republic | C84: LA | D84: LAK | E84: 0.18 | F84: D | G84: 3 | H84: 1.49 | I84: =IF(F84="S",1,IF(F84="A",0.8,IF(F84="B",0.55,IF(F84="C",0.3,IF(F84="D",0.25,0.25))))) -> 0.25 | J84: =MAX(H84,G84*I84) -> 1.49 | K84: =IFERROR(__xludf.DUMMYFUNCTION("GOOGLEFINANCE(""CURRENCY:USDLAK"")"),21924.27) -> 21924.27 | L84: =J84*K84 -> 32667.162 | M84: 29900
A85: Letonya | B85: Latvia | C85: LV | D85: EUR | E85: 0.6 | F85: B | G85: 3 | H85: 1.49 | I85: =IF(F85="S",1,IF(F85="A",0.8,IF(F85="B",0.55,IF(F85="C",0.3,IF(F85="D",0.25,0.25))))) -> 0.55 | J85: =MAX(H85,G85*I85) -> 1.65 | K85: =IFERROR(__xludf.DUMMYFUNCTION("GOOGLEFINANCE(""CURRENCY:USDEUR"")"),0.8519) -> 0.8519 | L85: =J85*K85 -> 1.405635 | M85: 0.99
A86: Lübnan | B86: Lebanon | C86: LB | D86: LBP | E86: 0.4 | F86: B | G86: 3 | H86: 1.49 | I86: =IF(F86="S",1,IF(F86="A",0.8,IF(F86="B",0.55,IF(F86="C",0.3,IF(F86="D",0.25,0.25))))) -> 0.55 | J86: =MAX(H86,G86*I86) -> 1.65 | K86: =IFERROR(__xludf.DUMMYFUNCTION("GOOGLEFINANCE(""CURRENCY:USDLBP"")"),89559.52) -> 89559.52 | L86: =J86*K86 -> 147773.21 | M86: 139000
A87: Liberya | B87: Liberia | C87: LR | D87: LRD | E87: 0.18 | F87: D | G87: 3 | H87: 1.49 | I87: =IF(F87="S",1,IF(F87="A",0.8,IF(F87="B",0.55,IF(F87="C",0.3,IF(F87="D",0.25,0.25))))) -> 0.25 | J87: =MAX(H87,G87*I87) -> 1.49 | K87: =IFERROR(__xludf.DUMMYFUNCTION("GOOGLEFINANCE(""CURRENCY:USDLRD"")"),183.0247) -> 183.0247 | L87: =J87*K87 -> 272.7068 | M87: 249
A88: Libya | B88: Libya | C88: LY | D88: LYD | E88: 0.35 | F88: C | G88: 3 | H88: 1.49 | I88: =IF(F88="S",1,IF(F88="A",0.8,IF(F88="B",0.55,IF(F88="C",0.3,IF(F88="D",0.25,0.25))))) -> 0.3 | J88: =MAX(H88,G88*I88) -> 1.49 | K88: =IFERROR(__xludf.DUMMYFUNCTION("GOOGLEFINANCE(""CURRENCY:USDLYD"")"),6.3274099999999995) -> 6.32741 | L88: =J88*K88 -> 9.4278409 | M88: 9.39
A89: Liechtenstan | B89: Liechtenstein | C89: LI | D89: CHF | E89: 1 | F89: S | G89: 3 | H89: 1.49 | I89: =IF(F89="S",1,IF(F89="A",0.8,IF(F89="B",0.55,IF(F89="C",0.3,IF(F89="D",0.25,0.25))))) -> 1 | J89: =MAX(H89,G89*I89) -> 3 | K89: =IFERROR(__xludf.DUMMYFUNCTION("GOOGLEFINANCE(""CURRENCY:USDCHF"")"),0.78042) -> 0.78042 | L89: =J89*K89 -> 2.34126 | M89: 2.19
A90: Litvanya | B90: Lithuania | C90: LT | D90: EUR | E90: 0.65 | F90: B | G90: 3 | H90: 1.49 | I90: =IF(F90="S",1,IF(F90="A",0.8,IF(F90="B",0.55,IF(F90="C",0.3,IF(F90="D",0.25,0.25))))) -> 0.55 | J90: =MAX(H90,G90*I90) -> 1.65 | K90: =IFERROR(__xludf.DUMMYFUNCTION("GOOGLEFINANCE(""CURRENCY:USDEUR"")"),0.8519) -> 0.8519 | L90: =J90*K90 -> 1.405635 | M90: 1.39
A91: Lüksemburg | B91: Luxembourg | C91: LU | D91: EUR | E91: 1 | F91: S | G91: 3 | H91: 1.49 | I91: =IF(F91="S",1,IF(F91="A",0.8,IF(F91="B",0.55,IF(F91="C",0.3,IF(F91="D",0.25,0.25))))) -> 1 | J91: =MAX(H91,G91*I91) -> 3 | K91: =IFERROR(__xludf.DUMMYFUNCTION("GOOGLEFINANCE(""CURRENCY:USDEUR"")"),0.8519) -> 0.8519 | L91: =J91*K91 -> 2.5557 | M91: 2.49
A92: Makao | B92: Macao | C92: MO | D92: MOP | E92: 0.85 | F92: A | G92: 3 | H92: 1.49 | I92: =IF(F92="S",1,IF(F92="A",0.8,IF(F92="B",0.55,IF(F92="C",0.3,IF(F92="D",0.25,0.25))))) -> 0.8 | J92: =MAX(H92,G92*I92) -> 2.4 | K92: =IFERROR(__xludf.DUMMYFUNCTION("GOOGLEFINANCE(""CURRENCY:USDMOP"")"),8.064551999999999) -> 8.064552 | L92: =J92*K92 -> 19.354925 | M92: 18.9
A93: Malezya | B93: Malaysia | C93: MY | D93: MYR | E93: 0.5 | F93: B | G93: 3 | H93: 1.49 | I93: =IF(F93="S",1,IF(F93="A",0.8,IF(F93="B",0.55,IF(F93="C",0.3,IF(F93="D",0.25,0.25))))) -> 0.55 | J93: =MAX(H93,G93*I93) -> 1.65 | K93: =IFERROR(__xludf.DUMMYFUNCTION("GOOGLEFINANCE(""CURRENCY:USDMYR"")"),3.9339999999999997) -> 3.934 | L93: =J93*K93 -> 6.4911 | M93: 6.39
A94: Maldivler | B94: Maldives | C94: MV | D94: MVR | E94: 0.45 | F94: B | G94: 3 | H94: 1.49 | I94: =IF(F94="S",1,IF(F94="A",0.8,IF(F94="B",0.55,IF(F94="C",0.3,IF(F94="D",0.25,0.25))))) -> 0.55 | J94: =MAX(H94,G94*I94) -> 1.65 | K94: =IFERROR(__xludf.DUMMYFUNCTION("GOOGLEFINANCE(""CURRENCY:USDMVR"")"),15.400000000000002) -> 15.4 | L94: =J94*K94 -> 25.41 | M94: 24.9
A95: Mali | B95: Mali | C95: ML | D95: XOF | E95: 0.15 | F95: D | G95: 3 | H95: 1.49 | I95: =IF(F95="S",1,IF(F95="A",0.8,IF(F95="B",0.55,IF(F95="C",0.3,IF(F95="D",0.25,0.25))))) -> 0.25 | J95: =MAX(H95,G95*I95) -> 1.49 | K95: =IFERROR(__xludf.DUMMYFUNCTION("GOOGLEFINANCE(""CURRENCY:USDXOF"")"),558.7654) -> 558.7654 | L95: =J95*K95 -> 832.56045 | M95: 790
A96: Malta | B96: Malta | C96: MT | D96: EUR | E96: 0.75 | F96: A | G96: 3 | H96: 1.49 | I96: =IF(F96="S",1,IF(F96="A",0.8,IF(F96="B",0.55,IF(F96="C",0.3,IF(F96="D",0.25,0.25))))) -> 0.8 | J96: =MAX(H96,G96*I96) -> 2.4 | K96: =IFERROR(__xludf.DUMMYFUNCTION("GOOGLEFINANCE(""CURRENCY:USDEUR"")"),0.8519) -> 0.8519 | L96: =J96*K96 -> 2.04456 | M96: 1.9
A97: Mauritius | B97: Mauritius | C97: MU | D97: MUR | E97: 0.22 | F97: D | G97: 3 | H97: 1.49 | I97: =IF(F97="S",1,IF(F97="A",0.8,IF(F97="B",0.55,IF(F97="C",0.3,IF(F97="D",0.25,0.25))))) -> 0.25 | J97: =MAX(H97,G97*I97) -> 1.49 | K97: =IFERROR(__xludf.DUMMYFUNCTION("GOOGLEFINANCE(""CURRENCY:USDMUR"")"),46.7) -> 46.7 | L97: =J97*K97 -> 69.583 | M97: 64.9
A98: Meksika | B98: Mexico | C98: MX | D98: MXN | E98: 0.4 | F98: B | G98: 3 | H98: 1.49 | I98: =IF(F98="S",1,IF(F98="A",0.8,IF(F98="B",0.55,IF(F98="C",0.3,IF(F98="D",0.25,0.25))))) -> 0.55 | J98: =MAX(H98,G98*I98) -> 1.65 | K98: =IFERROR(__xludf.DUMMYFUNCTION("GOOGLEFINANCE(""CURRENCY:USDMXN"")"),17.2269) -> 17.2269 | L98: =J98*K98 -> 28.424385 | M98: 24.9
A99: Mikronezya | B99: Micronesia (Federated States of) | C99: FM | D99: USD | E99: 0.3 | F99: D | G99: 3 | H99: 1.49 | I99: =IF(F99="S",1,IF(F99="A",0.8,IF(F99="B",0.55,IF(F99="C",0.3,IF(F99="D",0.25,0.25))))) -> 0.25 | J99: =MAX(H99,G99*I99) -> 1.49 | K99: =IFERROR(__xludf.DUMMYFUNCTION("GOOGLEFINANCE(""CURRENCY:USDUSD"")"),"#N/A") -> #N/A | L99: =J99*K99 -> #N/A
A100: Moldova | B100: Moldova (the Republic of) | C100: MD | D100: MDL | E100: 0.3 | F100: D | G100: 3 | H100: 1.49 | I100: =IF(F100="S",1,IF(F100="A",0.8,IF(F100="B",0.55,IF(F100="C",0.3,IF(F100="D",0.25,0.25))))) -> 0.25 | J100: =MAX(H100,G100*I100) -> 1.49 | K100: =IFERROR(__xludf.DUMMYFUNCTION("GOOGLEFINANCE(""CURRENCY:USDMDL"")"),17.116570000000003) -> 17.11657 | L100: =J100*K100 -> 25.503689 | M100: 24.9
...

Sheet RoundingRules
A1: Rounding Rules / Editable Playbook
A3: Group | B3: Currency | C3: Logic | D3: Suggested Tiers | E3: Edit Note
A4: USD_99 | B4: USD | C4: Round to x.99 | D4: 0.99 / 1.99 / 2.99 / 3.99 / 4.99 | E4: Good for US-style pricing
A5: EUR_99 | B5: EUR | C5: Round to x.99 | D5: 0.99 / 1.99 / 2.99 / 3.99 / 4.99 | E5: EU premium-friendly
A6: TRY_TIERS | B6: TRY | C6: Fixed tier bucket | D6: 19 / 29 / 39 / 49 / 79 | E6: Test 29 vs 39 for conversion/revenue
A7: INR_TIERS | B7: INR | C7: Fixed tier bucket | D7: 29 / 49 / 99 | E7: Volume market
A8: BRL_90 | B8: BRL | C8: Round to x.90 | D8: 2.90 / 4.90 / 6.90 / 9.90
A9: IDR_000 | B9: IDR | C9: Nearest 1,000 | D9: 9,000 / 15,000 / 29,000
A10: JPY_00 | B10: JPY | C10: Nearest 100 | D10: 100 / 200 / 300 / 500
A11: KRW_000 | B11: KRW | C11: Nearest 1,000 | D11: 1,000 / 2,000 / 3,000 / 5,000
A12: VND_000 | B12: VND | C12: Nearest 1,000 | D12: 10,000 / 20,000 / 30,000

Sheet SourceNotes
A1: Source Notes / References
A3: Input | B3: Purpose | C3: Source / URL | D3: Refresh Cadence | E3: Notes
A4: PPP factor | B4: Relative local affordability input | C4: https://data.worldbank.org/indicator/PA.NUS.PPP | D4: Quarterly or before price updates | E4: Template values are starter estimates; replace with your chosen normalized PPP factors.
A5: FX rate | B5: Convert USD to local currency | C5: https://www.google.com/finance/ | D5: Before Play Console update | E5: In Google Sheets, use GOOGLEFINANCE formulas copied from PricingModel column N.
A6: Google Play pricing | B6: Check supported local prices and taxes | C6: https://support.google.com/googleplay/android-developer/ | D6: Before launch and major updates | E6: Play Console final local prices may differ due to tax/minimum price constraints.
A7: Competitor pricing | B7: Market adjustment sanity check | C7: Manual Play Store research | D7: Before launch | E7: Use Market Adj column to shift price after checking similar apps.

Sheet AB_TEST
A1: Date | B1: App | C1: Country | D1: Variant | E1: Price | F1: Currency | G1: Impressions | H1: Purchases | I1: Conversion | J1: Revenue | K1: ARPU | L1: Winner Note
A2: 46143 | B2: BLE Scanner | C2: TR | D2: A | E2: 39 | F2: TRY | G2: 1200 | H2: 48 | I2: =IFERROR(H2/G2,0) -> 0.04 | J2: =IFERROR(E2*H2,0) -> 1872 | K2: =IFERROR(J2/G2,0) -> 1.56 | L2: =IF(B2="","",IF(J2=MAX(SUMIFS($J$2:$J$200,$B$2:$B$200,B2,$C$2:$C$200,C2,$D$2:$D$200,"A"),SUMIFS($J$2:$J$200,$B$2:$B$200,B2,$C$2:$C$200,C2,$D$2:$D$200,"B")),"Current Winner",""))
A3: 46150 | B3: BLE Scanner | C3: TR | D3: B | E3: 29 | F3: TRY | G3: 1350 | H3: 78 | I3: =IFERROR(H3/G3,0) -> 0.057777778 | J3: =IFERROR(E3*H3,0) -> 2262 | K3: =IFERROR(J3/G3,0) -> 1.6755556 | L3: =IF(B3="","",IF(J3=MAX(SUMIFS($J$2:$J$200,$B$2:$B$200,B3,$C$2:$C$200,C3,$D$2:$D$200,"A"),SUMIFS($J$2:$J$200,$B$2:$B$200,B3,$C$2:$C$200,C3,$D$2:$D$200,"B")),"Current Winner","")) -> Current Winner
A4: 46143 | B4: Secure Vault | C4: TR | D4: A | E4: 49 | F4: TRY | G4: 900 | H4: 32 | I4: =IFERROR(H4/G4,0) -> 0.035555556 | J4: =IFERROR(E4*H4,0) -> 1568 | K4: =IFERROR(J4/G4,0) -> 1.7422222 | L4: =IF(B4="","",IF(J4=MAX(SUMIFS($J$2:$J$200,$B$2:$B$200,B4,$C$2:$C$200,C4,$D$2:$D$200,"A"),SUMIFS($J$2:$J$200,$B$2:$B$200,B4,$C$2:$C$200,C4,$D$2:$D$200,"B")),"Current Winner",""))
A5: 46150 | B5: Secure Vault | C5: TR | D5: B | E5: 39 | F5: TRY | G5: 960 | H5: 45 | I5: =IFERROR(H5/G5,0) -> 0.046875 | J5: =IFERROR(E5*H5,0) -> 1755 | K5: =IFERROR(J5/G5,0) -> 1.828125 | L5: =IF(B5="","",IF(J5=MAX(SUMIFS($J$2:$J$200,$B$2:$B$200,B5,$C$2:$C$200,C5,$D$2:$D$200,"A"),SUMIFS($J$2:$J$200,$B$2:$B$200,B5,$C$2:$C$200,C5,$D$2:$D$200,"B")),"Current Winner","")) -> Current Winner
A6: 46143 | B6: BLE Scanner | C6: IN | D6: A | E6: 49 | F6: INR | G6: 2400 | H6: 96 | I6: =IFERROR(H6/G6,0) -> 0.04 | J6: =IFERROR(E6*H6,0) -> 4704 | K6: =IFERROR(J6/G6,0) -> 1.96 | L6: =IF(B6="","",IF(J6=MAX(SUMIFS($J$2:$J$200,$B$2:$B$200,B6,$C$2:$C$200,C6,$D$2:$D$200,"A"),SUMIFS($J$2:$J$200,$B$2:$B$200,B6,$C$2:$C$200,C6,$D$2:$D$200,"B")),"Current Winner",""))
A7: 46150 | B7: BLE Scanner | C7: IN | D7: B | E7: 29 | F7: INR | G7: 2700 | H7: 168 | I7: =IFERROR(H7/G7,0) -> 0.062222222 | J7: =IFERROR(E7*H7,0) -> 4872 | K7: =IFERROR(J7/G7,0) -> 1.8044444 | L7: =IF(B7="","",IF(J7=MAX(SUMIFS($J$2:$J$200,$B$2:$B$200,B7,$C$2:$C$200,C7,$D$2:$D$200,"A"),SUMIFS($J$2:$J$200,$B$2:$B$200,B7,$C$2:$C$200,C7,$D$2:$D$200,"B")),"Current Winner","")) -> Current Winner
A8: 46143 | B8: Secure Vault | C8: BR | D8: A | E8: 6.9 | F8: BRL | G8: 760 | H8: 20 | I8: =IFERROR(H8/G8,0) -> 0.026315789 | J8: =IFERROR(E8*H8,0) -> 138 | K8: =IFERROR(J8/G8,0) -> 0.18157895 | L8: =IF(B8="","",IF(J8=MAX(SUMIFS($J$2:$J$200,$B$2:$B$200,B8,$C$2:$C$200,C8,$D$2:$D$200,"A"),SUMIFS($J$2:$J$200,$B$2:$B$200,B8,$C$2:$C$200,C8,$D$2:$D$200,"B")),"Current Winner",""))
A9: 46150 | B9: Secure Vault | C9: BR | D9: B | E9: 4.9 | F9: BRL | G9: 830 | H9: 32 | I9: =IFERROR(H9/G9,0) -> 0.038554217 | J9: =IFERROR(E9*H9,0) -> 156.8 | K9: =IFERROR(J9/G9,0) -> 0.18891566 | L9: =IF(B9="","",IF(J9=MAX(SUMIFS($J$2:$J$200,$B$2:$B$200,B9,$C$2:$C$200,C9,$D$2:$D$200,"A"),SUMIFS($J$2:$J$200,$B$2:$B$200,B9,$C$2:$C$200,C9,$D$2:$D$200,"B")),"Current Winner","")) -> Current Winner
I10: =IFERROR(H10/G10,0) -> 0 | J10: =IFERROR(E10*H10,0) -> 0 | K10: =IFERROR(J10/G10,0) -> 0 | L10: =IF(B10="","",IF(J10=MAX(SUMIFS($J$2:$J$200,$B$2:$B$200,B10,$C$2:$C$200,C10,$D$2:$D$200,"A"),SUMIFS($J$2:$J$200,$B$2:$B$200,B10,$C$2:$C$200,C10,$D$2:$D$200,"B")),"Current Winner",""))
I11: =IFERROR(H11/G11,0) -> 0 | J11: =IFERROR(E11*H11,0) -> 0 | K11: =IFERROR(J11/G11,0) -> 0 | L11: =IF(B11="","",IF(J11=MAX(SUMIFS($J$2:$J$200,$B$2:$B$200,B11,$C$2:$C$200,C11,$D$2:$D$200,"A"),SUMIFS($J$2:$J$200,$B$2:$B$200,B11,$C$2:$C$200,C11,$D$2:$D$200,"B")),"Current Winner",""))
I12: =IFERROR(H12/G12,0) -> 0 | J12: =IFERROR(E12*H12,0) -> 0 | K12: =IFERROR(J12/G12,0) -> 0 | L12: =IF(B12="","",IF(J12=MAX(SUMIFS($J$2:$J$200,$B$2:$B$200,B12,$C$2:$C$200,C12,$D$2:$D$200,"A"),SUMIFS($J$2:$J$200,$B$2:$B$200,B12,$C$2:$C$200,C12,$D$2:$D$200,"B")),"Current Winner",""))
I13: =IFERROR(H13/G13,0) -> 0 | J13: =IFERROR(E13*H13,0) -> 0 | K13: =IFERROR(J13/G13,0) -> 0 | L13: =IF(B13="","",IF(J13=MAX(SUMIFS($J$2:$J$200,$B$2:$B$200,B13,$C$2:$C$200,C13,$D$2:$D$200,"A"),SUMIFS($J$2:$J$200,$B$2:$B$200,B13,$C$2:$C$200,C13,$D$2:$D$200,"B")),"Current Winner",""))
I14: =IFERROR(H14/G14,0) -> 0 | J14: =IFERROR(E14*H14,0) -> 0 | K14: =IFERROR(J14/G14,0) -> 0 | L14: =IF(B14="","",IF(J14=MAX(SUMIFS($J$2:$J$200,$B$2:$B$200,B14,$C$2:$C$200,C14,$D$2:$D$200,"A"),SUMIFS($J$2:$J$200,$B$2:$B$200,B14,$C$2:$C$200,C14,$D$2:$D$200,"B")),"Current Winner",""))
I15: =IFERROR(H15/G15,0) -> 0 | J15: =IFERROR(E15*H15,0) -> 0 | K15: =IFERROR(J15/G15,0) -> 0 | L15: =IF(B15="","",IF(J15=MAX(SUMIFS($J$2:$J$200,$B$2:$B$200,B15,$C$2:$C$200,C15,$D$2:$D$200,"A"),SUMIFS($J$2:$J$200,$B$2:$B$200,B15,$C$2:$C$200,C15,$D$2:$D$200,"B")),"Current Winner",""))
I16: =IFERROR(H16/G16,0) -> 0 | J16: =IFERROR(E16*H16,0) -> 0 | K16: =IFERROR(J16/G16,0) -> 0 | L16: =IF(B16="","",IF(J16=MAX(SUMIFS($J$2:$J$200,$B$2:$B$200,B16,$C$2:$C$200,C16,$D$2:$D$200,"A"),SUMIFS($J$2:$J$200,$B$2:$B$200,B16,$C$2:$C$200,C16,$D$2:$D$200,"B")),"Current Winner",""))
I17: =IFERROR(H17/G17,0) -> 0 | J17: =IFERROR(E17*H17,0) -> 0 | K17: =IFERROR(J17/G17,0) -> 0 | L17: =IF(B17="","",IF(J17=MAX(SUMIFS($J$2:$J$200,$B$2:$B$200,B17,$C$2:$C$200,C17,$D$2:$D$200,"A"),SUMIFS($J$2:$J$200,$B$2:$B$200,B17,$C$2:$C$200,C17,$D$2:$D$200,"B")),"Current Winner",""))
I18: =IFERROR(H18/G18,0) -> 0 | J18: =IFERROR(E18*H18,0) -> 0 | K18: =IFERROR(J18/G18,0) -> 0 | L18: =IF(B18="","",IF(J18=MAX(SUMIFS($J$2:$J$200,$B$2:$B$200,B18,$C$2:$C$200,C18,$D$2:$D$200,"A"),SUMIFS($J$2:$J$200,$B$2:$B$200,B18,$C$2:$C$200,C18,$D$2:$D$200,"B")),"Current Winner",""))
I19: =IFERROR(H19/G19,0) -> 0 | J19: =IFERROR(E19*H19,0) -> 0 | K19: =IFERROR(J19/G19,0) -> 0 | L19: =IF(B19="","",IF(J19=MAX(SUMIFS($J$2:$J$200,$B$2:$B$200,B19,$C$2:$C$200,C19,$D$2:$D$200,"A"),SUMIFS($J$2:$J$200,$B$2:$B$200,B19,$C$2:$C$200,C19,$D$2:$D$200,"B")),"Current Winner",""))
I20: =IFERROR(H20/G20,0) -> 0 | J20: =IFERROR(E20*H20,0) -> 0 | K20: =IFERROR(J20/G20,0) -> 0 | L20: =IF(B20="","",IF(J20=MAX(SUMIFS($J$2:$J$200,$B$2:$B$200,B20,$C$2:$C$200,C20,$D$2:$D$200,"A"),SUMIFS($J$2:$J$200,$B$2:$B$200,B20,$C$2:$C$200,C20,$D$2:$D$200,"B")),"Current Winner",""))
I21: =IFERROR(H21/G21,0) -> 0 | J21: =IFERROR(E21*H21,0) -> 0 | K21: =IFERROR(J21/G21,0) -> 0 | L21: =IF(B21="","",IF(J21=MAX(SUMIFS($J$2:$J$200,$B$2:$B$200,B21,$C$2:$C$200,C21,$D$2:$D$200,"A"),SUMIFS($J$2:$J$200,$B$2:$B$200,B21,$C$2:$C$200,C21,$D$2:$D$200,"B")),"Current Winner",""))
... I200: =IFERROR(H200/G200,0) -> 0 | J200: =IFERROR(E200*H200,0) -> 0 | K200: =IFERROR(J200/G200,0) -> 0 | L200: =IF(B200="","",IF(J200=MAX(SUMIFS($J$2:$J$200,$B$2:$B$200,B200,$C$2:$C$200,C200,$D$2:$D$200,"A"),SUMIFS($J$2:$J$200,$B$2:$B$200,B200,$C$2:$C$200,C200,$D$2:$D$200,"B")),"Current Winner",""))

Sheet AB_Dashboard
A1: A/B Price Testing Dashboard
A3: Total Impressions | B3: =SUM(AB_TEST!G2:G200) -> 11100 | D3: How to use
A4: Total Purchases | B4: =SUM(AB_TEST!H2:H200) -> 519 | D4: 1) Add weekly price tests in AB_TEST.
A5: Total Revenue | B5: =SUM(AB_TEST!J2:J200) -> 17327.8 | D5: 2) Keep each test country/app split clean: A vs B.
A6: Avg Conversion | B6: =IFERROR(SUM(AB_TEST!H2:H200)/SUM(AB_TEST!G2:G200),0) -> 0.046756757 | D6: 3) Judge by Revenue first, then Conversion.
A7: Avg ARPU | B7: =IFERROR(SUM(AB_TEST!J2:J200)/SUM(AB_TEST!G2:G200),0) -> 1.5610631 | D7: 4) Run each variant at least 7 days if possible.
A8: Best Variant by Revenue | B8: {=INDEX(A13:A14,MATCH(MAX(E13:E14),E13:E14,0))} -> B | D8: 5) After winner is clear, update Play Store pricing.
A10: Variant Summary
A12: Variant | B12: Impressions | C12: Purchases | D12: Conversion | E12: Revenue | F12: ARPU | G12: Revenue Share | H12: Decision
A13: A | B13: =SUMIFS(AB_TEST!G2:G200,AB_TEST!D2:D200,A13) -> 5260 | C13: =SUMIFS(AB_TEST!H2:H200,AB_TEST!D2:D200,A13) -> 196 | D13: =IFERROR(C13/B13,0) -> 0.037262357 | E13: =SUMIFS(AB_TEST!J2:J200,AB_TEST!D2:D200,A13) -> 8282 | F13: =IFERROR(E13/B13,0) -> 1.5745247 | G13: =IFERROR(E13/SUM($E$13:$E$14),0) -> 0.47796027 | H13: =IF(E13=MAX($E$13:$E$14),"Winner","")
A14: B | B14: =SUMIFS(AB_TEST!G2:G200,AB_TEST!D2:D200,A14) -> 5840 | C14: =SUMIFS(AB_TEST!H2:H200,AB_TEST!D2:D200,A14) -> 323 | D14: =IFERROR(C14/B14,0) -> 0.055308219 | E14: =SUMIFS(AB_TEST!J2:J200,AB_TEST!D2:D200,A14) -> 9045.8 | F14: =IFERROR(E14/B14,0) -> 1.5489384 | G14: =IFERROR(E14/SUM($E$13:$E$14),0) -> 0.52203973 | H14: =IF(E14=MAX($E$13:$E$14),"Winner","") -> Winner
A17: Country / App Breakdown
A19: App | B19: Country | C19: Variant | D19: Impressions | E19: Purchases | F19: Conversion | G19: Revenue | H19: ARPU
A20: BLE Scanner | B20: TR | C20: A | D20: =SUMIFS(AB_TEST!G2:G200,AB_TEST!B2:B200,A20,AB_TEST!C2:C200,B20,AB_TEST!D2:D200,C20) -> 1200 | E20: =SUMIFS(AB_TEST!H2:H200,AB_TEST!B2:B200,A20,AB_TEST!C2:C200,B20,AB_TEST!D2:D200,C20) -> 48 | F20: =IFERROR(E20/D20,0) -> 0.04 | G20: =SUMIFS(AB_TEST!J2:J200,AB_TEST!B2:B200,A20,AB_TEST!C2:C200,B20,AB_TEST!D2:D200,C20) -> 1872 | H20: =IFERROR(G20/D20,0) -> 1.56
A21: BLE Scanner | B21: TR | C21: B | D21: =SUMIFS(AB_TEST!G2:G200,AB_TEST!B2:B200,A21,AB_TEST!C2:C200,B21,AB_TEST!D2:D200,C21) -> 1350 | E21: =SUMIFS(AB_TEST!H2:H200,AB_TEST!B2:B200,A21,AB_TEST!C2:C200,B21,AB_TEST!D2:D200,C21) -> 78 | F21: =IFERROR(E21/D21,0) -> 0.057777778 | G21: =SUMIFS(AB_TEST!J2:J200,AB_TEST!B2:B200,A21,AB_TEST!C2:C200,B21,AB_TEST!D2:D200,C21) -> 2262 | H21: =IFERROR(G21/D21,0) -> 1.6755556
A22: Secure Vault | B22: TR | C22: A | D22: =SUMIFS(AB_TEST!G2:G200,AB_TEST!B2:B200,A22,AB_TEST!C2:C200,B22,AB_TEST!D2:D200,C22) -> 900 | E22: =SUMIFS(AB_TEST!H2:H200,AB_TEST!B2:B200,A22,AB_TEST!C2:C200,B22,AB_TEST!D2:D200,C22) -> 32 | F22: =IFERROR(E22/D22,0) -> 0.035555556 | G22: =SUMIFS(AB_TEST!J2:J200,AB_TEST!B2:B200,A22,AB_TEST!C2:C200,B22,AB_TEST!D2:D200,C22) -> 1568 | H22: =IFERROR(G22/D22,0) -> 1.7422222
A23: Secure Vault | B23: TR | C23: B | D23: =SUMIFS(AB_TEST!G2:G200,AB_TEST!B2:B200,A23,AB_TEST!C2:C200,B23,AB_TEST!D2:D200,C23) -> 960 | E23: =SUMIFS(AB_TEST!H2:H200,AB_TEST!B2:B200,A23,AB_TEST!C2:C200,B23,AB_TEST!D2:D200,C23) -> 45 | F23: =IFERROR(E23/D23,0) -> 0.046875 | G23: =SUMIFS(AB_TEST!J2:J200,AB_TEST!B2:B200,A23,AB_TEST!C2:C200,B23,AB_TEST!D2:D200,C23) -> 1755 | H23: =IFERROR(G23/D23,0) -> 1.828125
A24: BLE Scanner | B24: IN | C24: A | D24: =SUMIFS(AB_TEST!G2:G200,AB_TEST!B2:B200,A24,AB_TEST!C2:C200,B24,AB_TEST!D2:D200,C24) -> 2400 | E24: =SUMIFS(AB_TEST!H2:H200,AB_TEST!B2:B200,A24,AB_TEST!C2:C200,B24,AB_TEST!D2:D200,C24) -> 96 | F24: =IFERROR(E24/D24,0) -> 0.04 | G24: =SUMIFS(AB_TEST!J2:J200,AB_TEST!B2:B200,A24,AB_TEST!C2:C200,B24,AB_TEST!D2:D200,C24) -> 4704 | H24: =IFERROR(G24/D24,0) -> 1.96
A25: BLE Scanner | B25: IN | C25: B | D25: =SUMIFS(AB_TEST!G2:G200,AB_TEST!B2:B200,A25,AB_TEST!C2:C200,B25,AB_TEST!D2:D200,C25) -> 2700 | E25: =SUMIFS(AB_TEST!H2:H200,AB_TEST!B2:B200,A25,AB_TEST!C2:C200,B25,AB_TEST!D2:D200,C25) -> 168 | F25: =IFERROR(E25/D25,0) -> 0.062222222 | G25: =SUMIFS(AB_TEST!J2:J200,AB_TEST!B2:B200,A25,AB_TEST!C2:C200,B25,AB_TEST!D2:D200,C25) -> 4872 | H25: =IFERROR(G25/D25,0) -> 1.8044444
A26: Secure Vault | B26: BR | C26: A | D26: =SUMIFS(AB_TEST!G2:G200,AB_TEST!B2:B200,A26,AB_TEST!C2:C200,B26,AB_TEST!D2:D200,C26) -> 760 | E26: =SUMIFS(AB_TEST!H2:H200,AB_TEST!B2:B200,A26,AB_TEST!C2:C200,B26,AB_TEST!D2:D200,C26) -> 20 | F26: =IFERROR(E26/D26,0) -> 0.026315789 | G26: =SUMIFS(AB_TEST!J2:J200,AB_TEST!B2:B200,A26,AB_TEST!C2:C200,B26,AB_TEST!D2:D200,C26) -> 138 | H26: =IFERROR(G26/D26,0) -> 0.18157895
A27: Secure Vault | B27: BR | C27: B | D27: =SUMIFS(AB_TEST!G2:G200,AB_TEST!B2:B200,A27,AB_TEST!C2:C200,B27,AB_TEST!D2:D200,C27) -> 830 | E27: =SUMIFS(AB_TEST!H2:H200,AB_TEST!B2:B200,A27,AB_TEST!C2:C200,B27,AB_TEST!D2:D200,C27) -> 32 | F27: =IFERROR(E27/D27,0) -> 0.038554217 | G27: =SUMIFS(AB_TEST!J2:J200,AB_TEST!B2:B200,A27,AB_TEST!C2:C200,B27,AB_TEST!D2:D200,C27) -> 156.8 | H27: =IFERROR(G27/D27,0) -> 0.18891566

Sheet AB_Setup
A1: AB Price Testing Setup
A2: Editable fields | B2: Meaning | C2: Example | D2: Notes
A3: App | B3: Which app / SKU you are testing | C3: BLE Scanner | D3: Use same naming in AB_TEST
A4: Country | B4: Play Store country code | C4: TR | D4: TR, US, IN, BR etc.
A5: Variant | B5: Price variant label | C5: A / B | D5: A = higher price, B = lower price recommended
A6: Impressions | B6: Paywall / purchase screen views | C6: 1000 | D6: Use Play Console / analytics
A7: Purchases | B7: Completed purchases | C7: 50 | D7: Use Play Console order data
A8: Revenue | B8: Auto calculated | D8: Price × Purchases
A9: Conversion | B9: Auto calculated | D9: Purchases ÷ Impressions
A10: Decision metric | B10: Primary winner metric | C10: Revenue | D10: Conversion alone is not enough
